Workbook

Sheet Sumário
A1: NORMATEL • Diagnóstico de Efetivo
A2: Fonte única: aba EFETIVO 11.05.2026 • Fórmulas vivas referenciando a base
B4: Visão Geral
B5: Esta planilha consolida o quadro de pessoal dos projetos 741 e 743 a partir da aba EFETIVO 11.05.2026. Todas as análises usam fórmulas dinâmicas (COUNTIFS, SUMPRODUCT) referenciando a base - basta atualizar a aba de efetivo (SIT, PROJETO, BASE, FUNÇÃO) e os números recalculam automaticamente. Filtros aplicados: somente registros com SIT = 'A' (ativo) ou SIT = 'D' (desligado). Identificação de projeto pela presença de '741' ou '743' na coluna PROJETO.
B7: ATIVOS 741 | G7: DESLIGADOS 741
B8: {=SUMPRODUCT(ISNUMBER(SEARCH("741",'EFETIVO 11.05.2026'!$H$2:$H$1919))*('EFETIVO 11.05.2026'!$G$2:$G$1919="A"))} -> 185 | G8: {=SUMPRODUCT(ISNUMBER(SEARCH("741",'EFETIVO 11.05.2026'!$H$2:$H$1919))*('EFETIVO 11.05.2026'!$G$2:$G$1919="D"))} -> 87
B10: ATIVOS 743 | G10: DESLIGADOS 743
B11: {=SUMPRODUCT(ISNUMBER(SEARCH("743",'EFETIVO 11.05.2026'!$H$2:$H$1919))*('EFETIVO 11.05.2026'!$G$2:$G$1919="A"))} -> 319 | G11: {=SUMPRODUCT(ISNUMBER(SEARCH("743",'EFETIVO 11.05.2026'!$H$2:$H$1919))*('EFETIVO 11.05.2026'!$G$2:$G$1919="D"))} -> 101
B13: ATIVOS 736 | G13: DESLIGADOS 736
B14: {=SUMPRODUCT(ISNUMBER(SEARCH("736",'EFETIVO 11.05.2026'!$H$2:$H$1919))*('EFETIVO 11.05.2026'!$G$2:$G$1919="A"))} -> 399 | G14: {=SUMPRODUCT(ISNUMBER(SEARCH("736",'EFETIVO 11.05.2026'!$H$2:$H$1919))*('EFETIVO 11.05.2026'!$G$2:$G$1919="D"))} -> 180
B16: ATIVOS 737 | G16: DESLIGADOS 737
B17: {=SUMPRODUCT(ISNUMBER(SEARCH("737",'EFETIVO 11.05.2026'!$H$2:$H$1919))*('EFETIVO 11.05.2026'!$G$2:$G$1919="A"))} -> 406 | G17: {=SUMPRODUCT(ISNUMBER(SEARCH("737",'EFETIVO 11.05.2026'!$H$2:$H$1919))*('EFETIVO 11.05.2026'!$G$2:$G$1919="D"))} -> 145
B19: TOTAL ATIVOS | G19: AFASTADOS (F/P/T/M)
B20: {=SUMPRODUCT(('EFETIVO 11.05.2026'!$G$2:$G$1919="A")*1)} -> 1309 | G20: {=SUMPRODUCT(('EFETIVO 11.05.2026'!$G$2:$G$1919="F")+('EFETIVO 11.05.2026'!$G$2:$G$1919="P")+('EFETIVO 11.05.2026'!$G$2:$G$1919="T")+('EFETIVO 11.05.2026'!$G$2:$G$1919="M"))} -> 89
B22: TOTAL REGS
B23: {=SUMPRODUCT((('EFETIVO 11.05.2026'!$G$2:$G$1919="A")+('EFETIVO 11.05.2026'!$G$2:$G$1919="D"))*1)} -> 1822
B26: Índice das Abas
B27: 1 | C27: Sumário | F27: Esta aba - KPIs gerais e índice
B28: 2 | C28: Análises 736 | F28: Mesma estrutura aplicada ao projeto 736 (614 registros)
B29: 3 | C29: Análises 737 | F29: Mesma estrutura aplicada ao projeto 737 (586 registros)
B30: 4 | C30: Análises 741 | F30: 5 seções com fórmulas vivas: KPIs, headcount por função, base, pontos únicos, movimentação histórica
B31: 5 | C31: Análises 743 | F31: Mesma estrutura aplicada ao projeto 743
B32: 6 | C32: EFETIVO 11.05.2026 | F32: FONTE ÚNICA. Atualize SIT, PROJETO, BASE, FUNÇÃO aqui e tudo recalcula automaticamente.
B33: 7 | C33: EFETIVO 20.10.2025 | F33: Base histórica para referência (não conectada às fórmulas)
B34: 8 | C34: 741 EFTV ATUALIZADO | F34: Base auxiliar do 741 (com classificação por Grupo/Área)
B35: 9 | C35: FG-ORGANOGRAMA-741 | F35: Organograma desenhado do projeto 741
B36: 10 | C36: FG-ORGANOGRAMA-743 | F36: Organograma desenhado do projeto 743
B37: 11 | C37: ORG. RESUMIDO-741 | F37: Versão executiva do organograma 741
B38: 12 | C38: ORG-RESUMIDO-743 | F38: Versão executiva do 743 (atualmente vazia, será preenchida)
B40: Notas Metodológicas
B41: -1 | C41: Todos os números desta planilha vêm de fórmulas que referenciam a aba EFETIVO 11.05.2026. Edições em SIT, PROJETO, BASE ou FUNÇÃO refletem nas análises imediatamente.
B42: -2 | C42: Identificação de projeto: SUMPRODUCT + ISNUMBER(SEARCH("741"...)) ou SEARCH("743"...) na coluna PROJETO. Funciona mesmo que o texto venha completo (ex.: 'PROJETO 741 - FACILITIES MULT CABIUNAS UTE/AE-SINTRAINDISTAL').
B43: -3 | C43: Filtro padrão: SIT = 'A' (ativo) ou SIT = 'D' (desligado). Outros valores (F/V/P/T/M) são ignorados nas seções de Headcount/Funções.
B44: -4 | C44: Movimentação histórica: o ano é extraído com YEAR() das colunas ADMISSÃO (entradas) e DEMISSÃO (saídas). Em 'D' já desligados, a contagem de ATIVO/DESLIGADO conta o registro pelo seu status final.
B45: -5 | C45: Pontos Únicos de Falha (Seção 4): funções com exatamente 1 ocupante ativo. Resultado dinâmico via INDEX/SMALL - quando uma função ganhar ou perder ocupante, a lista se ajusta sozinha.
B47: 🔒 Acesso Restrito
B48: As abas abaixo estão protegidas. Clique no botão correspondente e informe a senha para visualizar. Ao retornar ao Sumário, a aba é ocultada novamente automaticamente.
B50: Aba | C50: Descrição | F50: Acesso
B51: FG-ORGANOGRAMA-736 | C51: Organograma completo do projeto 736
B52: FG-ORGANOGRAMA-737 | C52: Organograma completo do projeto 737
B53: FG-ORGANOGRAMA-741 | C53: Organograma completo do projeto 741
B54: FG-ORGANOGRAMA-743 | C54: Organograma completo do projeto 743
B55: FG-ORGANOGRAMA-APOIO MACAÉ | C55: Organograma de apoio - Macaé
B56: Análises 736 | C56: Análises detalhadas do projeto 736
B57: Análises 737 | C57: Análises detalhadas do projeto 737
B58: Análises 741 | C58: Análises detalhadas do projeto 741
B59: Análises 743 | C59: Análises detalhadas do projeto 743
B60: EFETIVO | C60: Base atual de efetivo

Sheet FG-ORGANOGRAMA-741
CU4: Gerente Regional
CT5: DIEGO CASTELUBER BASSETTI
CT10: 0.5 | CU10: Gerente de Facilities | DU10: Engenheiro de Segurança | FF10: Gerente Administrativo
CT11: JOSE DANIEL SILVA SANTOS JUNIOR | DT11: RODRIGO RODRIGUES | FE11: EVANDO GERONIMO
AS12: =SUM(AJ13+AJ15) -> 1 | CM12: =SUM(CD13+CD16+CD18+CD20+CD22) -> 5
AJ13: 0.5 | AK13: Assistente Administrativo | BG13: 0.5 | BH13: Supervisor Administrativo | CD13: 1 | CE13: Supervisor de Planejamento
AJ14: GABRIEL SERAFIM DA CRUZ | BG14: MAICON MONTEIRO | CD14: PEDRO PAULO TAVARES BARBOSA MACHADO | EP14: =SUM(DT20+DK24+DK26+DT24+DT26+DT28+DT30+DT32+EC24+EC26+EC28+DT17) -> 9.5 | FE14: =SUM(EV18+EV20) -> 2 | FW14: =SUM(FN20+FN22+FN24) -> 3
AJ15: 0.5 | AK15: Assistente Administrativo | EH15: Tecnico de Enfermagem | EW15: Supervisora Administrativo | FO15: Supervisor Administrativo
AJ16: RAPHAEL DURAO SENOS DE CAMPOS | CD16: 1 | CE16: Planejador | EG16: CLEITON ORILIO LIRA DA SILVA
BI17: =SUM(AZ18+AZ22+AZ24+AZ26+AZ28+AZ30) -> 5 | BW17: =SUM(BN18+BN20+BN22+BN24+BN26) -> 4.5 | CD17: TAIANE TEIXEIRA DA SILVA DE OLIVEIRA | DT17: 0.5 | DU17: Supervisora de SMS
AP18: Software | AZ18: 1 | BA18: Assistente de Logistica I | BN18: 1 | BO18: Comprador - Normatel | CD18: 1 | CE18: Planejador | DT18: DANIELE LIMA PONTES | EV18: 1 | EW18: Auxiliar Administrativo | FN18: 1 | FO18: Almoxarife
AZ19: IZABELLA DE JESUS LIMA | BN19: DIEGO GREGORIO HESPANHOL | CD19: ALESSANDRA DA SILVA MARIANO | EV19: MICHELE VIEIRA SOUZA | FN19: ADENILSON LUIZ DA SILVA
AZ20: 1 | BA20: Assistente de Logistica I | BN20: 1 | BO20: Comprador - Normatel | CD20: 1 | CE20: Assistente Administrativo | DT20: 0.5 | DU20: Tecnico de Segurança II | EV20: 1 | EW20: Auxiliar Administrativo | FN20: 1 | FO20: Almoxarife
AZ21: THAINANDA DOS SANTOS SOUZA LEONE | BN21: VITOR DANIEL RODRIGUES DE CARVALHO MATOS | CD21: KARINY CORREA REIS | DT21: HERALDO JULIO GREGORIO DA SILVA | EV21: JULIA FRANCO SOUZA | FN21: VANESSA DE OLIVEIRA MACHARETE
AZ22: 1 | BA22: Motorista | BN22: 1 | BO22: Comprador - Petrobras | CD22: 1 | CE22: Assistente Administrativo | FN22: 1 | FO22: Auxiliar de Almoxarifado
AZ23: GERALDO ALVES BEZERRA | BN23: IONE DE FREIRAS | CD23: EDUARDA MANHAES VELASCO | DK23: DOCUMENTAÇÃO | DT23: ÁREA / DOCUMENTAÇÃO | EC23: INSPEÇÃO | FB23: RH | FN23: WEBERSON DA PAIXAO DE ARAUJO SILVA
AZ24: 1 | BA24: Motorista | BN24: 1 | BO24: Comprador - Petrobras | DK24: 1 | DL24: Auxiliar de SMS | DT24: 1 | DU24: Tecnico de Segurança | EC24: 0.5 | ED24: Tecnico de Segurança | FN24: 1 | FO24: Auxiliar de Almoxarifado
AZ25: JOABSON DE OLIVEIRA FERREIRA | BN25: NIVIA RANGEL | CJ25: Planejamento | DK25: IZADORA MONTEIRO CARVALHO | DT25: FILIPE DE PAULA DA SILVA | EC25: RAFAELA GAUDENCIO MAXIMO | FN25: DALISSON CARDOSO FERREIRA
AZ26: 1 | BA26: Motorista | BN26: 0.5 | BO26: Comprador - Petrobras | DK26: 1 | DL26: Auxiliar de SMS | DT26: 1 | DU26: Tecnico de Segurança | EC26: 0.5 | ED26: Tecnico de Segurança
AZ27: CLAUDIO MONTEIRO ANDRE | BN27: CRISTIANO PAIVA | DK27: LAURAH HECTH FELIX | DT27: MARIA FERNANDA SILVA SANTOS | EC27: SANDRO AUGUSTO SOUZA DO COUTO | FT27: Suprimentos
AZ28: 0.5 | BA28: Operador de Retroesvacadeira | DT28: 1 | DU28: Tecnico de Segurança | EC28: 0.5 | ED28: Tecnico de Segurança
AZ29: VAGA | BT29: Compras | DT29: VAGA | EC29: MATEUS HIPOLITO CHAGAS RIBEIRO
AZ30: 0.5 | BA30: Motorista Munckeiro | DT30: 1 | DU30: Tecnico de Segurança
AZ31: UENDER DA SILVA GOMES | DT31: LEONARDO LOUSA DA SILVA
DT32: 1 | DU32: Tecnico de Segurança
BF33: Logística | DT33: MARIA LUIZA DE FATIMA ALFARO
EM35: SMS
CT40: 1 | CU40: Preposto
CT41: ALEXANDRO DOS REIS JUNIOR
CT43: 1 | CU43: Coordenador de Manutenção
CT44: ANA CAROLINA RODRIGUES
CT48: AREAS EXTERNAS
AJ55: =SUM(T56+M62+M64+M66+M68+AA62+AA64+AA66+AA68+AA70+AA72+AA74) -> 12 | CO55: =SUM(BO59+AX64+AX66+BH64+BH66+BV64+BV66+CF64+AX76+AX78+AX80+AX82+AX84+AX86+AX88+AX90+BH76+BH78+BV76+CF76+CF78+CF80+CF82+CF84+CF86+CF88+BO56+BH68+BV80+BV78+BH80+BH82) -> 25.5
T56: 1 | U56: Supervisor de Eletrica | BO56: 0.5 | BP56: Engenheira Civil | DT56: 0.5 | DU56: Engenheiro Agronomo
T57: RODRIGO COTA SANTOS | BO57: KARLA KOPPE BATISTA | DT57: GUSTAVO FABRI BASTOS
BO59: 1 | BP59: Supervisor de Manutencao Civil | DX59: =SUM(DJ60+DJ63+DE66+DE68+DE70+DE72+DO142+DE76+DE78+DE80+DE82+DO66+DO68+DO70+DO72+DO74+DO76+DO78+DO80+DO82) -> 20 | EK59: =SUM(EB60+EB63+EB66+EB68+EB70+EB72+EB74+EB76+EB78+EB80+EB82+EB84+EB86+EB88+EB90+EB92) -> 15.5
BO60: ARVIDO BALANIUK JUNIOR | DJ60: 1 | DK60: Supervisor de Áreas Verdes | EB60: 0.5 | EC60: Supervisor de Limpeza
M61: MECANICA | AA61: ELETRICA | DJ61: JEFFERSON DE SOUZA CUNHA | EB61: TIAGO DIOGO SANTOS DA COSTA
M62: 1 | N62: Tecnico de Mecanica | AA62: 1 | AB62: Tecnico em Eletrotecnica
M63: GEFERSON RODRIGUES SIMPLICIO | AA63: FERNANDO SILVA ALVARENGA | AX63: ANDAIMES | BH63: APOIO TÉCNICO | BV63: HIDRAULICA | CF63: DRONE | DJ63: 1 | DK63: Encarregado de Áreas Verdes | EB63: 1 | EC63: Encarregado de Limpeza
M64: 1 | N64: Mecanico | AA64: 1 | AB64: Eletricista Predial | AX64: 1 | AY64: Montador de Andaimes | BH64: 1 | BI64: Planejador | BV64: 1 | BW64: Artífice | CF64: 0.5 | CG64: Operador de RPAS | DJ64: BRENO RODRIGUES CINQUINE | EB64: CLEIDIANE CONCEICAO SANTOS
M65: VAGA | AA65: ESTEVAO DIANINI CUNHA CRUZ DE CARVALHO | AX65: EM ANDAMENTO | BH65: LEONARDO LUCAS SILVA PINHEIRO | BV65: KISEPP CLAYTON MENDES DOS SANTOS | CF65: DIEGO WAGNER MARTINS DA SILVA
M66: 1 | N66: Ajudante de Mecanica Predial | AA66: 1 | AB66: Eletricista Predial | AX66: 1 | AY66: Montador de Andaimes | BH66: 1 | BI66: Técnico de Edificacoes | BV66: 1 | BW66: Artífice | DE66: 1 | DF66: Jardineiro | DO66: 1 | DP66: Operador de Rocadeira | EB66: 1 | EC66: Auxiliar de Serviços Gerais - 2x2
M67: JOAO FELIPE DE OLIVEIRA ALMEIDA | AA67: LEONARDO BEZERRA DE SOUSA PAIVA | AX67: ROEMILSON LOPES RIBEIRO | BH67: LUIS PAULO SANTOS DA SILVA | BV67: JORGE LUIZ FERREIRA DA SILVA | DE67: CLEDEILSON BORGES MARCELINO | DO67: ANTONIO VEIGA POSES | EB67: VAGA
M68: 1 | N68: Ajudante de Eletromecanica Predial | AA68: 1 | AB68: Ajudante de Eletrica Predial | BH68: 1 | BI68: Assistente Administrativo | DE68: 1 | DF68: Auxiliar de Jardinagem | DO68: 1 | DP68: Operador de Rocadeira | EB68: 1 | EC68: Auxiliar de Serviços Gerais - 2x2
M69: FILIPE LEITE DA CRUZ | AA69: BRUNO SACRAMENTO SANTANA | BH69: BARBARA SALDANHA SANTOS | DE69: DANILO CINQUINE CRISOSTOMO | DO69: CARLOS HENRIQUE CRUZ MARIANO DE OLIVEIRA | EB69: ERICA SOUZA DE JESUS PORTELA
AA70: 1 | AB70: Ajudante de Eletrica Predial | DE70: 1 | DF70: Auxiliar de Jardinagem | DO70: 1 | DP70: Operador de Rocadeira | EB70: 1 | EC70: Auxiliar de Serviços Gerais - 2x2
AA71: CAUA SILVA DE PAULA | DE71: CLAUDECIR OLIVEIRA SANTOS | DO71: LUAN ADILSON DE SOUZA CUNHA | EB71: TANIA APARECIDA BARRETO
AA72: 1 | AB72: Ajudante de Eletrica Predial | DE72: 1 | DF72: Auxiliar de Jardinagem | DO72: 1 | DP72: Operador de Rocadeira | EB72: 1 | EC72: Auxiliar de Serviços Gerais
AA73: VAGA | DE73: JEFFERSON MARQUES PEREIRA | DO73: JOSIMAR CORDEIRO PEREIRA | EB73: WANDERNEY ENCARNACAO DOS SANTOS
AA74: 1 | AB74: Ajudante de Eletrica Predial | DE74: 1 | DF74: Auxiliar de Jardinagem | DO74: 1 | DP74: Operador de Rocadeira | EB74: 1 | EC74: Auxiliar de Serviços Gerais
AA75: NATAN SAMUEL MONTEIRO FORTES | AX75: PINTURA | BH75: MARCENARIA | BV75: CALDEIRARIA | CF75: ALVENARIA | DE75: VAGA | DO75: CARLOS ANDRE DE OLIVEIRA | EB75: CARLOS DANIEL BARRETO VASCO DA GLORIA
AX76: 0.5 | AY76: Pintor Industrial | BH76: 1 | BI76: Artífice | BV76: 1 | BW76: Caldeireiro | CF76: 1 | CG76: Artífice | DE76: 1 | DF76: Auxiliar de Jardinagem | DO76: 1 | DP76: Operador de Rocadeira | EB76: 1 | EC76: Auxiliar de Serviços Gerais
AF77: Manutenção | AX77: ISMAEL MACHADO ALMEIDA | BH77: JOAO PAULO GEAMONOND PINTO CHAVES | BV77: LEONARDO LUCIDIO DOS SANTOS | CF77: WESLEY FERREIRA DOS SANTOS | DE77: MATEUS SANT ANA COUTINHO | DO77: GABRIEL FERNANDES DOS SANTOS | EB77: EM ANDAMENTO
AX78: 0.5 | AY78: Pintor | BH78: 1 | BI78: Artífice | BV78: 1 | BW78: Auxiliar de Manut. em Caldeiraria | CF78: 1 | CG78: Artífice | DE78: 1 | DF78: Auxiliar de Jardinagem | DO78: 1 | DP78: Operador de Rocadeira | EB78: 1 | EC78: Auxiliar de Serviços Gerais
AX79: AMELIO SILVINO MAIA DA SILVA | BH79: RUBINEY DOS SANTOS MARTINS | BV79: EM ANDAMENTO | CF79: GILSON CARVALHO DOS SANTOS | DE79: MARCIO CLAUDIO ALVES DO NASCIMENTO | DO79: VAGA | EB79: DAMARYS ANDRE DO AMARAL SOUZA
AX80: 0.5 | AY80: Ajudante de Pintura | BH80: 1 | BI80: Artífice | CF80: 1 | CG80: Artífice | DE80: 1 | DF80: Auxiliar de Jardinagem | DO80: 1 | DP80: Operador de Rocadeira | EB80: 1 | EC80: Auxiliar de Serviços Gerais
AX81: GUILHERME OLIVEIRA FERREIRA | BH81: EM ANDAMENTO | CF81: ISAIAS DO ROSARIO | DE81: WELLINGTON ALVARENGA MENDES | DO81: VAGA | EB81: FABIOLA LOPES DA SILVA ANDRADE
AX82: 0.5 | AY82: Ajudante de Pintura | BH82: 1 | BI82: Artífice | CF82: 1 | CG82: Artífice | DE82: 1 | DF82: Auxiliar de Jardinagem | DO82: 1 | DP82: Operador de Rocadeira | EB82: 1 | EC82: Auxiliar de Serviços Gerais
AX83: DIOGO NOGUEIRA DE ALMEIDA | BH83: EM ANDAMENTO | CF83: LUIANDERSON DE SOUZA ROCHA | DE83: YURI DIAS DOS SANTOS | DO83: VAGA | EB83: JOSEFA DOS SANTOS JOVINO
AX84: 0.5 | AY84: Pintor Industrial | CF84: 1 | CG84: Auxiliar de Manutencao Civil | EB84: 1 | EC84: Auxiliar de Serviços Gerais
AX85: VAGA | CF85: VAGA | DU85: Àreas Verdes | EB85: THALINE REIS ANUNCIACAO
AX86: 0.5 | AY86: Ajudante de Pintura | CF86: 1 | CG86: Auxiliar de Manutencao Civil | EB86: 1 | EC86: Auxiliar de Serviços Gerais
AX87: VAGA | CF87: VAGA | EB87: THAISE REIS ANUNCIACAO
AX88: 0.5 | AY88: Ajudante de Pintura | CF88: 1 | CG88: Auxiliar de Manutencao Civil | EB88: 1 | EC88: Auxiliar de Serviços Gerais
AX89: VAGA | CF89: VAGA | EB89: VALDENEIDE DOS SANTOS
EB90: 1 | EC90: Auxiliar de Serviços Gerais
CL91: Civil | EB91: UILSON JANES BATISTA
EB92: 1 | EC92: Auxiliar de Serviços Gerais
EB93: LEANDRA EVANGELISTA DOS SANTOS MACHADO
EH95: Limpeza
CT98: UTE-TMA
AJ105: =SUM(T106+T109+N115+N117+N119+N121+Z115+Z117+Z119+Z121+Z123+Z125+Z127+N123+N125) -> 15 | CP105: =SUM(AY118+AY120+BW118+BW120+CG118+BJ127+BJ129+BJ131+BJ133+BI118+BI120+BV127+BV129+BV131+BV133+BP106+BP108+BZ112+BP114+BV135+BV137+BV139+BV141+BV143+BJ135+BJ137+BJ139+BJ141+BJ143+BV145+BV147+BV149+BV151+BV153+BV155+BV157+BV159+BF112+BP112+BP109) -> 35.5
T106: 1 | U106: Supervisor de Manutenção II | BP106: 0.5 | BQ106: Engenheira Civil | DT106: 0.5 | DU106: Engenheiro Agronomo
T107: LAFAETE DAUMAS BRAGA DE MORAES | BP107: KARLA KOPPE BATISTA | DT107: GUSTAVO FABRI BASTOS
T109: 1 | U109: Supervisor de Eletrica | BP109: 1 | BQ109: Supervisor de Manutencao Civil | DX109: =SUM(DJ110+DJ113+DE116+DE118+DE120+DE122+DE124+DE126+DE128+DE130+DE132+DE134+DE136+DE138+DE140+DE144+DE146+DE148+DE142+DO116+DO118+DO120+DO122+DO124+DO126+DO128+DO130+DO132+DO134+DO136+DO138+DO140+#REF!) -> #REF! | EK109: =SUM(EB110+EB113+EB116+EB118+EB120+EB122+EB124+EB126+EB128+EB130+EB132+EB134+EB136+EB138+EB140+EB142) -> 15.5
T110: HUGO GABRIEL DOS SANTOS | BP110: BRUNO DA COSTA ROCHA | DJ110: 1 | DK110: Supervisor de Áreas Verdes | EB110: 0.5 | EC110: Supervisor de Limpeza
DJ111: EDUARDO SALDANHA SANTOS | EB111: TIAGO DIOGO SANTOS DA COSTA
BF112: 1 | BG112: Cadista | BP112: 1 | BQ112: Encarregado Civil | CA112: Tecnico de Edificacoes
BF113: MAIZA DA SILVA DE SOUZA | BP113: CELIO PERES | BZ113: SUSPENSA | DJ113: 1 | DK113: Encarregado de Áreas Verdes | EB113: 1 | EC113: Encarregado de Limpeza
N114: MECÂNICA | Z114: ELÉTRICA | DJ114: FILIPE GOMES DOS SANTOS DE LIMA | EB114: RAYSSA DE SOUZA DA SILVA
N115: 1 | O115: Mecanico | Z115: 1 | AA115: Tecnico em Eletrotecnica
N116: ROGERIO QUEIROZ DE DEUS | Z116: MARCELO MAGALHAES CHAVES | DE116: 1 | DF116: Jardineiro | DO116: 1 | DP116: Operador de Roçadeira | EB116: 1 | EC116: Auxiliar de Serviços Gerais
N117: 1 | O117: Mecanico | Z117: 1 | AA117: Eletricista Predial | AY117: ANDAIMES | BI117: CALDEIRARIA | BW117: HIDRÁULICA | CG117: DRONE | DE117: ALISOM DE OLIVEIRA ROSA | DO117: ALCIMAR SILVA MONTEIRO | EB117: ALICE ALVES DINIZ
N118: CRISTIANO DA COSTA SAMPAYO | Z118: CLAUDENIR PEREIRA LIMA | AY118: 1 | AZ118: Montador de Andaimes | BI118: 1 | BJ118: Caldeireiro | BW118: 1 | BX118: Artífice | CH118: Operador de RPAS | DE118: 1 | DF118: Jardineiro | DO118: 1 | DP118: Operador de Roçadeira | EB118: 1 | EC118: Auxiliar de Serviços Gerais
N119: 1 | O119: Mecanico | Z119: 1 | AA119: Eletricista Predial | AY119: FELIPE LOPES FERREIRA | BI119: JEFE DO CARMO CABRAL | BW119: JOSE RIBAMAR NOVAIS PEREIRA | CG119: DIEGO WAGNER MARTINS DA SILVA | DE119: JOSE APARICIO PEREIRA BEMBEM | DO119: ANDERSON ALVES DINIZ MARQUES | EB119: CARMEM LUCIA BARBOZA DE OLIVEIRA QUINTANILHA
N120: EDSON ROBERTO CARVALHO DE OLIVEIRA | Z120: GABRIEL DOS SANTOS AZEVEDO MACHADO | AY120: 1 | AZ120: Montador de Andaimes | BI120: 1 | BJ120: Ajudante de Caldeiraria | BW120: 1 | BX120: Artífice | DE120: 1 | DF120: Auxiliar de Jardinagem | DO120: 1 | DP120: Operador de Roçadeira | EB120: 1 | EC120: Auxiliar de Serviços Gerais
N121: 1 | O121: Mecanico de Refrigeracao I | Z121: 1 | AA121: Ajudante de Eletromecanica Predial | AY121: LUCAS ALVES SILVA | BI121: WELLINGTON DE MORAES XAVIER JARDIM | BW121: VALDECIR DA SILVA | DE121: ELYARDO DUTRA RIBEIRO MACHADO | DO121: ESDRAS ANDRE DE OLIVEIRA | EB121: DEBORA DE OLIVEIRA
N122: FRANCISCO DE ASSIS DOS SANTOS DA COSTA | Z122: THIAGO CORREA SIQUEIRA | DE122: 1 | DF122: Auxiliar de Jardinagem | DO122: 1 | DP122: Operador de Roçadeira | EB122: 1 | EC122: Auxiliar de Serviços Gerais
N123: 1 | O123: Ajudante de Mecanica Predial | Z123: 1 | AA123: Ajudante de Eletromecanica Predial | DE123: FERNANDO DA SILVA DE SOUZA | DO123: GILSON DE AZEVEDO NEVES SOARES | EB123: EDIR DA SILVA FERNANDES LEONEL
N124: GAUDENCIO CARLOS DOS SANTOS | Z124: KENNY GABRIEL RIBEIRO TEIXEIRA | DE124: 1 | DF124: Auxiliar de Jardinagem | DO124: 1 | DP124: Operador de Roçadeira | EB124: 1 | EC124: Auxiliar de Serviços Gerais
N125: 1 | O125: Ajudante de Mecanica Predial | Z125: 1 | AA125: Ajudante de Eletrica Predial | DE125: IGOR BRENNER ALVES | DO125: HEBRAIA SILVA ANDRADE | EB125: VAGA
N126: MATHEUS ANDRE CARDIM | Z126: LEONARDO STODUTO MUNIZ | BJ126: PINTURA | BV126: ALVENARIA | DE126: 1 | DF126: Auxiliar de Jardinagem | DO126: 1 | DP126: Operador de Roçadeira | EB126: 1 | EC126: Auxiliar de Serviços Gerais
Z127: 1 | AA127: Ajudante de Eletromecanica Predial | BJ127: 1 | BK127: Pintor Industrial | BV127: 1 | BW127: Artífice | DE127: JADER MADUREIRA DA SILVA | DO127: ICARO EVANGELISTA DALTI ALBINO | EB127: FABRICIO MENEZES DE SOUZA
Z128: VAGA | BJ128: REINALDO VIRGULINO | BV128: GENILSON SANTANA DA CONCEICAO | DE128: 1 | DF128: Auxiliar de Jardinagem | DO128: 1 | DP128: Operador de Roçadeira | EB128: 1 | EC128: Auxiliar de Serviços Gerais
BJ129: 1 | BK129: Artífice | BV129: 1 | BW129: Artífice | DE129: LUCAS DAUMAS BRAGA DE MORAES | DO129: JOSE DO CARMO MORAES | EB129: ITAMARA DE FREITAS DA SILVA
AG130: Manutenção | BJ130: ANDERSON SOUZA DA SILVA | BV130: LEANDRO RIBEIRO DA COSTA | DE130: 1 | DF130: Auxiliar de Jardinagem | DO130: 1 | DP130: Operador de Roçadeira | EB130: 1 | EC130: Auxiliar de Serviços Gerais
BJ131: 1 | BK131: Artífice | BV131: 1 | BW131: Artífice | DE131: PAULO VICTOR GOMES RODRIGUES MANHAES | DO131: PAULO SERGIO ROCHA DOS SANTOS | EB131: JOANITA VICENTE VIANA FLORES
BJ132: CARLOS ANTONIO DOS SANTOS GENEROSO | BV132: CARLOS AUGUSTO POSES DO NASCIMENTO | DE132: 1 | DF132: Auxiliar de Jardinagem | DO132: 1 | DP132: Operador de Roçadeira | EB132: 1 | EC132: Auxiliar de Serviços Gerais
BJ133: 1 | BK133: Artífice | BV133: 1 | BW133: Artífice | DE133: THALISSON LEANDRO DA SILVA | DO133: THELWIS DOS SANTOS SILVA | EB133: QUELEN MARCIA GREGORIO DA SILVA
...

Sheet ORG. RESUMIDO-741
X3: Gerente Regional
W4: DIEGO CASTELUBER BASSETTI
W7: 0.5 | X7: Gerente de Facilites | AX7: Gerente de SMS | BK7: Gerente ADM
W8: JOSE DANIEL SILVA SANTOS JUNIOR | AW8: RODRIGO CESAR RODRIGUES | BJ8: EVANDO GERONIMO
P10: EQUIPE ESTRATÉGICA
P11: GERÊNCIA DE INTEGRAÇÃO | AX11: QUALIDADE, SAÚDE SEGURANÇA E MEIO AMBIENTE | BB11: EQUIPE DE SAUDE | BK11: RH | BO11: ALMOXARIFADO
W15: ='FG-ORGANOGRAMA-741'!BG13 -> 0.5 | X15: Supervisor Administrativo | AG15: ='FG-ORGANOGRAMA-741'!CD13 -> 1 | AH15: Supervisora de Planejamento
W16: MAICON MONTEIRO | AG16: PEDRO PAULO TAVARES BARBOSA MACHADO
P18: SOFTWARE | X18: LOGÍSTICA | AA18: COMPRAS | AJ18: PLANEJAMENTO
AX21: ='FG-ORGANOGRAMA-741'!EP14 -> 9.5 | BB21: 0 | BK21: ='FG-ORGANOGRAMA-741'!EV18 -> 1 | BO21: ='FG-ORGANOGRAMA-741'!FW14 -> 3
P28: ='FG-ORGANOGRAMA-741'!AS12 -> 1 | X28: ='FG-ORGANOGRAMA-741'!AZ22+'FG-ORGANOGRAMA-741'!AZ24+'FG-ORGANOGRAMA-741'!AZ26+'FG-ORGANOGRAMA-741'!AZ28+'FG-ORGANOGRAMA-741'!AZ30 -> 4 | AA28: =SUM('FG-ORGANOGRAMA-741'!BI17,'FG-ORGANOGRAMA-741'!BW17) -> 9.5 | AJ28: ='FG-ORGANOGRAMA-741'!CM12 -> 5
AO33: 1 | AP33: Preposto
AO34: ALEXANDRO DOS REIS JUNIOR
AO36: 1 | AP36: Coordenador de Manutenção
AO37: ANA CAROLINA RODRIGUES
T40: Áreas Externas | AQ40: Tapera | BN40: UTE-TMA
H44: 0.5 | I44: Supervisor de Manutenção II | R44: 0.5 | S44: Engenheiro Civil | AB44: 0.5 | AC44: Engenheiro Agronomo | AP44: Supervisor de Manutenção II | BB44: 0.5 | BC44: Supervisor de Manutenção II | BL44: 0.5 | BM44: Engenheiro Civil | BV44: 0.5 | BW44: Engenheiro Agronomo
H45: LAFAETE DAUMAS BRAGA DE MORAES | R45: KARLA KOPPE BATISTA | AB45: GUSTAVO FABRI BASTOS | AO45: LAFAETE DAUMAS BRAGA DE MORAES | BB45: LAFAETE DAUMAS BRAGA DE MORAES | BL45: KARLA KOPPE BATISTA | BV45: GUSTAVO FABRI BASTOS
K47: MANUTENÇÃO | U47: CIVIL | AD47: ÁREAS VERDES | AG47: CONS. LIMPEZA | AP47: ÁREAS VERDES | AS47: CONS. LIMPEZA | BE47: MANUTENÇÃO | BO47: CIVIL | BX47: ÁREAS VERDES | CA47: CONS. LIMPEZA
K57: ='FG-ORGANOGRAMA-741'!AJ55 -> 12 | U57: ='FG-ORGANOGRAMA-741'!CO55 -> 25.5 | AD57: ='FG-ORGANOGRAMA-741'!DX59 -> 20 | AG57: ='FG-ORGANOGRAMA-741'!EK59 -> 15.5 | AP57: ='FG-ORGANOGRAMA-741'!CV184 -> 2 | AS57: ='FG-ORGANOGRAMA-741'!DH184 -> 1 | BE57: ='FG-ORGANOGRAMA-741'!AJ105 -> 15 | BO57: ='FG-ORGANOGRAMA-741'!CP105 -> 35.5 | BX57: ='FG-ORGANOGRAMA-741'!DX109 -> #REF! | CA57: ='FG-ORGANOGRAMA-741'!EK109 -> 15.5
AM64: TOTAL | AQ64: =SUM(W3+W7+M15+W15+AG15+P28+X28+AA28+AJ28+AW7+AX21+BB21+BJ7+BK21+BO21+AO33+AO36+H44+R44+AB44+K57+U57+AD57+AG57+AO44+AP57+AS57+BB44+BE57+BL44+BO57+BV44+BX57+CA57) -> #REF!

Sheet Análises 741
A1: NORMATEL • Análises Projeto 741
A2: Cálculos dinâmicos sobre EFETIVO 11.05.2026 - Situações (SIT): A=Ativo, D=Desligado, F=Férias, P=INSS, T=Acidente de Trabalho, M=Serviço Militar
B4: 1. Indicadores do Projeto 741
B5: Total de registros vinculados ao 741 (todas situações) | C5: {=SUMPRODUCT(ISNUMBER(SEARCH("741",'EFETIVO 11.05.2026'!$H$2:$H$712))*(('EFETIVO 11.05.2026'!$G$2:$G$712="A")+('EFETIVO 11.05.2026'!$G$2:$G$712="D")+('EFETIVO 11.05.2026'!$G$2:$G$712="F")+('EFETIVO 11.05.2026'!$G$2:$G$712="P")+('EFETIVO 11.05.2026'!$G$2:$G$712="T")+('EFETIVO 11.05.2026'!$G$2:$G$712="M")))} -> 278
B6: Ativos no 741 | C6: {=SUMPRODUCT(ISNUMBER(SEARCH("741",'EFETIVO 11.05.2026'!$H$2:$H$712))*('EFETIVO 11.05.2026'!$G$2:$G$712="A"))} -> 185
B7: Desligados no 741 | C7: {=SUMPRODUCT(ISNUMBER(SEARCH("741",'EFETIVO 11.05.2026'!$H$2:$H$712))*('EFETIVO 11.05.2026'!$G$2:$G$712="D"))} -> 87
B8: % de turnover (desligados / total) | C8: =IFERROR(C7/C5,0) -> 0.31294964
B9: Afastados no 741 (F+P+T+M) | C9: {=SUMPRODUCT(ISNUMBER(SEARCH("741",'EFETIVO 11.05.2026'!$H$2:$H$712))*(('EFETIVO 11.05.2026'!$G$2:$G$712="F")+('EFETIVO 11.05.2026'!$G$2:$G$712="P")+('EFETIVO 11.05.2026'!$G$2:$G$712="T")+('EFETIVO 11.05.2026'!$G$2:$G$712="M")))} -> 6
B10: Funções distintas (ativos) | C10: {=SUMPRODUCT(--(C14:C71>0))} -> 50
B11: 2. Colaboradores por Função (Ativos / Desligados / Afastados)
B13: Função | C13: Ativos | D13: Desligados | E13: % do total ativos | F13: Afastados
B14: AJUDANTE DE CALDEIRARIA | C14: {=SUMPRODUCT(ISNUMBER(SEARCH("741",'EFETIVO 11.05.2026'!$H$2:$H$712))*('EFETIVO 11.05.2026'!$G$2:$G$712="A")*('EFETIVO 11.05.2026'!$C$2:$C$712="AJUDANTE DE CALDEIRARIA"))} -> 0 | D14: {=SUMPRODUCT(ISNUMBER(SEARCH("741",'EFETIVO 11.05.2026'!$H$2:$H$712))*('EFETIVO 11.05.2026'!$G$2:$G$712="D")*('EFETIVO 11.05.2026'!$C$2:$C$712="AJUDANTE DE CALDEIRARIA"))} -> 1 | E14: =IFERROR(C14/$C$6,0) -> 0 | F14: {=SUMPRODUCT(ISNUMBER(SEARCH("741",'EFETIVO 11.05.2026'!$H$2:$H$712))*(('EFETIVO 11.05.2026'!$G$2:$G$712="F")+('EFETIVO 11.05.2026'!$G$2:$G$712="P")+('EFETIVO 11.05.2026'!$G$2:$G$712="T")+('EFETIVO 11.05.2026'!$G$2:$G$712="M"))*('EFETIVO 11.05.2026'!$C$2:$C$712=$B14))} -> 0
B15: AJUDANTE DE ELETRICA PREDIAL | C15: {=SUMPRODUCT(ISNUMBER(SEARCH("741",'EFETIVO 11.05.2026'!$H$2:$H$712))*('EFETIVO 11.05.2026'!$G$2:$G$712="A")*('EFETIVO 11.05.2026'!$C$2:$C$712="AJUDANTE DE ELETRICA PREDIAL"))} -> 4 | D15: {=SUMPRODUCT(ISNUMBER(SEARCH("741",'EFETIVO 11.05.2026'!$H$2:$H$712))*('EFETIVO 11.05.2026'!$G$2:$G$712="D")*('EFETIVO 11.05.2026'!$C$2:$C$712="AJUDANTE DE ELETRICA PREDIAL"))} -> 0 | E15: =IFERROR(C15/$C$6,0) -> 0.021621622 | F15: {=SUMPRODUCT(ISNUMBER(SEARCH("741",'EFETIVO 11.05.2026'!$H$2:$H$712))*(('EFETIVO 11.05.2026'!$G$2:$G$712="F")+('EFETIVO 11.05.2026'!$G$2:$G$712="P")+('EFETIVO 11.05.2026'!$G$2:$G$712="T")+('EFETIVO 11.05.2026'!$G$2:$G$712="M"))*('EFETIVO 11.05.2026'!$C$2:$C$712=$B15))} -> 0
B16: AJUDANTE DE ELETROMECANICA PREDIAL | C16: {=SUMPRODUCT(ISNUMBER(SEARCH("741",'EFETIVO 11.05.2026'!$H$2:$H$712))*('EFETIVO 11.05.2026'!$G$2:$G$712="A")*('EFETIVO 11.05.2026'!$C$2:$C$712="AJUDANTE DE ELETROMECANICA PREDIAL"))} -> 3 | D16: {=SUMPRODUCT(ISNUMBER(SEARCH("741",'EFETIVO 11.05.2026'!$H$2:$H$712))*('EFETIVO 11.05.2026'!$G$2:$G$712="D")*('EFETIVO 11.05.2026'!$C$2:$C$712="AJUDANTE DE ELETROMECANICA PREDIAL"))} -> 2 | E16: =IFERROR(C16/$C$6,0) -> 0.016216216 | F16: {=SUMPRODUCT(ISNUMBER(SEARCH("741",'EFETIVO 11.05.2026'!$H$2:$H$712))*(('EFETIVO 11.05.2026'!$G$2:$G$712="F")+('EFETIVO 11.05.2026'!$G$2:$G$712="P")+('EFETIVO 11.05.2026'!$G$2:$G$712="T")+('EFETIVO 11.05.2026'!$G$2:$G$712="M"))*('EFETIVO 11.05.2026'!$C$2:$C$712=$B16))} -> 0
B17: AJUDANTE DE MANUTENCAO ELETRICA | C17: {=SUMPRODUCT(ISNUMBER(SEARCH("741",'EFETIVO 11.05.2026'!$H$2:$H$712))*('EFETIVO 11.05.2026'!$G$2:$G$712="A")*('EFETIVO 11.05.2026'!$C$2:$C$712="AJUDANTE DE MANUTENCAO ELETRICA"))} -> 1 | D17: {=SUMPRODUCT(ISNUMBER(SEARCH("741",'EFETIVO 11.05.2026'!$H$2:$H$712))*('EFETIVO 11.05.2026'!$G$2:$G$712="D")*('EFETIVO 11.05.2026'!$C$2:$C$712="AJUDANTE DE MANUTENCAO ELETRICA"))} -> 0 | E17: =IFERROR(C17/$C$6,0) -> 0.0054054054 | F17: {=SUMPRODUCT(ISNUMBER(SEARCH("741",'EFETIVO 11.05.2026'!$H$2:$H$712))*(('EFETIVO 11.05.2026'!$G$2:$G$712="F")+('EFETIVO 11.05.2026'!$G$2:$G$712="P")+('EFETIVO 11.05.2026'!$G$2:$G$712="T")+('EFETIVO 11.05.2026'!$G$2:$G$712="M"))*('EFETIVO 11.05.2026'!$C$2:$C$712=$B17))} -> 0
B18: AJUDANTE DE MECANICA PREDIAL | C18: {=SUMPRODUCT(ISNUMBER(SEARCH("741",'EFETIVO 11.05.2026'!$H$2:$H$712))*('EFETIVO 11.05.2026'!$G$2:$G$712="A")*('EFETIVO 11.05.2026'!$C$2:$C$712="AJUDANTE DE MECANICA PREDIAL"))} -> 2 | D18: {=SUMPRODUCT(ISNUMBER(SEARCH("741",'EFETIVO 11.05.2026'!$H$2:$H$712))*('EFETIVO 11.05.2026'!$G$2:$G$712="D")*('EFETIVO 11.05.2026'!$C$2:$C$712="AJUDANTE DE MECANICA PREDIAL"))} -> 0 | E18: =IFERROR(C18/$C$6,0) -> 0.010810811 | F18: {=SUMPRODUCT(ISNUMBER(SEARCH("741",'EFETIVO 11.05.2026'!$H$2:$H$712))*(('EFETIVO 11.05.2026'!$G$2:$G$712="F")+('EFETIVO 11.05.2026'!$G$2:$G$712="P")+('EFETIVO 11.05.2026'!$G$2:$G$712="T")+('EFETIVO 11.05.2026'!$G$2:$G$712="M"))*('EFETIVO 11.05.2026'!$C$2:$C$712=$B18))} -> 0
B19: AJUDANTE DE PEDREIRO | C19: {=SUMPRODUCT(ISNUMBER(SEARCH("741",'EFETIVO 11.05.2026'!$H$2:$H$712))*('EFETIVO 11.05.2026'!$G$2:$G$712="A")*('EFETIVO 11.05.2026'!$C$2:$C$712="AJUDANTE DE PEDREIRO"))} -> 0 | D19: {=SUMPRODUCT(ISNUMBER(SEARCH("741",'EFETIVO 11.05.2026'!$H$2:$H$712))*('EFETIVO 11.05.2026'!$G$2:$G$712="D")*('EFETIVO 11.05.2026'!$C$2:$C$712="AJUDANTE DE PEDREIRO"))} -> 2 | E19: =IFERROR(C19/$C$6,0) -> 0 | F19: {=SUMPRODUCT(ISNUMBER(SEARCH("741",'EFETIVO 11.05.2026'!$H$2:$H$712))*(('EFETIVO 11.05.2026'!$G$2:$G$712="F")+('EFETIVO 11.05.2026'!$G$2:$G$712="P")+('EFETIVO 11.05.2026'!$G$2:$G$712="T")+('EFETIVO 11.05.2026'!$G$2:$G$712="M"))*('EFETIVO 11.05.2026'!$C$2:$C$712=$B19))} -> 0
B20: AJUDANTE DE PINTURA | C20: {=SUMPRODUCT(ISNUMBER(SEARCH("741",'EFETIVO 11.05.2026'!$H$2:$H$712))*('EFETIVO 11.05.2026'!$G$2:$G$712="A")*('EFETIVO 11.05.2026'!$C$2:$C$712="AJUDANTE DE PINTURA"))} -> 2 | D20: {=SUMPRODUCT(ISNUMBER(SEARCH("741",'EFETIVO 11.05.2026'!$H$2:$H$712))*('EFETIVO 11.05.2026'!$G$2:$G$712="D")*('EFETIVO 11.05.2026'!$C$2:$C$712="AJUDANTE DE PINTURA"))} -> 4 | E20: =IFERROR(C20/$C$6,0) -> 0.010810811 | F20: {=SUMPRODUCT(ISNUMBER(SEARCH("741",'EFETIVO 11.05.2026'!$H$2:$H$712))*(('EFETIVO 11.05.2026'!$G$2:$G$712="F")+('EFETIVO 11.05.2026'!$G$2:$G$712="P")+('EFETIVO 11.05.2026'!$G$2:$G$712="T")+('EFETIVO 11.05.2026'!$G$2:$G$712="M"))*('EFETIVO 11.05.2026'!$C$2:$C$712=$B20))} -> 0
B21: AJUDANTE DE PINTURA INDUSTRIAL | C21: {=SUMPRODUCT(ISNUMBER(SEARCH("741",'EFETIVO 11.05.2026'!$H$2:$H$712))*('EFETIVO 11.05.2026'!$G$2:$G$712="A")*('EFETIVO 11.05.2026'!$C$2:$C$712="AJUDANTE DE PINTURA INDUSTRIAL"))} -> 0 | D21: {=SUMPRODUCT(ISNUMBER(SEARCH("741",'EFETIVO 11.05.2026'!$H$2:$H$712))*('EFETIVO 11.05.2026'!$G$2:$G$712="D")*('EFETIVO 11.05.2026'!$C$2:$C$712="AJUDANTE DE PINTURA INDUSTRIAL"))} -> 1 | E21: =IFERROR(C21/$C$6,0) -> 0 | F21: {=SUMPRODUCT(ISNUMBER(SEARCH("741",'EFETIVO 11.05.2026'!$H$2:$H$712))*(('EFETIVO 11.05.2026'!$G$2:$G$712="F")+('EFETIVO 11.05.2026'!$G$2:$G$712="P")+('EFETIVO 11.05.2026'!$G$2:$G$712="T")+('EFETIVO 11.05.2026'!$G$2:$G$712="M"))*('EFETIVO 11.05.2026'!$C$2:$C$712=$B21))} -> 0
B22: ALMOXARIFE | C22: {=SUMPRODUCT(ISNUMBER(SEARCH("741",'EFETIVO 11.05.2026'!$H$2:$H$712))*('EFETIVO 11.05.2026'!$G$2:$G$712="A")*('EFETIVO 11.05.2026'!$C$2:$C$712="ALMOXARIFE"))} -> 2 | D22: {=SUMPRODUCT(ISNUMBER(SEARCH("741",'EFETIVO 11.05.2026'!$H$2:$H$712))*('EFETIVO 11.05.2026'!$G$2:$G$712="D")*('EFETIVO 11.05.2026'!$C$2:$C$712="ALMOXARIFE"))} -> 0 | E22: =IFERROR(C22/$C$6,0) -> 0.010810811 | F22: {=SUMPRODUCT(ISNUMBER(SEARCH("741",'EFETIVO 11.05.2026'!$H$2:$H$712))*(('EFETIVO 11.05.2026'!$G$2:$G$712="F")+('EFETIVO 11.05.2026'!$G$2:$G$712="P")+('EFETIVO 11.05.2026'!$G$2:$G$712="T")+('EFETIVO 11.05.2026'!$G$2:$G$712="M"))*('EFETIVO 11.05.2026'!$C$2:$C$712=$B22))} -> 0
B23: ARTIFICE | C23: {=SUMPRODUCT(ISNUMBER(SEARCH("741",'EFETIVO 11.05.2026'!$H$2:$H$712))*('EFETIVO 11.05.2026'!$G$2:$G$712="A")*('EFETIVO 11.05.2026'!$C$2:$C$712="ARTIFICE"))} -> 20 | D23: {=SUMPRODUCT(ISNUMBER(SEARCH("741",'EFETIVO 11.05.2026'!$H$2:$H$712))*('EFETIVO 11.05.2026'!$G$2:$G$712="D")*('EFETIVO 11.05.2026'!$C$2:$C$712="ARTIFICE"))} -> 2 | E23: =IFERROR(C23/$C$6,0) -> 0.10810811 | F23: {=SUMPRODUCT(ISNUMBER(SEARCH("741",'EFETIVO 11.05.2026'!$H$2:$H$712))*(('EFETIVO 11.05.2026'!$G$2:$G$712="F")+('EFETIVO 11.05.2026'!$G$2:$G$712="P")+('EFETIVO 11.05.2026'!$G$2:$G$712="T")+('EFETIVO 11.05.2026'!$G$2:$G$712="M"))*('EFETIVO 11.05.2026'!$C$2:$C$712=$B23))} -> 2
B24: ASSISTENTE ADMINISTRATIVO | C24: {=SUMPRODUCT(ISNUMBER(SEARCH("741",'EFETIVO 11.05.2026'!$H$2:$H$712))*('EFETIVO 11.05.2026'!$G$2:$G$712="A")*('EFETIVO 11.05.2026'!$C$2:$C$712="ASSISTENTE ADMINISTRATIVO"))} -> 3 | D24: {=SUMPRODUCT(ISNUMBER(SEARCH("741",'EFETIVO 11.05.2026'!$H$2:$H$712))*('EFETIVO 11.05.2026'!$G$2:$G$712="D")*('EFETIVO 11.05.2026'!$C$2:$C$712="ASSISTENTE ADMINISTRATIVO"))} -> 0 | E24: =IFERROR(C24/$C$6,0) -> 0.016216216 | F24: {=SUMPRODUCT(ISNUMBER(SEARCH("741",'EFETIVO 11.05.2026'!$H$2:$H$712))*(('EFETIVO 11.05.2026'!$G$2:$G$712="F")+('EFETIVO 11.05.2026'!$G$2:$G$712="P")+('EFETIVO 11.05.2026'!$G$2:$G$712="T")+('EFETIVO 11.05.2026'!$G$2:$G$712="M"))*('EFETIVO 11.05.2026'!$C$2:$C$712=$B24))} -> 0
B25: ASSISTENTE DE LOGISTICA I | C25: {=SUMPRODUCT(ISNUMBER(SEARCH("741",'EFETIVO 11.05.2026'!$H$2:$H$712))*('EFETIVO 11.05.2026'!$G$2:$G$712="A")*('EFETIVO 11.05.2026'!$C$2:$C$712="ASSISTENTE DE LOGISTICA I"))} -> 2 | D25: {=SUMPRODUCT(ISNUMBER(SEARCH("741",'EFETIVO 11.05.2026'!$H$2:$H$712))*('EFETIVO 11.05.2026'!$G$2:$G$712="D")*('EFETIVO 11.05.2026'!$C$2:$C$712="ASSISTENTE DE LOGISTICA I"))} -> 0 | E25: =IFERROR(C25/$C$6,0) -> 0.010810811 | F25: {=SUMPRODUCT(ISNUMBER(SEARCH("741",'EFETIVO 11.05.2026'!$H$2:$H$712))*(('EFETIVO 11.05.2026'!$G$2:$G$712="F")+('EFETIVO 11.05.2026'!$G$2:$G$712="P")+('EFETIVO 11.05.2026'!$G$2:$G$712="T")+('EFETIVO 11.05.2026'!$G$2:$G$712="M"))*('EFETIVO 11.05.2026'!$C$2:$C$712=$B25))} -> 0
B26: AUXILIAR ADMINISTRATIVO | C26: {=SUMPRODUCT(ISNUMBER(SEARCH("741",'EFETIVO 11.05.2026'!$H$2:$H$712))*('EFETIVO 11.05.2026'!$G$2:$G$712="A")*('EFETIVO 11.05.2026'!$C$2:$C$712="AUXILIAR ADMINISTRATIVO"))} -> 2 | D26: {=SUMPRODUCT(ISNUMBER(SEARCH("741",'EFETIVO 11.05.2026'!$H$2:$H$712))*('EFETIVO 11.05.2026'!$G$2:$G$712="D")*('EFETIVO 11.05.2026'!$C$2:$C$712="AUXILIAR ADMINISTRATIVO"))} -> 1 | E26: =IFERROR(C26/$C$6,0) -> 0.010810811 | F26: {=SUMPRODUCT(ISNUMBER(SEARCH("741",'EFETIVO 11.05.2026'!$H$2:$H$712))*(('EFETIVO 11.05.2026'!$G$2:$G$712="F")+('EFETIVO 11.05.2026'!$G$2:$G$712="P")+('EFETIVO 11.05.2026'!$G$2:$G$712="T")+('EFETIVO 11.05.2026'!$G$2:$G$712="M"))*('EFETIVO 11.05.2026'!$C$2:$C$712=$B26))} -> 0
B27: AUXILIAR DE ALMOXARIFADO | C27: {=SUMPRODUCT(ISNUMBER(SEARCH("741",'EFETIVO 11.05.2026'!$H$2:$H$712))*('EFETIVO 11.05.2026'!$G$2:$G$712="A")*('EFETIVO 11.05.2026'!$C$2:$C$712="AUXILIAR DE ALMOXARIFADO"))} -> 2 | D27: {=SUMPRODUCT(ISNUMBER(SEARCH("741",'EFETIVO 11.05.2026'!$H$2:$H$712))*('EFETIVO 11.05.2026'!$G$2:$G$712="D")*('EFETIVO 11.05.2026'!$C$2:$C$712="AUXILIAR DE ALMOXARIFADO"))} -> 0 | E27: =IFERROR(C27/$C$6,0) -> 0.010810811 | F27: {=SUMPRODUCT(ISNUMBER(SEARCH("741",'EFETIVO 11.05.2026'!$H$2:$H$712))*(('EFETIVO 11.05.2026'!$G$2:$G$712="F")+('EFETIVO 11.05.2026'!$G$2:$G$712="P")+('EFETIVO 11.05.2026'!$G$2:$G$712="T")+('EFETIVO 11.05.2026'!$G$2:$G$712="M"))*('EFETIVO 11.05.2026'!$C$2:$C$712=$B27))} -> 0
B28: AUXILIAR DE ALMOXARIFE | C28: {=SUMPRODUCT(ISNUMBER(SEARCH("741",'EFETIVO 11.05.2026'!$H$2:$H$712))*('EFETIVO 11.05.2026'!$G$2:$G$712="A")*('EFETIVO 11.05.2026'!$C$2:$C$712="AUXILIAR DE ALMOXARIFE"))} -> 0 | D28: {=SUMPRODUCT(ISNUMBER(SEARCH("741",'EFETIVO 11.05.2026'!$H$2:$H$712))*('EFETIVO 11.05.2026'!$G$2:$G$712="D")*('EFETIVO 11.05.2026'!$C$2:$C$712="AUXILIAR DE ALMOXARIFE"))} -> 2 | E28: =IFERROR(C28/$C$6,0) -> 0 | F28: {=SUMPRODUCT(ISNUMBER(SEARCH("741",'EFETIVO 11.05.2026'!$H$2:$H$712))*(('EFETIVO 11.05.2026'!$G$2:$G$712="F")+('EFETIVO 11.05.2026'!$G$2:$G$712="P")+('EFETIVO 11.05.2026'!$G$2:$G$712="T")+('EFETIVO 11.05.2026'!$G$2:$G$712="M"))*('EFETIVO 11.05.2026'!$C$2:$C$712=$B28))} -> 0
B29: AUXILIAR DE JARDINAGEM | C29: {=SUMPRODUCT(ISNUMBER(SEARCH("741",'EFETIVO 11.05.2026'!$H$2:$H$712))*('EFETIVO 11.05.2026'!$G$2:$G$712="A")*('EFETIVO 11.05.2026'!$C$2:$C$712="AUXILIAR DE JARDINAGEM"))} -> 23 | D29: {=SUMPRODUCT(ISNUMBER(SEARCH("741",'EFETIVO 11.05.2026'!$H$2:$H$712))*('EFETIVO 11.05.2026'!$G$2:$G$712="D")*('EFETIVO 11.05.2026'!$C$2:$C$712="AUXILIAR DE JARDINAGEM"))} -> 7 | E29: =IFERROR(C29/$C$6,0) -> 0.12432432 | F29: {=SUMPRODUCT(ISNUMBER(SEARCH("741",'EFETIVO 11.05.2026'!$H$2:$H$712))*(('EFETIVO 11.05.2026'!$G$2:$G$712="F")+('EFETIVO 11.05.2026'!$G$2:$G$712="P")+('EFETIVO 11.05.2026'!$G$2:$G$712="T")+('EFETIVO 11.05.2026'!$G$2:$G$712="M"))*('EFETIVO 11.05.2026'!$C$2:$C$712=$B29))} -> 1
B30: AUXILIAR DE MANUTENCAO CIVIL | C30: {=SUMPRODUCT(ISNUMBER(SEARCH("741",'EFETIVO 11.05.2026'!$H$2:$H$712))*('EFETIVO 11.05.2026'!$G$2:$G$712="A")*('EFETIVO 11.05.2026'!$C$2:$C$712="AUXILIAR DE MANUTENCAO CIVIL"))} -> 12 | D30: {=SUMPRODUCT(ISNUMBER(SEARCH("741",'EFETIVO 11.05.2026'!$H$2:$H$712))*('EFETIVO 11.05.2026'!$G$2:$G$712="D")*('EFETIVO 11.05.2026'!$C$2:$C$712="AUXILIAR DE MANUTENCAO CIVIL"))} -> 5 | E30: =IFERROR(C30/$C$6,0) -> 0.064864865 | F30: {=SUMPRODUCT(ISNUMBER(SEARCH("741",'EFETIVO 11.05.2026'!$H$2:$H$712))*(('EFETIVO 11.05.2026'!$G$2:$G$712="F")+('EFETIVO 11.05.2026'!$G$2:$G$712="P")+('EFETIVO 11.05.2026'!$G$2:$G$712="T")+('EFETIVO 11.05.2026'!$G$2:$G$712="M"))*('EFETIVO 11.05.2026'!$C$2:$C$712=$B30))} -> 1
B31: AUXILIAR DE MANUTENCAO EM CALDEIRARIA | C31: {=SUMPRODUCT(ISNUMBER(SEARCH("741",'EFETIVO 11.05.2026'!$H$2:$H$712))*('EFETIVO 11.05.2026'!$G$2:$G$712="A")*('EFETIVO 11.05.2026'!$C$2:$C$712="AUXILIAR DE MANUTENCAO EM CALDEIRARIA"))} -> 1 | D31: {=SUMPRODUCT(ISNUMBER(SEARCH("741",'EFETIVO 11.05.2026'!$H$2:$H$712))*('EFETIVO 11.05.2026'!$G$2:$G$712="D")*('EFETIVO 11.05.2026'!$C$2:$C$712="AUXILIAR DE MANUTENCAO EM CALDEIRARIA"))} -> 0 | E31: =IFERROR(C31/$C$6,0) -> 0.0054054054 | F31: {=SUMPRODUCT(ISNUMBER(SEARCH("741",'EFETIVO 11.05.2026'!$H$2:$H$712))*(('EFETIVO 11.05.2026'!$G$2:$G$712="F")+('EFETIVO 11.05.2026'!$G$2:$G$712="P")+('EFETIVO 11.05.2026'!$G$2:$G$712="T")+('EFETIVO 11.05.2026'!$G$2:$G$712="M"))*('EFETIVO 11.05.2026'!$C$2:$C$712=$B31))} -> 0
B32: AUXILIAR DE SEGURANCA DO TRABALHO | C32: {=SUMPRODUCT(ISNUMBER(SEARCH("741",'EFETIVO 11.05.2026'!$H$2:$H$712))*('EFETIVO 11.05.2026'!$G$2:$G$712="A")*('EFETIVO 11.05.2026'!$C$2:$C$712="AUXILIAR DE SEGURANCA DO TRABALHO"))} -> 2 | D32: {=SUMPRODUCT(ISNUMBER(SEARCH("741",'EFETIVO 11.05.2026'!$H$2:$H$712))*('EFETIVO 11.05.2026'!$G$2:$G$712="D")*('EFETIVO 11.05.2026'!$C$2:$C$712="AUXILIAR DE SEGURANCA DO TRABALHO"))} -> 2 | E32: =IFERROR(C32/$C$6,0) -> 0.010810811 | F32: {=SUMPRODUCT(ISNUMBER(SEARCH("741",'EFETIVO 11.05.2026'!$H$2:$H$712))*(('EFETIVO 11.05.2026'!$G$2:$G$712="F")+('EFETIVO 11.05.2026'!$G$2:$G$712="P")+('EFETIVO 11.05.2026'!$G$2:$G$712="T")+('EFETIVO 11.05.2026'!$G$2:$G$712="M"))*('EFETIVO 11.05.2026'!$C$2:$C$712=$B32))} -> 0
B33: AUXILIAR DE SERVICOS GERAIS | C33: {=SUMPRODUCT(ISNUMBER(SEARCH("741",'EFETIVO 11.05.2026'!$H$2:$H$712))*('EFETIVO 11.05.2026'!$G$2:$G$712="A")*('EFETIVO 11.05.2026'!$C$2:$C$712="AUXILIAR DE SERVICOS GERAIS"))} -> 27 | D33: {=SUMPRODUCT(ISNUMBER(SEARCH("741",'EFETIVO 11.05.2026'!$H$2:$H$712))*('EFETIVO 11.05.2026'!$G$2:$G$712="D")*('EFETIVO 11.05.2026'!$C$2:$C$712="AUXILIAR DE SERVICOS GERAIS"))} -> 11 | E33: =IFERROR(C33/$C$6,0) -> 0.14594595 | F33: {=SUMPRODUCT(ISNUMBER(SEARCH("741",'EFETIVO 11.05.2026'!$H$2:$H$712))*(('EFETIVO 11.05.2026'!$G$2:$G$712="F")+('EFETIVO 11.05.2026'!$G$2:$G$712="P")+('EFETIVO 11.05.2026'!$G$2:$G$712="T")+('EFETIVO 11.05.2026'!$G$2:$G$712="M"))*('EFETIVO 11.05.2026'!$C$2:$C$712=$B33))} -> 1
B34: BOMBEIRO HIDRAULICO | C34: {=SUMPRODUCT(ISNUMBER(SEARCH("741",'EFETIVO 11.05.2026'!$H$2:$H$712))*('EFETIVO 11.05.2026'!$G$2:$G$712="A")*('EFETIVO 11.05.2026'!$C$2:$C$712="BOMBEIRO HIDRAULICO"))} -> 0 | D34: {=SUMPRODUCT(ISNUMBER(SEARCH("741",'EFETIVO 11.05.2026'!$H$2:$H$712))*('EFETIVO 11.05.2026'!$G$2:$G$712="D")*('EFETIVO 11.05.2026'!$C$2:$C$712="BOMBEIRO HIDRAULICO"))} -> 1 | E34: =IFERROR(C34/$C$6,0) -> 0 | F34: {=SUMPRODUCT(ISNUMBER(SEARCH("741",'EFETIVO 11.05.2026'!$H$2:$H$712))*(('EFETIVO 11.05.2026'!$G$2:$G$712="F")+('EFETIVO 11.05.2026'!$G$2:$G$712="P")+('EFETIVO 11.05.2026'!$G$2:$G$712="T")+('EFETIVO 11.05.2026'!$G$2:$G$712="M"))*('EFETIVO 11.05.2026'!$C$2:$C$712=$B34))} -> 0
B35: CADISTA I | C35: {=SUMPRODUCT(ISNUMBER(SEARCH("741",'EFETIVO 11.05.2026'!$H$2:$H$712))*('EFETIVO 11.05.2026'!$G$2:$G$712="A")*('EFETIVO 11.05.2026'!$C$2:$C$712="CADISTA I"))} -> 1 | D35: {=SUMPRODUCT(ISNUMBER(SEARCH("741",'EFETIVO 11.05.2026'!$H$2:$H$712))*('EFETIVO 11.05.2026'!$G$2:$G$712="D")*('EFETIVO 11.05.2026'!$C$2:$C$712="CADISTA I"))} -> 0 | E35: =IFERROR(C35/$C$6,0) -> 0.0054054054 | F35: {=SUMPRODUCT(ISNUMBER(SEARCH("741",'EFETIVO 11.05.2026'!$H$2:$H$712))*(('EFETIVO 11.05.2026'!$G$2:$G$712="F")+('EFETIVO 11.05.2026'!$G$2:$G$712="P")+('EFETIVO 11.05.2026'!$G$2:$G$712="T")+('EFETIVO 11.05.2026'!$G$2:$G$712="M"))*('EFETIVO 11.05.2026'!$C$2:$C$712=$B35))} -> 0
B36: CALDEIREIRO | C36: {=SUMPRODUCT(ISNUMBER(SEARCH("741",'EFETIVO 11.05.2026'!$H$2:$H$712))*('EFETIVO 11.05.2026'!$G$2:$G$712="A")*('EFETIVO 11.05.2026'!$C$2:$C$712="CALDEIREIRO"))} -> 2 | D36: {=SUMPRODUCT(ISNUMBER(SEARCH("741",'EFETIVO 11.05.2026'!$H$2:$H$712))*('EFETIVO 11.05.2026'!$G$2:$G$712="D")*('EFETIVO 11.05.2026'!$C$2:$C$712="CALDEIREIRO"))} -> 1 | E36: =IFERROR(C36/$C$6,0) -> 0.010810811 | F36: {=SUMPRODUCT(ISNUMBER(SEARCH("741",'EFETIVO 11.05.2026'!$H$2:$H$712))*(('EFETIVO 11.05.2026'!$G$2:$G$712="F")+('EFETIVO 11.05.2026'!$G$2:$G$712="P")+('EFETIVO 11.05.2026'!$G$2:$G$712="T")+('EFETIVO 11.05.2026'!$G$2:$G$712="M"))*('EFETIVO 11.05.2026'!$C$2:$C$712=$B36))} -> 0
B37: CARPINTEIRO | C37: {=SUMPRODUCT(ISNUMBER(SEARCH("741",'EFETIVO 11.05.2026'!$H$2:$H$712))*('EFETIVO 11.05.2026'!$G$2:$G$712="A")*('EFETIVO 11.05.2026'!$C$2:$C$712="CARPINTEIRO"))} -> 0 | D37: {=SUMPRODUCT(ISNUMBER(SEARCH("741",'EFETIVO 11.05.2026'!$H$2:$H$712))*('EFETIVO 11.05.2026'!$G$2:$G$712="D")*('EFETIVO 11.05.2026'!$C$2:$C$712="CARPINTEIRO"))} -> 1 | E37: =IFERROR(C37/$C$6,0) -> 0 | F37: {=SUMPRODUCT(ISNUMBER(SEARCH("741",'EFETIVO 11.05.2026'!$H$2:$H$712))*(('EFETIVO 11.05.2026'!$G$2:$G$712="F")+('EFETIVO 11.05.2026'!$G$2:$G$712="P")+('EFETIVO 11.05.2026'!$G$2:$G$712="T")+('EFETIVO 11.05.2026'!$G$2:$G$712="M"))*('EFETIVO 11.05.2026'!$C$2:$C$712=$B37))} -> 0
B38: COMPRADOR | C38: {=SUMPRODUCT(ISNUMBER(SEARCH("741",'EFETIVO 11.05.2026'!$H$2:$H$712))*('EFETIVO 11.05.2026'!$G$2:$G$712="A")*('EFETIVO 11.05.2026'!$C$2:$C$712="COMPRADOR"))} -> 2 | D38: {=SUMPRODUCT(ISNUMBER(SEARCH("741",'EFETIVO 11.05.2026'!$H$2:$H$712))*('EFETIVO 11.05.2026'!$G$2:$G$712="D")*('EFETIVO 11.05.2026'!$C$2:$C$712="COMPRADOR"))} -> 0 | E38: =IFERROR(C38/$C$6,0) -> 0.010810811 | F38: {=SUMPRODUCT(ISNUMBER(SEARCH("741",'EFETIVO 11.05.2026'!$H$2:$H$712))*(('EFETIVO 11.05.2026'!$G$2:$G$712="F")+('EFETIVO 11.05.2026'!$G$2:$G$712="P")+('EFETIVO 11.05.2026'!$G$2:$G$712="T")+('EFETIVO 11.05.2026'!$G$2:$G$712="M"))*('EFETIVO 11.05.2026'!$C$2:$C$712=$B38))} -> 0
B39: COORDENADOR DE MANUTENCAO | C39: {=SUMPRODUCT(ISNUMBER(SEARCH("741",'EFETIVO 11.05.2026'!$H$2:$H$712))*('EFETIVO 11.05.2026'!$G$2:$G$712="A")*('EFETIVO 11.05.2026'!$C$2:$C$712="COORDENADOR DE MANUTENCAO"))} -> 1 | D39: {=SUMPRODUCT(ISNUMBER(SEARCH("741",'EFETIVO 11.05.2026'!$H$2:$H$712))*('EFETIVO 11.05.2026'!$G$2:$G$712="D")*('EFETIVO 11.05.2026'!$C$2:$C$712="COORDENADOR DE MANUTENCAO"))} -> 1 | E39: =IFERROR(C39/$C$6,0) -> 0.0054054054 | F39: {=SUMPRODUCT(ISNUMBER(SEARCH("741",'EFETIVO 11.05.2026'!$H$2:$H$712))*(('EFETIVO 11.05.2026'!$G$2:$G$712="F")+('EFETIVO 11.05.2026'!$G$2:$G$712="P")+('EFETIVO 11.05.2026'!$G$2:$G$712="T")+('EFETIVO 11.05.2026'!$G$2:$G$712="M"))*('EFETIVO 11.05.2026'!$C$2:$C$712=$B39))} -> 0
B40: ELETRICISTA PREDIAL | C40: {=SUMPRODUCT(ISNUMBER(SEARCH("741",'EFETIVO 11.05.2026'!$H$2:$H$712))*('EFETIVO 11.05.2026'!$G$2:$G$712="A")*('EFETIVO 11.05.2026'!$C$2:$C$712="ELETRICISTA PREDIAL"))} -> 4 | D40: {=SUMPRODUCT(ISNUMBER(SEARCH("741",'EFETIVO 11.05.2026'!$H$2:$H$712))*('EFETIVO 11.05.2026'!$G$2:$G$712="D")*('EFETIVO 11.05.2026'!$C$2:$C$712="ELETRICISTA PREDIAL"))} -> 4 | E40: =IFERROR(C40/$C$6,0) -> 0.021621622 | F40: {=SUMPRODUCT(ISNUMBER(SEARCH("741",'EFETIVO 11.05.2026'!$H$2:$H$712))*(('EFETIVO 11.05.2026'!$G$2:$G$712="F")+('EFETIVO 11.05.2026'!$G$2:$G$712="P")+('EFETIVO 11.05.2026'!$G$2:$G$712="T")+('EFETIVO 11.05.2026'!$G$2:$G$712="M"))*('EFETIVO 11.05.2026'!$C$2:$C$712=$B40))} -> 0
B41: ENCARREGADO CIVIL | C41: {=SUMPRODUCT(ISNUMBER(SEARCH("741",'EFETIVO 11.05.2026'!$H$2:$H$712))*('EFETIVO 11.05.2026'!$G$2:$G$712="A")*('EFETIVO 11.05.2026'!$C$2:$C$712="ENCARREGADO CIVIL"))} -> 1 | D41: {=SUMPRODUCT(ISNUMBER(SEARCH("741",'EFETIVO 11.05.2026'!$H$2:$H$712))*('EFETIVO 11.05.2026'!$G$2:$G$712="D")*('EFETIVO 11.05.2026'!$C$2:$C$712="ENCARREGADO CIVIL"))} -> 4 | E41: =IFERROR(C41/$C$6,0) -> 0.0054054054 | F41: {=SUMPRODUCT(ISNUMBER(SEARCH("741",'EFETIVO 11.05.2026'!$H$2:$H$712))*(('EFETIVO 11.05.2026'!$G$2:$G$712="F")+('EFETIVO 11.05.2026'!$G$2:$G$712="P")+('EFETIVO 11.05.2026'!$G$2:$G$712="T")+('EFETIVO 11.05.2026'!$G$2:$G$712="M"))*('EFETIVO 11.05.2026'!$C$2:$C$712=$B41))} -> 0
B42: ENCARREGADO DE AREAS VERDES | C42: {=SUMPRODUCT(ISNUMBER(SEARCH("741",'EFETIVO 11.05.2026'!$H$2:$H$712))*('EFETIVO 11.05.2026'!$G$2:$G$712="A")*('EFETIVO 11.05.2026'!$C$2:$C$712="ENCARREGADO DE AREAS VERDES"))} -> 2 | D42: {=SUMPRODUCT(ISNUMBER(SEARCH("741",'EFETIVO 11.05.2026'!$H$2:$H$712))*('EFETIVO 11.05.2026'!$G$2:$G$712="D")*('EFETIVO 11.05.2026'!$C$2:$C$712="ENCARREGADO DE AREAS VERDES"))} -> 0 | E42: =IFERROR(C42/$C$6,0) -> 0.010810811 | F42: {=SUMPRODUCT(ISNUMBER(SEARCH("741",'EFETIVO 11.05.2026'!$H$2:$H$712))*(('EFETIVO 11.05.2026'!$G$2:$G$712="F")+('EFETIVO 11.05.2026'!$G$2:$G$712="P")+('EFETIVO 11.05.2026'!$G$2:$G$712="T")+('EFETIVO 11.05.2026'!$G$2:$G$712="M"))*('EFETIVO 11.05.2026'!$C$2:$C$712=$B42))} -> 0
B43: ENCARREGADO DE CONSERVACAO E LIMPEZA | C43: {=SUMPRODUCT(ISNUMBER(SEARCH("741",'EFETIVO 11.05.2026'!$H$2:$H$712))*('EFETIVO 11.05.2026'!$G$2:$G$712="A")*('EFETIVO 11.05.2026'!$C$2:$C$712="ENCARREGADO DE CONSERVACAO E LIMPEZA"))} -> 2 | D43: {=SUMPRODUCT(ISNUMBER(SEARCH("741",'EFETIVO 11.05.2026'!$H$2:$H$712))*('EFETIVO 11.05.2026'!$G$2:$G$712="D")*('EFETIVO 11.05.2026'!$C$2:$C$712="ENCARREGADO DE CONSERVACAO E LIMPEZA"))} -> 0 | E43: =IFERROR(C43/$C$6,0) -> 0.010810811 | F43: {=SUMPRODUCT(ISNUMBER(SEARCH("741",'EFETIVO 11.05.2026'!$H$2:$H$712))*(('EFETIVO 11.05.2026'!$G$2:$G$712="F")+('EFETIVO 11.05.2026'!$G$2:$G$712="P")+('EFETIVO 11.05.2026'!$G$2:$G$712="T")+('EFETIVO 11.05.2026'!$G$2:$G$712="M"))*('EFETIVO 11.05.2026'!$C$2:$C$712=$B43))} -> 0
B44: ENGENHEIRO AGRONOMO | C44: {=SUMPRODUCT(ISNUMBER(SEARCH("741",'EFETIVO 11.05.2026'!$H$2:$H$712))*('EFETIVO 11.05.2026'!$G$2:$G$712="A")*('EFETIVO 11.05.2026'!$C$2:$C$712="ENGENHEIRO AGRONOMO"))} -> 1 | D44: {=SUMPRODUCT(ISNUMBER(SEARCH("741",'EFETIVO 11.05.2026'!$H$2:$H$712))*('EFETIVO 11.05.2026'!$G$2:$G$712="D")*('EFETIVO 11.05.2026'!$C$2:$C$712="ENGENHEIRO AGRONOMO"))} -> 1 | E44: =IFERROR(C44/$C$6,0) -> 0.0054054054 | F44: {=SUMPRODUCT(ISNUMBER(SEARCH("741",'EFETIVO 11.05.2026'!$H$2:$H$712))*(('EFETIVO 11.05.2026'!$G$2:$G$712="F")+('EFETIVO 11.05.2026'!$G$2:$G$712="P")+('EFETIVO 11.05.2026'!$G$2:$G$712="T")+('EFETIVO 11.05.2026'!$G$2:$G$712="M"))*('EFETIVO 11.05.2026'!$C$2:$C$712=$B44))} -> 0
B45: ENGENHEIRO CIVIL | C45: {=SUMPRODUCT(ISNUMBER(SEARCH("741",'EFETIVO 11.05.2026'!$H$2:$H$712))*('EFETIVO 11.05.2026'!$G$2:$G$712="A")*('EFETIVO 11.05.2026'!$C$2:$C$712="ENGENHEIRO CIVIL"))} -> 1 | D45: {=SUMPRODUCT(ISNUMBER(SEARCH("741",'EFETIVO 11.05.2026'!$H$2:$H$712))*('EFETIVO 11.05.2026'!$G$2:$G$712="D")*('EFETIVO 11.05.2026'!$C$2:$C$712="ENGENHEIRO CIVIL"))} -> 1 | E45: =IFERROR(C45/$C$6,0) -> 0.0054054054 | F45: {=SUMPRODUCT(ISNUMBER(SEARCH("741",'EFETIVO 11.05.2026'!$H$2:$H$712))*(('EFETIVO 11.05.2026'!$G$2:$G$712="F")+('EFETIVO 11.05.2026'!$G$2:$G$712="P")+('EFETIVO 11.05.2026'!$G$2:$G$712="T")+('EFETIVO 11.05.2026'!$G$2:$G$712="M"))*('EFETIVO 11.05.2026'!$C$2:$C$712=$B45))} -> 0
B46: ESTIVAS | C46: {=SUMPRODUCT(ISNUMBER(SEARCH("741",'EFETIVO 11.05.2026'!$H$2:$H$712))*('EFETIVO 11.05.2026'!$G$2:$G$712="A")*('EFETIVO 11.05.2026'!$C$2:$C$712="ESTIVAS"))} -> 0 | D46: {=SUMPRODUCT(ISNUMBER(SEARCH("741",'EFETIVO 11.05.2026'!$H$2:$H$712))*('EFETIVO 11.05.2026'!$G$2:$G$712="D")*('EFETIVO 11.05.2026'!$C$2:$C$712="ESTIVAS"))} -> 1 | E46: =IFERROR(C46/$C$6,0) -> 0 | F46: {=SUMPRODUCT(ISNUMBER(SEARCH("741",'EFETIVO 11.05.2026'!$H$2:$H$712))*(('EFETIVO 11.05.2026'!$G$2:$G$712="F")+('EFETIVO 11.05.2026'!$G$2:$G$712="P")+('EFETIVO 11.05.2026'!$G$2:$G$712="T")+('EFETIVO 11.05.2026'!$G$2:$G$712="M"))*('EFETIVO 11.05.2026'!$C$2:$C$712=$B46))} -> 0
B47: GERENTE DE PROJETO | C47: {=SUMPRODUCT(ISNUMBER(SEARCH("741",'EFETIVO 11.05.2026'!$H$2:$H$712))*('EFETIVO 11.05.2026'!$G$2:$G$712="A")*('EFETIVO 11.05.2026'!$C$2:$C$712="GERENTE DE PROJETO"))} -> 1 | D47: {=SUMPRODUCT(ISNUMBER(SEARCH("741",'EFETIVO 11.05.2026'!$H$2:$H$712))*('EFETIVO 11.05.2026'!$G$2:$G$712="D")*('EFETIVO 11.05.2026'!$C$2:$C$712="GERENTE DE PROJETO"))} -> 1 | E47: =IFERROR(C47/$C$6,0) -> 0.0054054054 | F47: {=SUMPRODUCT(ISNUMBER(SEARCH("741",'EFETIVO 11.05.2026'!$H$2:$H$712))*(('EFETIVO 11.05.2026'!$G$2:$G$712="F")+('EFETIVO 11.05.2026'!$G$2:$G$712="P")+('EFETIVO 11.05.2026'!$G$2:$G$712="T")+('EFETIVO 11.05.2026'!$G$2:$G$712="M"))*('EFETIVO 11.05.2026'!$C$2:$C$712=$B47))} -> 0
B48: GERENTE DE PROJETO I | C48: {=SUMPRODUCT(ISNUMBER(SEARCH("741",'EFETIVO 11.05.2026'!$H$2:$H$712))*('EFETIVO 11.05.2026'!$G$2:$G$712="A")*('EFETIVO 11.05.2026'!$C$2:$C$712="GERENTE DE PROJETO I"))} -> 1 | D48: {=SUMPRODUCT(ISNUMBER(SEARCH("741",'EFETIVO 11.05.2026'!$H$2:$H$712))*('EFETIVO 11.05.2026'!$G$2:$G$712="D")*('EFETIVO 11.05.2026'!$C$2:$C$712="GERENTE DE PROJETO I"))} -> 0 | E48: =IFERROR(C48/$C$6,0) -> 0.0054054054 | F48: {=SUMPRODUCT(ISNUMBER(SEARCH("741",'EFETIVO 11.05.2026'!$H$2:$H$712))*(('EFETIVO 11.05.2026'!$G$2:$G$712="F")+('EFETIVO 11.05.2026'!$G$2:$G$712="P")+('EFETIVO 11.05.2026'!$G$2:$G$712="T")+('EFETIVO 11.05.2026'!$G$2:$G$712="M"))*('EFETIVO 11.05.2026'!$C$2:$C$712=$B48))} -> 0
B49: JARDINEIRO | C49: {=SUMPRODUCT(ISNUMBER(SEARCH("741",'EFETIVO 11.05.2026'!$H$2:$H$712))*('EFETIVO 11.05.2026'!$G$2:$G$712="A")*('EFETIVO 11.05.2026'!$C$2:$C$712="JARDINEIRO"))} -> 3 | D49: {=SUMPRODUCT(ISNUMBER(SEARCH("741",'EFETIVO 11.05.2026'!$H$2:$H$712))*('EFETIVO 11.05.2026'!$G$2:$G$712="D")*('EFETIVO 11.05.2026'!$C$2:$C$712="JARDINEIRO"))} -> 0 | E49: =IFERROR(C49/$C$6,0) -> 0.016216216 | F49: {=SUMPRODUCT(ISNUMBER(SEARCH("741",'EFETIVO 11.05.2026'!$H$2:$H$712))*(('EFETIVO 11.05.2026'!$G$2:$G$712="F")+('EFETIVO 11.05.2026'!$G$2:$G$712="P")+('EFETIVO 11.05.2026'!$G$2:$G$712="T")+('EFETIVO 11.05.2026'!$G$2:$G$712="M"))*('EFETIVO 11.05.2026'!$C$2:$C$712=$B49))} -> 0
B50: MECANICO | C50: {=SUMPRODUCT(ISNUMBER(SEARCH("741",'EFETIVO 11.05.2026'!$H$2:$H$712))*('EFETIVO 11.05.2026'!$G$2:$G$712="A")*('EFETIVO 11.05.2026'!$C$2:$C$712="MECANICO"))} -> 4 | D50: {=SUMPRODUCT(ISNUMBER(SEARCH("741",'EFETIVO 11.05.2026'!$H$2:$H$712))*('EFETIVO 11.05.2026'!$G$2:$G$712="D")*('EFETIVO 11.05.2026'!$C$2:$C$712="MECANICO"))} -> 2 | E50: =IFERROR(C50/$C$6,0) -> 0.021621622 | F50: {=SUMPRODUCT(ISNUMBER(SEARCH("741",'EFETIVO 11.05.2026'!$H$2:$H$712))*(('EFETIVO 11.05.2026'!$G$2:$G$712="F")+('EFETIVO 11.05.2026'!$G$2:$G$712="P")+('EFETIVO 11.05.2026'!$G$2:$G$712="T")+('EFETIVO 11.05.2026'!$G$2:$G$712="M"))*('EFETIVO 11.05.2026'!$C$2:$C$712=$B50))} -> 0
B51: MECANICO DE REFRIGERACAO I | C51: {=SUMPRODUCT(ISNUMBER(SEARCH("741",'EFETIVO 11.05.2026'!$H$2:$H$712))*('EFETIVO 11.05.2026'!$G$2:$G$712="A")*('EFETIVO 11.05.2026'!$C$2:$C$712="MECANICO DE REFRIGERACAO I"))} -> 1 | D51: {=SUMPRODUCT(ISNUMBER(SEARCH("741",'EFETIVO 11.05.2026'!$H$2:$H$712))*('EFETIVO 11.05.2026'!$G$2:$G$712="D")*('EFETIVO 11.05.2026'!$C$2:$C$712="MECANICO DE REFRIGERACAO I"))} -> 1 | E51: =IFERROR(C51/$C$6,0) -> 0.0054054054 | F51: {=SUMPRODUCT(ISNUMBER(SEARCH("741",'EFETIVO 11.05.2026'!$H$2:$H$712))*(('EFETIVO 11.05.2026'!$G$2:$G$712="F")+('EFETIVO 11.05.2026'!$G$2:$G$712="P")+('EFETIVO 11.05.2026'!$G$2:$G$712="T")+('EFETIVO 11.05.2026'!$G$2:$G$712="M"))*('EFETIVO 11.05.2026'!$C$2:$C$712=$B51))} -> 0
B52: MONTADOR DE ANDAIMES | C52: {=SUMPRODUCT(ISNUMBER(SEARCH("741",'EFETIVO 11.05.2026'!$H$2:$H$712))*('EFETIVO 11.05.2026'!$G$2:$G$712="A")*('EFETIVO 11.05.2026'!$C$2:$C$712="MONTADOR DE ANDAIMES"))} -> 3 | D52: {=SUMPRODUCT(ISNUMBER(SEARCH("741",'EFETIVO 11.05.2026'!$H$2:$H$712))*('EFETIVO 11.05.2026'!$G$2:$G$712="D")*('EFETIVO 11.05.2026'!$C$2:$C$712="MONTADOR DE ANDAIMES"))} -> 4 | E52: =IFERROR(C52/$C$6,0) -> 0.016216216 | F52: {=SUMPRODUCT(ISNUMBER(SEARCH("741",'EFETIVO 11.05.2026'!$H$2:$H$712))*(('EFETIVO 11.05.2026'!$G$2:$G$712="F")+('EFETIVO 11.05.2026'!$G$2:$G$712="P")+('EFETIVO 11.05.2026'!$G$2:$G$712="T")+('EFETIVO 11.05.2026'!$G$2:$G$712="M"))*('EFETIVO 11.05.2026'!$C$2:$C$712=$B52))} -> 0
B53: MOTORISTA | C53: {=SUMPRODUCT(ISNUMBER(SEARCH("741",'EFETIVO 11.05.2026'!$H$2:$H$712))*('EFETIVO 11.05.2026'!$G$2:$G$712="A")*('EFETIVO 11.05.2026'!$C$2:$C$712="MOTORISTA"))} -> 3 | D53: {=SUMPRODUCT(ISNUMBER(SEARCH("741",'EFETIVO 11.05.2026'!$H$2:$H$712))*('EFETIVO 11.05.2026'!$G$2:$G$712="D")*('EFETIVO 11.05.2026'!$C$2:$C$712="MOTORISTA"))} -> 0 | E53: =IFERROR(C53/$C$6,0) -> 0.016216216 | F53: {=SUMPRODUCT(ISNUMBER(SEARCH("741",'EFETIVO 11.05.2026'!$H$2:$H$712))*(('EFETIVO 11.05.2026'!$G$2:$G$712="F")+('EFETIVO 11.05.2026'!$G$2:$G$712="P")+('EFETIVO 11.05.2026'!$G$2:$G$712="T")+('EFETIVO 11.05.2026'!$G$2:$G$712="M"))*('EFETIVO 11.05.2026'!$C$2:$C$712=$B53))} -> 0
B54: OPERADOR DE ROCADEIRA | C54: {=SUMPRODUCT(ISNUMBER(SEARCH("741",'EFETIVO 11.05.2026'!$H$2:$H$712))*('EFETIVO 11.05.2026'!$G$2:$G$712="A")*('EFETIVO 11.05.2026'!$C$2:$C$712="OPERADOR DE ROCADEIRA"))} -> 19 | D54: {=SUMPRODUCT(ISNUMBER(SEARCH("741",'EFETIVO 11.05.2026'!$H$2:$H$712))*('EFETIVO 11.05.2026'!$G$2:$G$712="D")*('EFETIVO 11.05.2026'!$C$2:$C$712="OPERADOR DE ROCADEIRA"))} -> 5 | E54: =IFERROR(C54/$C$6,0) -> 0.1027027 | F54: {=SUMPRODUCT(ISNUMBER(SEARCH("741",'EFETIVO 11.05.2026'!$H$2:$H$712))*(('EFETIVO 11.05.2026'!$G$2:$G$712="F")+('EFETIVO 11.05.2026'!$G$2:$G$712="P")+('EFETIVO 11.05.2026'!$G$2:$G$712="T")+('EFETIVO 11.05.2026'!$G$2:$G$712="M"))*('EFETIVO 11.05.2026'!$C$2:$C$712=$B54))} -> 0
B55: OPERADOR DE RPAS | C55: {=SUMPRODUCT(ISNUMBER(SEARCH("741",'EFETIVO 11.05.2026'!$H$2:$H$712))*('EFETIVO 11.05.2026'!$G$2:$G$712="A")*('EFETIVO 11.05.2026'!$C$2:$C$712="OPERADOR DE RPAS"))} -> 1 | D55: {=SUMPRODUCT(ISNUMBER(SEARCH("741",'EFETIVO 11.05.2026'!$H$2:$H$712))*('EFETIVO 11.05.2026'!$G$2:$G$712="D")*('EFETIVO 11.05.2026'!$C$2:$C$712="OPERADOR DE RPAS"))} -> 0 | E55: =IFERROR(C55/$C$6,0) -> 0.0054054054 | F55: {=SUMPRODUCT(ISNUMBER(SEARCH("741",'EFETIVO 11.05.2026'!$H$2:$H$712))*(('EFETIVO 11.05.2026'!$G$2:$G$712="F")+('EFETIVO 11.05.2026'!$G$2:$G$712="P")+('EFETIVO 11.05.2026'!$G$2:$G$712="T")+('EFETIVO 11.05.2026'!$G$2:$G$712="M"))*('EFETIVO 11.05.2026'!$C$2:$C$712=$B55))} -> 0
B56: PINTOR | C56: {=SUMPRODUCT(ISNUMBER(SEARCH("741",'EFETIVO 11.05.2026'!$H$2:$H$712))*('EFETIVO 11.05.2026'!$G$2:$G$712="A")*('EFETIVO 11.05.2026'!$C$2:$C$712="PINTOR"))} -> 1 | D56: {=SUMPRODUCT(ISNUMBER(SEARCH("741",'EFETIVO 11.05.2026'!$H$2:$H$712))*('EFETIVO 11.05.2026'!$G$2:$G$712="D")*('EFETIVO 11.05.2026'!$C$2:$C$712="PINTOR"))} -> 3 | E56: =IFERROR(C56/$C$6,0) -> 0.0054054054 | F56: {=SUMPRODUCT(ISNUMBER(SEARCH("741",'EFETIVO 11.05.2026'!$H$2:$H$712))*(('EFETIVO 11.05.2026'!$G$2:$G$712="F")+('EFETIVO 11.05.2026'!$G$2:$G$712="P")+('EFETIVO 11.05.2026'!$G$2:$G$712="T")+('EFETIVO 11.05.2026'!$G$2:$G$712="M"))*('EFETIVO 11.05.2026'!$C$2:$C$712=$B56))} -> 0
B57: PINTOR INDUSTRIAL | C57: {=SUMPRODUCT(ISNUMBER(SEARCH("741",'EFETIVO 11.05.2026'!$H$2:$H$712))*('EFETIVO 11.05.2026'!$G$2:$G$712="A")*('EFETIVO 11.05.2026'!$C$2:$C$712="PINTOR INDUSTRIAL"))} -> 2 | D57: {=SUMPRODUCT(ISNUMBER(SEARCH("741",'EFETIVO 11.05.2026'!$H$2:$H$712))*('EFETIVO 11.05.2026'!$G$2:$G$712="D")*('EFETIVO 11.05.2026'!$C$2:$C$712="PINTOR INDUSTRIAL"))} -> 5 | E57: =IFERROR(C57/$C$6,0) -> 0.010810811 | F57: {=SUMPRODUCT(ISNUMBER(SEARCH("741",'EFETIVO 11.05.2026'!$H$2:$H$712))*(('EFETIVO 11.05.2026'!$G$2:$G$712="F")+('EFETIVO 11.05.2026'!$G$2:$G$712="P")+('EFETIVO 11.05.2026'!$G$2:$G$712="T")+('EFETIVO 11.05.2026'!$G$2:$G$712="M"))*('EFETIVO 11.05.2026'!$C$2:$C$712=$B57))} -> 0
B58: PLANEJADOR | C58: {=SUMPRODUCT(ISNUMBER(SEARCH("741",'EFETIVO 11.05.2026'!$H$2:$H$712))*('EFETIVO 11.05.2026'!$G$2:$G$712="A")*('EFETIVO 11.05.2026'!$C$2:$C$712="PLANEJADOR"))} -> 1 | D58: {=SUMPRODUCT(ISNUMBER(SEARCH("741",'EFETIVO 11.05.2026'!$H$2:$H$712))*('EFETIVO 11.05.2026'!$G$2:$G$712="D")*('EFETIVO 11.05.2026'!$C$2:$C$712="PLANEJADOR"))} -> 2 | E58: =IFERROR(C58/$C$6,0) -> 0.0054054054 | F58: {=SUMPRODUCT(ISNUMBER(SEARCH("741",'EFETIVO 11.05.2026'!$H$2:$H$712))*(('EFETIVO 11.05.2026'!$G$2:$G$712="F")+('EFETIVO 11.05.2026'!$G$2:$G$712="P")+('EFETIVO 11.05.2026'!$G$2:$G$712="T")+('EFETIVO 11.05.2026'!$G$2:$G$712="M"))*('EFETIVO 11.05.2026'!$C$2:$C$712=$B58))} -> 1
B59: SUPERVISOR ADMINISTRATIVO | C59: {=SUMPRODUCT(ISNUMBER(SEARCH("741",'EFETIVO 11.05.2026'!$H$2:$H$712))*('EFETIVO 11.05.2026'!$G$2:$G$712="A")*('EFETIVO 11.05.2026'!$C$2:$C$712="SUPERVISOR ADMINISTRATIVO"))} -> 1 | D59: {=SUMPRODUCT(ISNUMBER(SEARCH("741",'EFETIVO 11.05.2026'!$H$2:$H$712))*('EFETIVO 11.05.2026'!$G$2:$G$712="D")*('EFETIVO 11.05.2026'!$C$2:$C$712="SUPERVISOR ADMINISTRATIVO"))} -> 0 | E59: =IFERROR(C59/$C$6,0) -> 0.0054054054 | F59: {=SUMPRODUCT(ISNUMBER(SEARCH("741",'EFETIVO 11.05.2026'!$H$2:$H$712))*(('EFETIVO 11.05.2026'!$G$2:$G$712="F")+('EFETIVO 11.05.2026'!$G$2:$G$712="P")+('EFETIVO 11.05.2026'!$G$2:$G$712="T")+('EFETIVO 11.05.2026'!$G$2:$G$712="M"))*('EFETIVO 11.05.2026'!$C$2:$C$712=$B59))} -> 0
B60: SUPERVISOR DE AREAS VERDES | C60: {=SUMPRODUCT(ISNUMBER(SEARCH("741",'EFETIVO 11.05.2026'!$H$2:$H$712))*('EFETIVO 11.05.2026'!$G$2:$G$712="A")*('EFETIVO 11.05.2026'!$C$2:$C$712="SUPERVISOR DE AREAS VERDES"))} -> 2 | D60: {=SUMPRODUCT(ISNUMBER(SEARCH("741",'EFETIVO 11.05.2026'!$H$2:$H$712))*('EFETIVO 11.05.2026'!$G$2:$G$712="D")*('EFETIVO 11.05.2026'!$C$2:$C$712="SUPERVISOR DE AREAS VERDES"))} -> 0 | E60: =IFERROR(C60/$C$6,0) -> 0.010810811 | F60: {=SUMPRODUCT(ISNUMBER(SEARCH("741",'EFETIVO 11.05.2026'!$H$2:$H$712))*(('EFETIVO 11.05.2026'!$G$2:$G$712="F")+('EFETIVO 11.05.2026'!$G$2:$G$712="P")+('EFETIVO 11.05.2026'!$G$2:$G$712="T")+('EFETIVO 11.05.2026'!$G$2:$G$712="M"))*('EFETIVO 11.05.2026'!$C$2:$C$712=$B60))} -> 0
B61: SUPERVISOR DE ELETRICA | C61: {=SUMPRODUCT(ISNUMBER(SEARCH("741",'EFETIVO 11.05.2026'!$H$2:$H$712))*('EFETIVO 11.05.2026'!$G$2:$G$712="A")*('EFETIVO 11.05.2026'!$C$2:$C$712="SUPERVISOR DE ELETRICA"))} -> 2 | D61: {=SUMPRODUCT(ISNUMBER(SEARCH("741",'EFETIVO 11.05.2026'!$H$2:$H$712))*('EFETIVO 11.05.2026'!$G$2:$G$712="D")*('EFETIVO 11.05.2026'!$C$2:$C$712="SUPERVISOR DE ELETRICA"))} -> 0 | E61: =IFERROR(C61/$C$6,0) -> 0.010810811 | F61: {=SUMPRODUCT(ISNUMBER(SEARCH("741",'EFETIVO 11.05.2026'!$H$2:$H$712))*(('EFETIVO 11.05.2026'!$G$2:$G$712="F")+('EFETIVO 11.05.2026'!$G$2:$G$712="P")+('EFETIVO 11.05.2026'!$G$2:$G$712="T")+('EFETIVO 11.05.2026'!$G$2:$G$712="M"))*('EFETIVO 11.05.2026'!$C$2:$C$712=$B61))} -> 0
B62: SUPERVISOR DE ELETRICA PREDIAL | C62: {=SUMPRODUCT(ISNUMBER(SEARCH("741",'EFETIVO 11.05.2026'!$H$2:$H$712))*('EFETIVO 11.05.2026'!$G$2:$G$712="A")*('EFETIVO 11.05.2026'!$C$2:$C$712="SUPERVISOR DE ELETRICA PREDIAL"))} -> 0 | D62: {=SUMPRODUCT(ISNUMBER(SEARCH("741",'EFETIVO 11.05.2026'!$H$2:$H$712))*('EFETIVO 11.05.2026'!$G$2:$G$712="D")*('EFETIVO 11.05.2026'!$C$2:$C$712="SUPERVISOR DE ELETRICA PREDIAL"))} -> 1 | E62: =IFERROR(C62/$C$6,0) -> 0 | F62: {=SUMPRODUCT(ISNUMBER(SEARCH("741",'EFETIVO 11.05.2026'!$H$2:$H$712))*(('EFETIVO 11.05.2026'!$G$2:$G$712="F")+('EFETIVO 11.05.2026'!$G$2:$G$712="P")+('EFETIVO 11.05.2026'!$G$2:$G$712="T")+('EFETIVO 11.05.2026'!$G$2:$G$712="M"))*('EFETIVO 11.05.2026'!$C$2:$C$712=$B62))} -> 0
B63: SUPERVISOR DE LIMPEZA E CONSERVACAO | C63: {=SUMPRODUCT(ISNUMBER(SEARCH("741",'EFETIVO 11.05.2026'!$H$2:$H$712))*('EFETIVO 11.05.2026'!$G$2:$G$712="A")*('EFETIVO 11.05.2026'!$C$2:$C$712="SUPERVISOR DE LIMPEZA E CONSERVACAO"))} -> 1 | D63: {=SUMPRODUCT(ISNUMBER(SEARCH("741",'EFETIVO 11.05.2026'!$H$2:$H$712))*('EFETIVO 11.05.2026'!$G$2:$G$712="D")*('EFETIVO 11.05.2026'!$C$2:$C$712="SUPERVISOR DE LIMPEZA E CONSERVACAO"))} -> 0 | E63: =IFERROR(C63/$C$6,0) -> 0.0054054054 | F63: {=SUMPRODUCT(ISNUMBER(SEARCH("741",'EFETIVO 11.05.2026'!$H$2:$H$712))*(('EFETIVO 11.05.2026'!$G$2:$G$712="F")+('EFETIVO 11.05.2026'!$G$2:$G$712="P")+('EFETIVO 11.05.2026'!$G$2:$G$712="T")+('EFETIVO 11.05.2026'!$G$2:$G$712="M"))*('EFETIVO 11.05.2026'!$C$2:$C$712=$B63))} -> 0
B64: SUPERVISOR DE MANUTENCAO CIVIL | C64: {=SUMPRODUCT(ISNUMBER(SEARCH("741",'EFETIVO 11.05.2026'!$H$2:$H$712))*('EFETIVO 11.05.2026'!$G$2:$G$712="A")*('EFETIVO 11.05.2026'!$C$2:$C$712="SUPERVISOR DE MANUTENCAO CIVIL"))} -> 1 | D64: {=SUMPRODUCT(ISNUMBER(SEARCH("741",'EFETIVO 11.05.2026'!$H$2:$H$712))*('EFETIVO 11.05.2026'!$G$2:$G$712="D")*('EFETIVO 11.05.2026'!$C$2:$C$712="SUPERVISOR DE MANUTENCAO CIVIL"))} -> 0 | E64: =IFERROR(C64/$C$6,0) -> 0.0054054054 | F64: {=SUMPRODUCT(ISNUMBER(SEARCH("741",'EFETIVO 11.05.2026'!$H$2:$H$712))*(('EFETIVO 11.05.2026'!$G$2:$G$712="F")+('EFETIVO 11.05.2026'!$G$2:$G$712="P")+('EFETIVO 11.05.2026'!$G$2:$G$712="T")+('EFETIVO 11.05.2026'!$G$2:$G$712="M"))*('EFETIVO 11.05.2026'!$C$2:$C$712=$B64))} -> 0
B65: SUPERVISOR DE MANUTENCAO II | C65: {=SUMPRODUCT(ISNUMBER(SEARCH("741",'EFETIVO 11.05.2026'!$H$2:$H$712))*('EFETIVO 11.05.2026'!$G$2:$G$712="A")*('EFETIVO 11.05.2026'!$C$2:$C$712="SUPERVISOR DE MANUTENCAO II"))} -> 1 | D65: {=SUMPRODUCT(ISNUMBER(SEARCH("741",'EFETIVO 11.05.2026'!$H$2:$H$712))*('EFETIVO 11.05.2026'!$G$2:$G$712="D")*('EFETIVO 11.05.2026'!$C$2:$C$712="SUPERVISOR DE MANUTENCAO II"))} -> 0 | E65: =IFERROR(C65/$C$6,0) -> 0.0054054054 | F65: {=SUMPRODUCT(ISNUMBER(SEARCH("741",'EFETIVO 11.05.2026'!$H$2:$H$712))*(('EFETIVO 11.05.2026'!$G$2:$G$712="F")+('EFETIVO 11.05.2026'!$G$2:$G$712="P")+('EFETIVO 11.05.2026'!$G$2:$G$712="T")+('EFETIVO 11.05.2026'!$G$2:$G$712="M"))*('EFETIVO 11.05.2026'!$C$2:$C$712=$B65))} -> 0
B66: SUPERVISOR DE PLANEJAMENTO | C66: {=SUMPRODUCT(ISNUMBER(SEARCH("741",'EFETIVO 11.05.2026'!$H$2:$H$712))*('EFETIVO 11.05.2026'!$G$2:$G$712="A")*('EFETIVO 11.05.2026'!$C$2:$C$712="SUPERVISOR DE PLANEJAMENTO"))} -> 1 | D66: {=SUMPRODUCT(ISNUMBER(SEARCH("741",'EFETIVO 11.05.2026'!$H$2:$H$712))*('EFETIVO 11.05.2026'!$G$2:$G$712="D")*('EFETIVO 11.05.2026'!$C$2:$C$712="SUPERVISOR DE PLANEJAMENTO"))} -> 0 | E66: =IFERROR(C66/$C$6,0) -> 0.0054054054 | F66: {=SUMPRODUCT(ISNUMBER(SEARCH("741",'EFETIVO 11.05.2026'!$H$2:$H$712))*(('EFETIVO 11.05.2026'!$G$2:$G$712="F")+('EFETIVO 11.05.2026'!$G$2:$G$712="P")+('EFETIVO 11.05.2026'!$G$2:$G$712="T")+('EFETIVO 11.05.2026'!$G$2:$G$712="M"))*('EFETIVO 11.05.2026'!$C$2:$C$712=$B66))} -> 0
B67: SUPERVISOR DE SMS | C67: {=SUMPRODUCT(ISNUMBER(SEARCH("741",'EFETIVO 11.05.2026'!$H$2:$H$712))*('EFETIVO 11.05.2026'!$G$2:$G$712="A")*('EFETIVO 11.05.2026'!$C$2:$C$712="SUPERVISOR DE SMS"))} -> 1 | D67: {=SUMPRODUCT(ISNUMBER(SEARCH("741",'EFETIVO 11.05.2026'!$H$2:$H$712))*('EFETIVO 11.05.2026'!$G$2:$G$712="D")*('EFETIVO 11.05.2026'!$C$2:$C$712="SUPERVISOR DE SMS"))} -> 0 | E67: =IFERROR(C67/$C$6,0) -> 0.0054054054 | F67: {=SUMPRODUCT(ISNUMBER(SEARCH("741",'EFETIVO 11.05.2026'!$H$2:$H$712))*(('EFETIVO 11.05.2026'!$G$2:$G$712="F")+('EFETIVO 11.05.2026'!$G$2:$G$712="P")+('EFETIVO 11.05.2026'!$G$2:$G$712="T")+('EFETIVO 11.05.2026'!$G$2:$G$712="M"))*('EFETIVO 11.05.2026'!$C$2:$C$712=$B67))} -> 0
B68: TECNICO DE EDIFICACOES | C68: {=SUMPRODUCT(ISNUMBER(SEARCH("741",'EFETIVO 11.05.2026'!$H$2:$H$712))*('EFETIVO 11.05.2026'!$G$2:$G$712="A")*('EFETIVO 11.05.2026'!$C$2:$C$712="TECNICO DE EDIFICACOES"))} -> 2 | D68: {=SUMPRODUCT(ISNUMBER(SEARCH("741",'EFETIVO 11.05.2026'!$H$2:$H$712))*('EFETIVO 11.05.2026'!$G$2:$G$712="D")*('EFETIVO 11.05.2026'!$C$2:$C$712="TECNICO DE EDIFICACOES"))} -> 2 | E68: =IFERROR(C68/$C$6,0) -> 0.010810811 | F68: {=SUMPRODUCT(ISNUMBER(SEARCH("741",'EFETIVO 11.05.2026'!$H$2:$H$712))*(('EFETIVO 11.05.2026'!$G$2:$G$712="F")+('EFETIVO 11.05.2026'!$G$2:$G$712="P")+('EFETIVO 11.05.2026'!$G$2:$G$712="T")+('EFETIVO 11.05.2026'!$G$2:$G$712="M"))*('EFETIVO 11.05.2026'!$C$2:$C$712=$B68))} -> 0
B69: TECNICO DE MECANICA | C69: {=SUMPRODUCT(ISNUMBER(SEARCH("741",'EFETIVO 11.05.2026'!$H$2:$H$712))*('EFETIVO 11.05.2026'!$G$2:$G$712="A")*('EFETIVO 11.05.2026'!$C$2:$C$712="TECNICO DE MECANICA"))} -> 1 | D69: {=SUMPRODUCT(ISNUMBER(SEARCH("741",'EFETIVO 11.05.2026'!$H$2:$H$712))*('EFETIVO 11.05.2026'!$G$2:$G$712="D")*('EFETIVO 11.05.2026'!$C$2:$C$712="TECNICO DE MECANICA"))} -> 0 | E69: =IFERROR(C69/$C$6,0) -> 0.0054054054 | F69: {=SUMPRODUCT(ISNUMBER(SEARCH("741",'EFETIVO 11.05.2026'!$H$2:$H$712))*(('EFETIVO 11.05.2026'!$G$2:$G$712="F")+('EFETIVO 11.05.2026'!$G$2:$G$712="P")+('EFETIVO 11.05.2026'!$G$2:$G$712="T")+('EFETIVO 11.05.2026'!$G$2:$G$712="M"))*('EFETIVO 11.05.2026'!$C$2:$C$712=$B69))} -> 0
B70: TECNICO DE SEGURANCA DO TRABALHO | C70: {=SUMPRODUCT(ISNUMBER(SEARCH("741",'EFETIVO 11.05.2026'!$H$2:$H$712))*('EFETIVO 11.05.2026'!$G$2:$G$712="A")*('EFETIVO 11.05.2026'!$C$2:$C$712="TECNICO DE SEGURANCA DO TRABALHO"))} -> 5 | D70: {=SUMPRODUCT(ISNUMBER(SEARCH("741",'EFETIVO 11.05.2026'!$H$2:$H$712))*('EFETIVO 11.05.2026'!$G$2:$G$712="D")*('EFETIVO 11.05.2026'!$C$2:$C$712="TECNICO DE SEGURANCA DO TRABALHO"))} -> 5 | E70: =IFERROR(C70/$C$6,0) -> 0.027027027 | F70: {=SUMPRODUCT(ISNUMBER(SEARCH("741",'EFETIVO 11.05.2026'!$H$2:$H$712))*(('EFETIVO 11.05.2026'!$G$2:$G$712="F")+('EFETIVO 11.05.2026'!$G$2:$G$712="P")+('EFETIVO 11.05.2026'!$G$2:$G$712="T")+('EFETIVO 11.05.2026'!$G$2:$G$712="M"))*('EFETIVO 11.05.2026'!$C$2:$C$712=$B70))} -> 0
B71: TECNICO EM ELETROTECNICA | C71: {=SUMPRODUCT(ISNUMBER(SEARCH("741",'EFETIVO 11.05.2026'!$H$2:$H$712))*('EFETIVO 11.05.2026'!$G$2:$G$712="A")*('EFETIVO 11.05.2026'!$C$2:$C$712="TECNICO EM ELETROTECNICA"))} -> 2 | D71: {=SUMPRODUCT(ISNUMBER(SEARCH("741",'EFETIVO 11.05.2026'!$H$2:$H$712))*('EFETIVO 11.05.2026'!$G$2:$G$712="D")*('EFETIVO 11.05.2026'!$C$2:$C$712="TECNICO EM ELETROTECNICA"))} -> 1 | E71: =IFERROR(C71/$C$6,0) -> 0.010810811 | F71: {=SUMPRODUCT(ISNUMBER(SEARCH("741",'EFETIVO 11.05.2026'!$H$2:$H$712))*(('EFETIVO 11.05.2026'!$G$2:$G$712="F")+('EFETIVO 11.05.2026'!$G$2:$G$712="P")+('EFETIVO 11.05.2026'!$G$2:$G$712="T")+('EFETIVO 11.05.2026'!$G$2:$G$712="M"))*('EFETIVO 11.05.2026'!$C$2:$C$712=$B71))} -> 0
B72: TOTAL | C72: =C6 -> 185 | D72: =C7 -> 87 | E72: =IFERROR(C72/$C$6,0) -> 1 | F72: =SUM(F14:F71) -> 6
B75: 3. Pessoas por Base — Projeto 741
B76: A coluna BASE está parcialmente preenchida na fonte. Linhas sem base aparecem em '(sem base)'.
B78: Base | C78: Ativos 741 | D78: Desligados 741 | E78: Afastados 741 | F78: Total registros
B79: (sem base) | C79: {=SUMPRODUCT(ISNUMBER(SEARCH("741",'EFETIVO 11.05.2026'!$H$2:$H$712))*('EFETIVO 11.05.2026'!$G$2:$G$712="A")*('EFETIVO 11.05.2026'!$I$2:$I$712=""))} -> 1 | D79: {=SUMPRODUCT(ISNUMBER(SEARCH("741",'EFETIVO 11.05.2026'!$H$2:$H$712))*('EFETIVO 11.05.2026'!$G$2:$G$712="D")*('EFETIVO 11.05.2026'!$I$2:$I$712=""))} -> 85 | E79: {=SUMPRODUCT(ISNUMBER(SEARCH("741",'EFETIVO 11.05.2026'!$H$2:$H$712))*(('EFETIVO 11.05.2026'!$G$2:$G$712="F")+('EFETIVO 11.05.2026'!$G$2:$G$712="P")+('EFETIVO 11.05.2026'!$G$2:$G$712="T")+('EFETIVO 11.05.2026'!$G$2:$G$712="M"))*('EFETIVO 11.05.2026'!$I$2:$I$712=""))} -> 0 | F79: =C79+D79+E79 -> 86
B80: AE | C80: {=SUMPRODUCT(ISNUMBER(SEARCH("741",'EFETIVO 11.05.2026'!$H$2:$H$712))*('EFETIVO 11.05.2026'!$G$2:$G$712="A")*('EFETIVO 11.05.2026'!$I$2:$I$712="AE"))} -> 83 | D80: {=SUMPRODUCT(ISNUMBER(SEARCH("741",'EFETIVO 11.05.2026'!$H$2:$H$712))*('EFETIVO 11.05.2026'!$G$2:$G$712="D")*('EFETIVO 11.05.2026'!$I$2:$I$712="AE"))} -> 0 | E80: {=SUMPRODUCT(ISNUMBER(SEARCH("741",'EFETIVO 11.05.2026'!$H$2:$H$712))*(('EFETIVO 11.05.2026'!$G$2:$G$712="F")+('EFETIVO 11.05.2026'!$G$2:$G$712="P")+('EFETIVO 11.05.2026'!$G$2:$G$712="T")+('EFETIVO 11.05.2026'!$G$2:$G$712="M"))*('EFETIVO 11.05.2026'!$I$2:$I$712="AE"))} -> 3 | F80: =C80+D80+E80 -> 86
B81: TAPERA | C81: {=SUMPRODUCT(ISNUMBER(SEARCH("741",'EFETIVO 11.05.2026'!$H$2:$H$712))*('EFETIVO 11.05.2026'!$G$2:$G$712="A")*('EFETIVO 11.05.2026'!$I$2:$I$712="TAPERA"))} -> 3 | D81: {=SUMPRODUCT(ISNUMBER(SEARCH("741",'EFETIVO 11.05.2026'!$H$2:$H$712))*('EFETIVO 11.05.2026'!$G$2:$G$712="D")*('EFETIVO 11.05.2026'!$I$2:$I$712="TAPERA"))} -> 0 | E81: {=SUMPRODUCT(ISNUMBER(SEARCH("741",'EFETIVO 11.05.2026'!$H$2:$H$712))*(('EFETIVO 11.05.2026'!$G$2:$G$712="F")+('EFETIVO 11.05.2026'!$G$2:$G$712="P")+('EFETIVO 11.05.2026'!$G$2:$G$712="T")+('EFETIVO 11.05.2026'!$G$2:$G$712="M"))*('EFETIVO 11.05.2026'!$I$2:$I$712="TAPERA"))} -> 0 | F81: =C81+D81+E81 -> 3
B82: UTE | C82: {=SUMPRODUCT(ISNUMBER(SEARCH("741",'EFETIVO 11.05.2026'!$H$2:$H$712))*('EFETIVO 11.05.2026'!$G$2:$G$712="A")*('EFETIVO 11.05.2026'!$I$2:$I$712="UTE"))} -> 97 | D82: {=SUMPRODUCT(ISNUMBER(SEARCH("741",'EFETIVO 11.05.2026'!$H$2:$H$712))*('EFETIVO 11.05.2026'!$G$2:$G$712="D")*('EFETIVO 11.05.2026'!$I$2:$I$712="UTE"))} -> 2 | E82: {=SUMPRODUCT(ISNUMBER(SEARCH("741",'EFETIVO 11.05.2026'!$H$2:$H$712))*(('EFETIVO 11.05.2026'!$G$2:$G$712="F")+('EFETIVO 11.05.2026'!$G$2:$G$712="P")+('EFETIVO 11.05.2026'!$G$2:$G$712="T")+('EFETIVO 11.05.2026'!$G$2:$G$712="M"))*('EFETIVO 11.05.2026'!$I$2:$I$712="UTE"))} -> 3 | F82: =C82+D82+E82 -> 102
B83: VAGA UTE | C83: {=SUMPRODUCT(ISNUMBER(SEARCH("741",'EFETIVO 11.05.2026'!$H$2:$H$712))*('EFETIVO 11.05.2026'!$G$2:$G$712="A")*('EFETIVO 11.05.2026'!$I$2:$I$712="VAGA UTE"))} -> 0 | D83: {=SUMPRODUCT(ISNUMBER(SEARCH("741",'EFETIVO 11.05.2026'!$H$2:$H$712))*('EFETIVO 11.05.2026'!$G$2:$G$712="D")*('EFETIVO 11.05.2026'!$I$2:$I$712="VAGA UTE"))} -> 0 | E83: {=SUMPRODUCT(ISNUMBER(SEARCH("741",'EFETIVO 11.05.2026'!$H$2:$H$712))*(('EFETIVO 11.05.2026'!$G$2:$G$712="F")+('EFETIVO 11.05.2026'!$G$2:$G$712="P")+('EFETIVO 11.05.2026'!$G$2:$G$712="T")+('EFETIVO 11.05.2026'!$G$2:$G$712="M"))*('EFETIVO 11.05.2026'!$I$2:$I$712="VAGA UTE"))} -> 0 | F83: =C83+D83+E83 -> 0
B84: TOTAL | C84: =SUM(C79:C83) -> 184 | D84: =SUM(D79:D83) -> 87 | E84: =SUM(E79:E83) -> 6 | F84: =SUM(F79:F83) -> 277
B87: 3.1 Pessoas por Função × Base — Projeto 741 (Ativos)
B88: Mesma lista de funções da Seção 2, contando apenas ativos (SIT=A) por base. Linhas sem função distinta no projeto 741 ficam zeradas.
A90: Função BR | B90: Função | C90: UTE | D90: AE | E90: TAPERA | F90: Total Ativos
B91: =B14 -> AJUDANTE DE CALDEIRARIA | C91: {=SUMPRODUCT(ISNUMBER(SEARCH("741",'EFETIVO 11.05.2026'!$H$2:$H$712))*('EFETIVO 11.05.2026'!$G$2:$G$712="A")*('EFETIVO 11.05.2026'!$C$2:$C$712=$B91)*('EFETIVO 11.05.2026'!$I$2:$I$712="UTE"))} -> 0 | D91: {=SUMPRODUCT(ISNUMBER(SEARCH("741",'EFETIVO 11.05.2026'!$H$2:$H$712))*('EFETIVO 11.05.2026'!$G$2:$G$712="A")*('EFETIVO 11.05.2026'!$C$2:$C$712=$B91)*('EFETIVO 11.05.2026'!$I$2:$I$712="AE"))} -> 0 | E91: {=SUMPRODUCT(ISNUMBER(SEARCH("741",'EFETIVO 11.05.2026'!$H$2:$H$712))*('EFETIVO 11.05.2026'!$G$2:$G$712="A")*('EFETIVO 11.05.2026'!$C$2:$C$712=$B91)*('EFETIVO 11.05.2026'!$I$2:$I$712="TAPERA"))} -> 0 | F91: =SUM(C91:E91) -> 0
B92: =B15 -> AJUDANTE DE ELETRICA PREDIAL | C92: {=SUMPRODUCT(ISNUMBER(SEARCH("741",'EFETIVO 11.05.2026'!$H$2:$H$712))*('EFETIVO 11.05.2026'!$G$2:$G$712="A")*('EFETIVO 11.05.2026'!$C$2:$C$712=$B92)*('EFETIVO 11.05.2026'!$I$2:$I$712="UTE"))} -> 1 | D92: {=SUMPRODUCT(ISNUMBER(SEARCH("741",'EFETIVO 11.05.2026'!$H$2:$H$712))*('EFETIVO 11.05.2026'!$G$2:$G$712="A")*('EFETIVO 11.05.2026'!$C$2:$C$712=$B92)*('EFETIVO 11.05.2026'!$I$2:$I$712="AE"))} -> 3 | E92: {=SUMPRODUCT(ISNUMBER(SEARCH("741",'EFETIVO 11.05.2026'!$H$2:$H$712))*('EFETIVO 11.05.2026'!$G$2:$G$712="A")*('EFETIVO 11.05.2026'!$C$2:$C$712=$B92)*('EFETIVO 11.05.2026'!$I$2:$I$712="TAPERA"))} -> 0 | F92: =SUM(C92:E92) -> 4
B93: =B16 -> AJUDANTE DE ELETROMECANICA PREDIAL | C93: {=SUMPRODUCT(ISNUMBER(SEARCH("741",'EFETIVO 11.05.2026'!$H$2:$H$712))*('EFETIVO 11.05.2026'!$G$2:$G$712="A")*('EFETIVO 11.05.2026'!$C$2:$C$712=$B93)*('EFETIVO 11.05.2026'!$I$2:$I$712="UTE"))} -> 2 | D93: {=SUMPRODUCT(ISNUMBER(SEARCH("741",'EFETIVO 11.05.2026'!$H$2:$H$712))*('EFETIVO 11.05.2026'!$G$2:$G$712="A")*('EFETIVO 11.05.2026'!$C$2:$C$712=$B93)*('EFETIVO 11.05.2026'!$I$2:$I$712="AE"))} -> 1 | E93: {=SUMPRODUCT(ISNUMBER(SEARCH("741",'EFETIVO 11.05.2026'!$H$2:$H$712))*('EFETIVO 11.05.2026'!$G$2:$G$712="A")*('EFETIVO 11.05.2026'!$C$2:$C$712=$B93)*('EFETIVO 11.05.2026'!$I$2:$I$712="TAPERA"))} -> 0 | F93: =SUM(C93:E93) -> 3
B94: =B17 -> AJUDANTE DE MANUTENCAO ELETRICA | C94: {=SUMPRODUCT(ISNUMBER(SEARCH("741",'EFETIVO 11.05.2026'!$H$2:$H$712))*('EFETIVO 11.05.2026'!$G$2:$G$712="A")*('EFETIVO 11.05.2026'!$C$2:$C$712=$B94)*('EFETIVO 11.05.2026'!$I$2:$I$712="UTE"))} -> 0 | D94: {=SUMPRODUCT(ISNUMBER(SEARCH("741",'EFETIVO 11.05.2026'!$H$2:$H$712))*('EFETIVO 11.05.2026'!$G$2:$G$712="A")*('EFETIVO 11.05.2026'!$C$2:$C$712=$B94)*('EFETIVO 11.05.2026'!$I$2:$I$712="AE"))} -> 1 | E94: {=SUMPRODUCT(ISNUMBER(SEARCH("741",'EFETIVO 11.05.2026'!$H$2:$H$712))*('EFETIVO 11.05.2026'!$G$2:$G$712="A")*('EFETIVO 11.05.2026'!$C$2:$C$712=$B94)*('EFETIVO 11.05.2026'!$I$2:$I$712="TAPERA"))} -> 0 | F94: =SUM(C94:E94) -> 1
B95: =B18 -> AJUDANTE DE MECANICA PREDIAL | C95: {=SUMPRODUCT(ISNUMBER(SEARCH("741",'EFETIVO 11.05.2026'!$H$2:$H$712))*('EFETIVO 11.05.2026'!$G$2:$G$712="A")*('EFETIVO 11.05.2026'!$C$2:$C$712=$B95)*('EFETIVO 11.05.2026'!$I$2:$I$712="UTE"))} -> 2 | D95: {=SUMPRODUCT(ISNUMBER(SEARCH("741",'EFETIVO 11.05.2026'!$H$2:$H$712))*('EFETIVO 11.05.2026'!$G$2:$G$712="A")*('EFETIVO 11.05.2026'!$C$2:$C$712=$B95)*('EFETIVO 11.05.2026'!$I$2:$I$712="AE"))} -> 0 | E95: {=SUMPRODUCT(ISNUMBER(SEARCH("741",'EFETIVO 11.05.2026'!$H$2:$H$712))*('EFETIVO 11.05.2026'!$G$2:$G$712="A")*('EFETIVO 11.05.2026'!$C$2:$C$712=$B95)*('EFETIVO 11.05.2026'!$I$2:$I$712="TAPERA"))} -> 0 | F95: =SUM(C95:E95) -> 2
B96: =B19 -> AJUDANTE DE PEDREIRO | C96: {=SUMPRODUCT(ISNUMBER(SEARCH("741",'EFETIVO 11.05.2026'!$H$2:$H$712))*('EFETIVO 11.05.2026'!$G$2:$G$712="A")*('EFETIVO 11.05.2026'!$C$2:$C$712=$B96)*('EFETIVO 11.05.2026'!$I$2:$I$712="UTE"))} -> 0 | D96: {=SUMPRODUCT(ISNUMBER(SEARCH("741",'EFETIVO 11.05.2026'!$H$2:$H$712))*('EFETIVO 11.05.2026'!$G$2:$G$712="A")*('EFETIVO 11.05.2026'!$C$2:$C$712=$B96)*('EFETIVO 11.05.2026'!$I$2:$I$712="AE"))} -> 0 | E96: {=SUMPRODUCT(ISNUMBER(SEARCH("741",'EFETIVO 11.05.2026'!$H$2:$H$712))*('EFETIVO 11.05.2026'!$G$2:$G$712="A")*('EFETIVO 11.05.2026'!$C$2:$C$712=$B96)*('EFETIVO 11.05.2026'!$I$2:$I$712="TAPERA"))} -> 0 | F96: =SUM(C96:E96) -> 0
B97: =B20 -> AJUDANTE DE PINTURA | C97: {=SUMPRODUCT(ISNUMBER(SEARCH("741",'EFETIVO 11.05.2026'!$H$2:$H$712))*('EFETIVO 11.05.2026'!$G$2:$G$712="A")*('EFETIVO 11.05.2026'!$C$2:$C$712=$B97)*('EFETIVO 11.05.2026'!$I$2:$I$712="UTE"))} -> 0 | D97: {=SUMPRODUCT(ISNUMBER(SEARCH("741",'EFETIVO 11.05.2026'!$H$2:$H$712))*('EFETIVO 11.05.2026'!$G$2:$G$712="A")*('EFETIVO 11.05.2026'!$C$2:$C$712=$B97)*('EFETIVO 11.05.2026'!$I$2:$I$712="AE"))} -> 2 | E97: {=SUMPRODUCT(ISNUMBER(SEARCH("741",'EFETIVO 11.05.2026'!$H$2:$H$712))*('EFETIVO 11.05.2026'!$G$2:$G$712="A")*('EFETIVO 11.05.2026'!$C$2:$C$712=$B97)*('EFETIVO 11.05.2026'!$I$2:$I$712="TAPERA"))} -> 0 | F97: =SUM(C97:E97) -> 2
B98: =B21 -> AJUDANTE DE PINTURA INDUSTRIAL | C98: {=SUMPRODUCT(ISNUMBER(SEARCH("741",'EFETIVO 11.05.2026'!$H$2:$H$712))*('EFETIVO 11.05.2026'!$G$2:$G$712="A")*('EFETIVO 11.05.2026'!$C$2:$C$712=$B98)*('EFETIVO 11.05.2026'!$I$2:$I$712="UTE"))} -> 0 | D98: {=SUMPRODUCT(ISNUMBER(SEARCH("741",'EFETIVO 11.05.2026'!$H$2:$H$712))*('EFETIVO 11.05.2026'!$G$2:$G$712="A")*('EFETIVO 11.05.2026'!$C$2:$C$712=$B98)*('EFETIVO 11.05.2026'!$I$2:$I$712="AE"))} -> 0 | E98: {=SUMPRODUCT(ISNUMBER(SEARCH("741",'EFETIVO 11.05.2026'!$H$2:$H$712))*('EFETIVO 11.05.2026'!$G$2:$G$712="A")*('EFETIVO 11.05.2026'!$C$2:$C$712=$B98)*('EFETIVO 11.05.2026'!$I$2:$I$712="TAPERA"))} -> 0 | F98: =SUM(C98:E98) -> 0
B99: =B22 -> ALMOXARIFE | C99: {=SUMPRODUCT(ISNUMBER(SEARCH("741",'EFETIVO 11.05.2026'!$H$2:$H$712))*('EFETIVO 11.05.2026'!$G$2:$G$712="A")*('EFETIVO 11.05.2026'!$C$2:$C$712=$B99)*('EFETIVO 11.05.2026'!$I$2:$I$712="UTE"))} -> 1 | D99: {=SUMPRODUCT(ISNUMBER(SEARCH("741",'EFETIVO 11.05.2026'!$H$2:$H$712))*('EFETIVO 11.05.2026'!$G$2:$G$712="A")*('EFETIVO 11.05.2026'!$C$2:$C$712=$B99)*('EFETIVO 11.05.2026'!$I$2:$I$712="AE"))} -> 1 | E99: {=SUMPRODUCT(ISNUMBER(SEARCH("741",'EFETIVO 11.05.2026'!$H$2:$H$712))*('EFETIVO 11.05.2026'!$G$2:$G$712="A")*('EFETIVO 11.05.2026'!$C$2:$C$712=$B99)*('EFETIVO 11.05.2026'!$I$2:$I$712="TAPERA"))} -> 0 | F99: =SUM(C99:E99) -> 2
B100: =B23 -> ARTIFICE | C100: {=SUMPRODUCT(ISNUMBER(SEARCH("741",'EFETIVO 11.05.2026'!$H$2:$H$712))*('EFETIVO 11.05.2026'!$G$2:$G$712="A")*('EFETIVO 11.05.2026'!$C$2:$C$712=$B100)*('EFETIVO 11.05.2026'!$I$2:$I$712="UTE"))} -> 10 | D100: {=SUMPRODUCT(ISNUMBER(SEARCH("741",'EFETIVO 11.05.2026'!$H$2:$H$712))*('EFETIVO 11.05.2026'!$G$2:$G$712="A")*('EFETIVO 11.05.2026'!$C$2:$C$712=$B100)*('EFETIVO 11.05.2026'!$I$2:$I$712="AE"))} -> 9 | E100: {=SUMPRODUCT(ISNUMBER(SEARCH("741",'EFETIVO 11.05.2026'!$H$2:$H$712))*('EFETIVO 11.05.2026'!$G$2:$G$712="A")*('EFETIVO 11.05.2026'!$C$2:$C$712=$B100)*('EFETIVO 11.05.2026'!$I$2:$I$712="TAPERA"))} -> 0 | F100: =SUM(C100:E100) -> 19
B101: =B24 -> ASSISTENTE ADMINISTRATIVO | C101: {=SUMPRODUCT(ISNUMBER(SEARCH("741",'EFETIVO 11.05.2026'!$H$2:$H$712))*('EFETIVO 11.05.2026'!$G$2:$G$712="A")*('EFETIVO 11.05.2026'!$C$2:$C$712=$B101)*('EFETIVO 11.05.2026'!$I$2:$I$712="UTE"))} -> 0 | D101: {=SUMPRODUCT(ISNUMBER(SEARCH("741",'EFETIVO 11.05.2026'!$H$2:$H$712))*('EFETIVO 11.05.2026'!$G$2:$G$712="A")*('EFETIVO 11.05.2026'!$C$2:$C$712=$B101)*('EFETIVO 11.05.2026'!$I$2:$I$712="AE"))} -> 3 | E101: {=SUMPRODUCT(ISNUMBER(SEARCH("741",'EFETIVO 11.05.2026'!$H$2:$H$712))*('EFETIVO 11.05.2026'!$G$2:$G$712="A")*('EFETIVO 11.05.2026'!$C$2:$C$712=$B101)*('EFETIVO 11.05.2026'!$I$2:$I$712="TAPERA"))} -> 0 | F101: =SUM(C101:E101) -> 3
B102: =B25 -> ASSISTENTE DE LOGISTICA I | C102: {=SUMPRODUCT(ISNUMBER(SEARCH("741",'EFETIVO 11.05.2026'!$H$2:$H$712))*('EFETIVO 11.05.2026'!$G$2:$G$712="A")*('EFETIVO 11.05.2026'!$C$2:$C$712=$B102)*('EFETIVO 11.05.2026'!$I$2:$I$712="UTE"))} -> 1 | D102: {=SUMPRODUCT(ISNUMBER(SEARCH("741",'EFETIVO 11.05.2026'!$H$2:$H$712))*('EFETIVO 11.05.2026'!$G$2:$G$712="A")*('EFETIVO 11.05.2026'!$C$2:$C$712=$B102)*('EFETIVO 11.05.2026'!$I$2:$I$712="AE"))} -> 1 | E102: {=SUMPRODUCT(ISNUMBER(SEARCH("741",'EFETIVO 11.05.2026'!$H$2:$H$712))*('EFETIVO 11.05.2026'!$G$2:$G$712="A")*('EFETIVO 11.05.2026'!$C$2:$C$712=$B102)*('EFETIVO 11.05.2026'!$I$2:$I$712="TAPERA"))} -> 0 | F102: =SUM(C102:E102) -> 2
... B115: =B38 -> COMPRADOR | C115: {=SUMPRODUCT(ISNUMBER(SEARCH("741",'EFETIVO 11.05.2026'!$H$2:$H$712))*('EFETIVO 11.05.2026'!$G$2:$G$712="A")*('EFETIVO 11.05.2026'!$C$2:$C$712=$B115)*('EFETIVO 11.05.2026'!$I$2:$I$712="UTE"))} -> 0 | D115: {=SUMPRODUCT(ISNUMBER(SEARCH("741",'EFETIVO 11.05.2026'!$H$2:$H$712))*('EFETIVO 11.05.2026'!$G$2:$G$712="A")*('EFETIVO 11.05.2026'!$C$2:$C$712=$B115)*('EFETIVO 11.05.2026'!$I$2:$I$712="AE"))} -> 2 | E115: {=SUMPRODUCT(ISNUMBER(SEARCH("741",'EFETIVO 11.05.2026'!$H$2:$H$712))*('EFETIVO 11.05.2026'!$G$2:$G$712="A")*('EFETIVO 11.05.2026'!$C$2:$C$712=$B115)*('EFETIVO 11.05.2026'!$I$2:$I$712="TAPERA"))} -> 0 | F115: =SUM(C115:E115) -> 2
B116: =B39 -> COORDENADOR DE MANUTENCAO | C116: 0 | D116: {=SUMPRODUCT(ISNUMBER(SEARCH("741",'EFETIVO 11.05.2026'!$H$2:$H$712))*('EFETIVO 11.05.2026'!$G$2:$G$712="A")*('EFETIVO 11.05.2026'!$C$2:$C$712=$B116)*('EFETIVO 11.05.2026'!$I$2:$I$712="AE"))} -> 0 | E116: {=SUMPRODUCT(ISNUMBER(SEARCH("741",'EFETIVO 11.05.2026'!$H$2:$H$712))*('EFETIVO 11.05.2026'!$G$2:$G$712="A")*('EFETIVO 11.05.2026'!$C$2:$C$712=$B116)*('EFETIVO 11.05.2026'!$I$2:$I$712="TAPERA"))} -> 0 | F116: =SUM(C116:E116) -> 0
B117: =B40 -> ELETRICISTA PREDIAL | C117: {=SUMPRODUCT(ISNUMBER(SEARCH("741",'EFETIVO 11.05.2026'!$H$2:$H$712))*('EFETIVO 11.05.2026'!$G$2:$G$712="A")*('EFETIVO 11.05.2026'!$C$2:$C$712=$B117)*('EFETIVO 11.05.2026'!$I$2:$I$712="UTE"))} -> 2 | D117: {=SUMPRODUCT(ISNUMBER(SEARCH("741",'EFETIVO 11.05.2026'!$H$2:$H$712))*('EFETIVO 11.05.2026'!$G$2:$G$712="A")*('EFETIVO 11.05.2026'!$C$2:$C$712=$B117)*('EFETIVO 11.05.2026'!$I$2:$I$712="AE"))} -> 2 | E117: {=SUMPRODUCT(ISNUMBER(SEARCH("741",'EFETIVO 11.05.2026'!$H$2:$H$712))*('EFETIVO 11.05.2026'!$G$2:$G$712="A")*('EFETIVO 11.05.2026'!$C$2:$C$712=$B117)*('EFETIVO 11.05.2026'!$I$2:$I$712="TAPERA"))} -> 0 | F117: =SUM(C117:E117) -> 4
B118: =B41 -> ENCARREGADO CIVIL | C118: {=SUMPRODUCT(ISNUMBER(SEARCH("741",'EFETIVO 11.05.2026'!$H$2:$H$712))*('EFETIVO 11.05.2026'!$G$2:$G$712="A")*('EFETIVO 11.05.2026'!$C$2:$C$712=$B118)*('EFETIVO 11.05.2026'!$I$2:$I$712="UTE"))} -> 1 | D118: {=SUMPRODUCT(ISNUMBER(SEARCH("741",'EFETIVO 11.05.2026'!$H$2:$H$712))*('EFETIVO 11.05.2026'!$G$2:$G$712="A")*('EFETIVO 11.05.2026'!$C$2:$C$712=$B118)*('EFETIVO 11.05.2026'!$I$2:$I$712="AE"))} -> 0 | E118: {=SUMPRODUCT(ISNUMBER(SEARCH("741",'EFETIVO 11.05.2026'!$H$2:$H$712))*('EFETIVO 11.05.2026'!$G$2:$G$712="A")*('EFETIVO 11.05.2026'!$C$2:$C$712=$B118)*('EFETIVO 11.05.2026'!$I$2:$I$712="TAPERA"))} -> 0 | F118: =SUM(C118:E118) -> 1
B119: =B42 -> ENCARREGADO DE AREAS VERDES | C119: {=SUMPRODUCT(ISNUMBER(SEARCH("741",'EFETIVO 11.05.2026'!$H$2:$H$712))*('EFETIVO 11.05.2026'!$G$2:$G$712="A")*('EFETIVO 11.05.2026'!$C$2:$C$712=$B119)*('EFETIVO 11.05.2026'!$I$2:$I$712="UTE"))} -> 1 | D119: {=SUMPRODUCT(ISNUMBER(SEARCH("741",'EFETIVO 11.05.2026'!$H$2:$H$712))*('EFETIVO 11.05.2026'!$G$2:$G$712="A")*('EFETIVO 11.05.2026'!$C$2:$C$712=$B119)*('EFETIVO 11.05.2026'!$I$2:$I$712="AE"))} -> 1 | E119: {=SUMPRODUCT(ISNUMBER(SEARCH("741",'EFETIVO 11.05.2026'!$H$2:$H$712))*('EFETIVO 11.05.2026'!$G$2:$G$712="A")*('EFETIVO 11.05.2026'!$C$2:$C$712=$B119)*('EFETIVO 11.05.2026'!$I$2:$I$712="TAPERA"))} -> 0 | F119: =SUM(C119:E119) -> 2
B120: =B43 -> ENCARREGADO DE CONSERVACAO E LIMPEZA | C120: {=SUMPRODUCT(ISNUMBER(SEARCH("741",'EFETIVO 11.05.2026'!$H$2:$H$712))*('EFETIVO 11.05.2026'!$G$2:$G$712="A")*('EFETIVO 11.05.2026'!$C$2:$C$712=$B120)*('EFETIVO 11.05.2026'!$I$2:$I$712="UTE"))} -> 1 | D120: {=SUMPRODUCT(ISNUMBER(SEARCH("741",'EFETIVO 11.05.2026'!$H$2:$H$712))*('EFETIVO 11.05.2026'!$G$2:$G$712="A")*('EFETIVO 11.05.2026'!$C$2:$C$712=$B120)*('EFETIVO 11.05.2026'!$I$2:$I$712="AE"))} -> 1 | E120: {=SUMPRODUCT(ISNUMBER(SEARCH("741",'EFETIVO 11.05.2026'!$H$2:$H$712))*('EFETIVO 11.05.2026'!$G$2:$G$712="A")*('EFETIVO 11.05.2026'!$C$2:$C$712=$B120)*('EFETIVO 11.05.2026'!$I$2:$I$712="TAPERA"))} -> 0 | F120: =SUM(C120:E120) -> 2
...

Sheet EFETIVO 11.05.2026
A1: CHAPA | B1: NOME | C1: FUNÇÃO | D1: CPF | E1: ADMISSÃO | F1: DEMISSÃO | G1: SIT | H1: PROJETO | I1: BASE | J1: CARTEIRA
A2: 21283 | B2: ABIBA COSTA SALAMI MARQUES | C2: PLANEJADOR | D2: 14778656750 | E2: 45779 | F2: 45819 | G2: D | H2: PROJETO 743 - FACILITIES MULT CABIUNAS-SINTRAINDISTAL | I2: CABIUNAS
A3: 22022 | B3: ABILIO BOMFIM DA SILVA NETO | C3: PLANEJADOR | D3: 16262817778 | E3: 45826 | F3: 45964 | G3: D | H3: PROJETO 743 - FACILITIES MULT CABIUNAS-SINTRAINDISTAL | I3: CABIUNAS
A4: 22357 | B4: JULIO CESAR FERNANDES | C4: AJUDANTE DE BOMBEIRO PREDIAL | D4: 90158920759 | E4: 45840 | G4: A | H4: PROJETO 743 - FACILITIES MULT CABIUNAS-SINTRAINDISTAL | I4: BARRA DO FURADO | J4: CIVIL
A5: 20764 | B5: BRUNO SACRAMENTO SANTANA | C5: AJUDANTE DE ELETRICA PREDIAL | D5: 14215895758 | E5: 45756 | G5: A | H5: PROJETO 741 - FACILITIES MULT CABIUNAS UTE/AE-SINTRAINDISTAL | I5: AE | J5: ELETRICA
A6: 20769 | B6: ADRIANO CANDAL LEAL | C6: TECNICO DE SEGURANCA DO TRABALHO | D6: 9922726700 | E6: 45756 | F6: 45764 | G6: D | H6: PROJETO 741 - FACILITIES MULT CABIUNAS UTE/AE-SINTRAINDISTAL | I6: UTE
A7: 22919 | B7: LUIZ CESAR MADUREIRA NEVES | C7: AJUDANTE DE BOMBEIRO PREDIAL | D7: 18040867703 | E7: 45890 | G7: A | H7: PROJETO 743 - FACILITIES MULT CABIUNAS-SINTRAINDISTAL | I7: CABIUNAS | J7: CIVIL
A8: 21808 | B8: ADRIANO DA SILVA SOUSA | C8: AUXILIAR DE JARDINAGEM | D8: 16821398755 | E8: 45810 | F8: 45904 | G8: D | H8: PROJETO 743 - FACILITIES MULT CABIUNAS-SEEACEC | I8: CABIUNAS
A9: 21908 | B9: LUIZ FELIPE DA SILVA MARTINS | C9: AJUDANTE DE BOMBEIRO PREDIAL | D9: 12898637769 | E9: 45820 | G9: A | H9: PROJETO 743 - FACILITIES MULT CABIUNAS-SINTRAINDISTAL | I9: CABIUNAS | J9: CIVIL
A10: 20454 | B10: CAUA SILVA DE PAULA | C10: AJUDANTE DE ELETRICA PREDIAL | D10: 18886236751 | E10: 45729 | G10: A | H10: PROJETO 741 - FACILITIES MULT CABIUNAS UTE/AE-SINTRAINDISTAL | I10: AE | J10: ELETRICA
A11: 21753 | B11: LEONARDO STODUTO MUNIZ | C11: AJUDANTE DE ELETRICA PREDIAL | D11: 12101146746 | E11: 45810 | G11: A | H11: PROJETO 741 - FACILITIES MULT CABIUNAS UTE/AE-SINTRAINDISTAL | I11: UTE | J11: ELETRICA
A12: 21001 | B12: NATAN SAMUEL MONTEIRO FORTES | C12: AJUDANTE DE ELETRICA PREDIAL | D12: 16187094700 | E12: 45761 | G12: A | H12: PROJETO 741 - FACILITIES MULT CABIUNAS UTE/AE-SINTRAINDISTAL | I12: AE | J12: ELETRICA
A13: 21272 | B13: LUCAS OLIVEIRA DE PAULA | C13: AJUDANTE DE CALDEIRARIA PREDIAL | D13: 15467886703 | E13: 45779 | G13: A | H13: PROJETO 743 - FACILITIES MULT CABIUNAS-SINTRAINDISTAL | I13: CABIUNAS | J13: CIVIL
A14: 23249 | B14: ALDEMIR SCHWARTZ DA SILVA JUNIOR | C14: JARDINEIRO | D14: 13262226785 | E14: 45912 | F14: 46090 | G14: D | H14: PROJETO 743 - FACILITIES MULT CABIUNAS-SEEACEC | I14: CABIUNAS
A15: 20766 | B15: FILIPE LEITE DA CRUZ | C15: AJUDANTE DE ELETROMECANICA PREDIAL | D15: 19878182703 | E15: 45756 | G15: A | H15: PROJETO 741 - FACILITIES MULT CABIUNAS UTE/AE-SINTRAINDISTAL | I15: AE | J15: MECANICA
A16: 22887 | B16: LUIS GUSTAVO SILVA GEMINO | C16: AJUDANTE DE CARPINTEIRO | D16: 14081348707 | E16: 45889 | G16: A | H16: PROJETO 743 - FACILITIES MULT CABIUNAS-SINTRAINDISTAL | I16: CABIUNAS | J16: CIVIL
A17: 23762 | B17: ALESSANDRO FONTES CABRAL | C17: AUXILIAR DE SERVICOS GERAIS | D17: 16375884705 | E17: 45964 | F17: 46059 | G17: D | H17: PROJETO 741 - FACILITIES MULT CABIUNAS UTE/AE-SEEACEC
A18: 22918 | B18: THIAGO ILDEBRANDO FINAMOR | C18: AJUDANTE DE CARPINTEIRO | D18: 13096838755 | E18: 45890 | G18: A | H18: PROJETO 743 - FACILITIES MULT CABIUNAS-SINTRAINDISTAL | I18: CABIUNAS | J18: CIVIL
A19: 21777 | B19: ALEX BERNARDO RODRIGUES | C19: ESTIVAS | D19: 10112667414 | E19: 45810 | F19: 45842 | G19: D | H19: PROJETO 743 - FACILITIES MULT CABIUNAS-SINTRAINDISTAL | I19: CABIUNAS
A20: 21140 | B20: ALESSANDRO PEREIRA BORGES | C20: AJUDANTE DE ELETRICA PREDIAL | D20: 2782522574 | E20: 45772 | G20: A | H20: PROJETO 743 - FACILITIES MULT CABIUNAS-SINTRAINDISTAL | I20: CABIUNAS | J20: OPERACAO
A21: 22517 | B21: ALEX SALES DA COSTA | C21: ENCARREGADO CIVIL | D21: 12216776750 | E21: 45852 | F21: 45975 | G21: D | H21: PROJETO 741 - FACILITIES MULT CABIUNAS UTE/AE-SINTRAINDISTAL
A22: 21069 | B22: ALEX SANDRO CORREA VIANA | C22: ELETRICISTA PREDIAL | D22: 3049054700 | E22: 45763 | F22: 45847 | G22: D | H22: PROJETO 743 - FACILITIES MULT CABIUNAS-SINTRAINDISTAL | I22: CABIUNAS
A23: 23136 | B23: GABRIEL DE ALMEIDA SOUTO | C23: AJUDANTE DE ELETRICA PREDIAL | D23: 17651694708 | E23: 45903 | G23: A | H23: PROJETO 743 - FACILITIES MULT CABIUNAS-SINTRAINDISTAL | I23: CABIUNAS | J23: ELETRICA
A24: 22505 | B24: JOAO PEDRO MELLO | C24: AJUDANTE DE ELETRICA PREDIAL | D24: 15467827707 | E24: 45849 | G24: A | H24: PROJETO 743 - FACILITIES MULT CABIUNAS-SINTRAINDISTAL | I24: CABIUNAS | J24: ELETRICA
A25: 21833 | B25: JOAO VITOR CORDEIRO LUNA | C25: AJUDANTE DE ELETRICA PREDIAL | D25: 13169925784 | E25: 45810 | G25: A | H25: PROJETO 743 - FACILITIES MULT CABIUNAS-SINTRAINDISTAL | I25: CABIUNAS | J25: OPERACAO
A26: 22275 | B26: ALEXANDRE GUEDES BARBOSA | C26: AJUDANTE DE ELETRICA PREDIAL | D26: 3268742750 | E26: 45839 | F26: 46120 | G26: D | H26: PROJETO 743 - FACILITIES MULT CABIUNAS-SINTRAINDISTAL | I26: CABIUNAS
A27: 21733 | B27: ALEXANDRE SILVA SANTOS | C27: AUXILIAR DE JARDINAGEM | D27: 17214072785 | E27: 45810 | F27: 45819 | G27: D | H27: PROJETO 741 - FACILITIES MULT CABIUNAS UTE/AE-SEEACEC
A28: 21262 | B28: KENNY GABRIEL RIBEIRO TEIXEIRA | C28: AJUDANTE DE ELETROMECANICA PREDIAL | D28: 15437298781 | E28: 45779 | G28: A | H28: PROJETO 741 - FACILITIES MULT CABIUNAS UTE/AE-SINTRAINDISTAL | I28: UTE | J28: ELETRICA
A29: 21316 | B29: THIAGO CORREA SIQUEIRA | C29: AJUDANTE DE ELETROMECANICA PREDIAL | D29: 12694893724 | E29: 45779 | G29: A | H29: PROJETO 741 - FACILITIES MULT CABIUNAS UTE/AE-SINTRAINDISTAL | I29: UTE | J29: ELETRICA
A30: 21166 | B30: LUCAS NASCIMENTO FERREIRA | C30: AJUDANTE DE ELETRICA PREDIAL | D30: 19156831730 | E30: 45772 | G30: A | H30: PROJETO 743 - FACILITIES MULT CABIUNAS-SINTRAINDISTAL | I30: CABIUNAS | J30: ELETRICA
A31: 20942 | B31: JOAO FELIPE DE OLIVEIRA ALMEIDA | C31: AJUDANTE DE MANUTENCAO ELETRICA | D31: 17769571723 | E31: 45761 | G31: A | H31: PROJETO 741 - FACILITIES MULT CABIUNAS UTE/AE-SINTRAINDISTAL | I31: AE | J31: MECANICA
A32: 22892 | B32: RAFAEL ALVES DA SILVA | C32: AJUDANTE DE ELETRICA PREDIAL | D32: 6019189759 | E32: 45889 | G32: A | H32: PROJETO 743 - FACILITIES MULT CABIUNAS-SINTRAINDISTAL | I32: CABIUNAS | J32: ELETRICA
A33: 22831 | B33: ALLEFY KELVI SOUZA SANTOS | C33: ELETRICISTA PREDIAL | D33: 18498193788 | E33: 45887 | F33: 46083 | G33: D | H33: PROJETO 743 - FACILITIES MULT CABIUNAS-SINTRAINDISTAL | I33: CABIUNAS
A34: 21160 | B34: AMANDA DE CARVALHO BELO DA SILVA | C34: AUXILIAR DE SERVICOS GERAIS | D34: 16083637759 | E34: 45772 | F34: 45881 | G34: D | H34: PROJETO 743 - FACILITIES MULT CABIUNAS-SEEACEC | I34: CABIUNAS
A35: 20501 | B35: AMANDA PORTUGAL NUNES | C35: PLANEJADOR | D35: 15454281743 | E35: 45737 | F35: 45924 | G35: D | H35: PROJETO 741 - FACILITIES MULT CABIUNAS UTE/AE-SINTRAINDISTAL
A36: 21330 | B36: RHAY DINIZ BUENO MADUREIRA | C36: AJUDANTE DE ELETRICA PREDIAL | D36: 19729268703 | E36: 45779 | G36: A | H36: PROJETO 743 - FACILITIES MULT CABIUNAS-SINTRAINDISTAL | I36: CABIUNAS | J36: OPERACAO
A37: 21824 | B37: GAUDENCIO CARLOS DOS SANTOS | C37: AJUDANTE DE MECANICA PREDIAL | D37: 9304164737 | E37: 45810 | G37: A | H37: PROJETO 741 - FACILITIES MULT CABIUNAS UTE/AE-SINTRAINDISTAL | I37: UTE | J37: MECANICA
A38: 21371 | B38: MATHEUS ANDRE CARDIM | C38: AJUDANTE DE MECANICA PREDIAL | D38: 15443282735 | E38: 45782 | G38: A | H38: PROJETO 741 - FACILITIES MULT CABIUNAS UTE/AE-SINTRAINDISTAL | I38: UTE | J38: MECANICA
A39: 21780 | B39: VALMIR SILVA VIANA NETO | C39: AJUDANTE DE ELETRICA PREDIAL | D39: 19569910771 | E39: 45810 | G39: A | H39: PROJETO 743 - FACILITIES MULT CABIUNAS-SINTRAINDISTAL | I39: CABIUNAS | J39: OPERACAO
A40: 23944 | B40: JOAO PEDRO SANTOS CARDIM | C40: AJUDANTE DE MANUTENCAO ELETRICA | D40: 18389906740 | E40: 46008 | G40: A | H40: PROJETO 743 - FACILITIES MULT CABIUNAS-SINTRAINDISTAL | I40: CABIUNAS | J40: ELETRICA
A41: 24786 | B41: LUCAS SOUZA MEDEIROS DA SILVA DE OLIVEIRA | C41: AJUDANTE DE MANUTENCAO ELETRICA | D41: 18083991708 | E41: 46128 | G41: A | H41: PROJETO 743 - FACILITIES MULT CABIUNAS-SINTRAINDISTAL | I41: BARRA DO FURADO | J41: ELETRICA
A42: 23949 | B42: MATHEUS FERREIRA CALDEIRA | C42: AJUDANTE DE MANUTENCAO ELETRICA | D42: 6220364759 | E42: 46008 | G42: A | H42: PROJETO 743 - FACILITIES MULT CABIUNAS-SINTRAINDISTAL | I42: CABIUNAS | J42: ELETRICA
A43: 23753 | B43: DIOGO NOGUEIRA DE ALMEIDA | C43: AJUDANTE DE PINTURA | D43: 13744630781 | E43: 45964 | G43: A | H43: PROJETO 741 - FACILITIES MULT CABIUNAS UTE/AE-SINTRAINDISTAL | I43: AE | J43: CIVIL
A44: 21260 | B44: ANDERSON BRAGA | C44: PINTOR | D44: 13732914780 | E44: 45772 | F44: 45876 | G44: D | H44: PROJETO 741 - FACILITIES MULT CABIUNAS UTE/AE-SINTRAINDISTAL
A45: 24759 | B45: WALDIR PEREIRA DE SOUZA | C45: AJUDANTE DE MANUTENCAO ELETRICA | D45: 16910375750 | E45: 46127 | G45: A | H45: PROJETO 743 - FACILITIES MULT CABIUNAS-SINTRAINDISTAL | I45: CABIUNAS | J45: ELETRICA
A46: 22764 | B46: ANDERSON GUIMARAES GREGORIO | C46: MONTADOR DE ANDAIMES | D46: 8282944530 | E46: 45877 | F46: 45902 | G46: D | H46: PROJETO 741 - FACILITIES MULT CABIUNAS UTE/AE-SINTRAINDISTAL
A47: 23754 | B47: GUILHERME OLIVEIRA FERREIRA | C47: AJUDANTE DE PINTURA | D47: 9804875608 | E47: 45964 | G47: A | H47: PROJETO 741 - FACILITIES MULT CABIUNAS UTE/AE-SINTRAINDISTAL | I47: AE | J47: CIVIL
A48: 22381 | B48: ANDRE ARAUJO DOS SANTOS | C48: ARTIFICE | D48: 3096407509 | E48: 45845 | F48: 45922 | G48: D | H48: PROJETO 743 - FACILITIES MULT CABIUNAS-SINTRAINDISTAL | I48: CABIUNAS
A49: 21550 | B49: ANDRE DA SILVA MARINHO | C49: OPERADOR DE ROCADEIRA | D49: 12878011708 | E49: 45785 | F49: 45962 | G49: D | H49: PROJETO 743 - FACILITIES MULT CABIUNAS-SEEACEC | I49: CABIUNAS
A50: 20466 | B50: ANDRE DE JESUS SOUZA | C50: AUXILIAR DE SERVICOS GERAIS | D50: 1322069514 | E50: 45730 | F50: 45873 | G50: D | H50: PROJETO 741 - FACILITIES MULT CABIUNAS UTE/AE-SEEACEC
A51: 22917 | B51: JOSE AIRES DA SILVA | C51: AJUDANTE DE MARCENEIRO | D51: 3042563316 | E51: 45890 | G51: A | H51: PROJETO 743 - FACILITIES MULT CABIUNAS-SINTRAINDISTAL | I51: CABIUNAS | J51: CIVIL
A52: 21751 | B52: ADENILSON LUIZ DA SILVA | C52: ALMOXARIFE | D52: 4895295699 | E52: 45810 | G52: A | H52: PROJETO 741 - FACILITIES MULT CABIUNAS UTE/AE-SINTRAINDISTAL | I52: AE | J52: SUPRIMENTOS
A53: 21101 | B53: PATRICK MUNIZ ALVARENGA | C53: AJUDANTE DE MARCENEIRO | D53: 12769806718 | E53: 45764 | G53: A | H53: PROJETO 743 - FACILITIES MULT CABIUNAS-SINTRAINDISTAL | I53: CABIUNAS | J53: CIVIL
A54: 22697 | B54: DANIEL GONCALVES DA SILVA | C54: AJUDANTE DE MECANICA PREDIAL | D54: 9872059780 | E54: 45870 | G54: A | H54: PROJETO 743 - FACILITIES MULT CABIUNAS-SINTRAINDISTAL | I54: CABIUNAS | J54: ELETROMECANICA
A55: 22778 | B55: JOSUE DA CONCEICAO PESSANHA | C55: AJUDANTE DE MECANICA PREDIAL | D55: 14551868728 | E55: 45880 | G55: A | H55: PROJETO 743 - FACILITIES MULT CABIUNAS-SINTRAINDISTAL | I55: CABIUNAS | J55: ELETROMECANICA
A56: 22835 | B56: NADILTON SANTOS DE JESUS | C56: AJUDANTE DE MECANICA PREDIAL | D56: 2840590565 | E56: 45887 | G56: A | H56: PROJETO 743 - FACILITIES MULT CABIUNAS-SINTRAINDISTAL | I56: CABIUNAS | J56: ELETROMECANICA
A57: 24398 | B57: VANESSA DE OLIVEIRA MACHARETE | C57: ALMOXARIFE | D57: 9243758764 | E57: 46099 | G57: A | H57: PROJETO 741 - FACILITIES MULT CABIUNAS UTE/AE-SINTRAINDISTAL | I57: UTE | J57: SUPRIMENTOS
A58: 21064 | B58: ADRIANO DA SILVA MOREIRA | C58: AJUDANTE DE PEDREIRO | D58: 8382774709 | E58: 45763 | G58: A | H58: PROJETO 743 - FACILITIES MULT CABIUNAS-SINTRAINDISTAL | I58: CABIUNAS | J58: CIVIL
A59: 22006 | B59: ARIANE AMANDA AUGUSTO GERMANO | C59: INSPETOR PREDIAL | D59: 13761288700 | E59: 45825 | F59: 45840 | G59: D | H59: PROJETO 743 - FACILITIES MULT CABIUNAS-SINTRAINDISTAL | I59: CABIUNAS
A60: 22920 | B60: ARISTIDES MARTINS DE OLIVEIRA NETO | C60: AJUDANTE DE ELETROMECANICA PREDIAL | D60: 16959168759 | E60: 45890 | F60: 45964 | G60: D | H60: PROJETO 743 - FACILITIES MULT CABIUNAS-SINTRAINDISTAL | I60: CABIUNAS
A61: 21180 | B61: DANIEL BUENO MARQUES | C61: AJUDANTE DE PEDREIRO | D61: 5929696730 | E61: 45772 | G61: A | H61: PROJETO 743 - FACILITIES MULT CABIUNAS-SINTRAINDISTAL | I61: CABIUNAS | J61: CIVIL
A62: 21308 | B62: EMERSON BRANDAO SILVA | C62: AJUDANTE DE PEDREIRO | D62: 15449161751 | E62: 45779 | G62: A | H62: PROJETO 743 - FACILITIES MULT CABIUNAS-SINTRAINDISTAL | I62: CABIUNAS | J62: CIVIL
A63: 20772 | B63: ARTHUR FRANCISCO DA PAIXAO | C63: AJUDANTE DE ELETROMECANICA PREDIAL | D63: 17694549777 | E63: 45756 | F63: 45874 | G63: D | H63: PROJETO 741 - FACILITIES MULT CABIUNAS UTE/AE-SINTRAINDISTAL
A64: 21822 | B64: ARTHUR GABRIEL SANTOS | C64: AUXILIAR DE JARDINAGEM | D64: 16866880750 | E64: 45810 | F64: 46064 | G64: D | H64: PROJETO 743 - FACILITIES MULT CABIUNAS-SEEACEC | I64: CABIUNAS
A65: 21830 | B65: ARTHUR MARTINS SILVA | C65: PINTOR | D65: 19771072730 | E65: 45810 | F65: 46066 | G65: D | H65: PROJETO 743 - FACILITIES MULT CABIUNAS-SINTRAINDISTAL | I65: CABIUNAS
A66: 21061 | B66: ANDERSON SOUZA DA SILVA | C66: ARTIFICE | D66: 15965366752 | E66: 45763 | G66: A | H66: PROJETO 741 - FACILITIES MULT CABIUNAS UTE/AE-SINTRAINDISTAL | I66: UTE | J66: CIVIL
A67: 23138 | B67: FILIPE LEITE AZEVEDO | C67: AJUDANTE DE PEDREIRO | D67: 15826032782 | E67: 45903 | G67: A | H67: PROJETO 743 - FACILITIES MULT CABIUNAS-SINTRAINDISTAL | I67: CABIUNAS | J67: CIVIL
A68: 21790 | B68: JOSE CARLOS SILVA DOS SANTOS | C68: AJUDANTE DE PEDREIRO | D68: 17299623781 | E68: 45810 | G68: A | H68: PROJETO 743 - FACILITIES MULT CABIUNAS-SINTRAINDISTAL | I68: CABIUNAS | J68: CIVIL
A69: 24347 | B69: ANDRE GOMES DA SILVA | C69: ARTIFICE | D69: 9833303790 | E69: 46093 | G69: A | H69: PROJETO 741 - FACILITIES MULT CABIUNAS UTE/AE-SINTRAINDISTAL | I69: UTE | J69: CIVIL
A70: 22889 | B70: LEONARDO DIAS DOS SANTOS MACHADO | C70: AJUDANTE DE PEDREIRO | D70: 3060826757 | E70: 45889 | G70: A | H70: PROJETO 743 - FACILITIES MULT CABIUNAS-SINTRAINDISTAL | I70: CABIUNAS | J70: CIVIL
A71: 22910 | B71: MARCIO CLAUDIO MOTA SILVEIRA | C71: AJUDANTE DE PEDREIRO | D71: 17580281732 | E71: 45890 | G71: A | H71: PROJETO 743 - FACILITIES MULT CABIUNAS-SINTRAINDISTAL | I71: CABIUNAS | J71: CIVIL
A72: 21426 | B72: BRAIAM NOGUEIRA SOARES | C72: AJUDANTE DE PINTURA | D72: 15982421723 | E72: 45784 | F72: 45842 | G72: D | H72: PROJETO 743 - FACILITIES MULT CABIUNAS-SINTRAINDISTAL | I72: CABIUNAS
A73: 21810 | B73: PATRICK GOMES MANHAES | C73: AJUDANTE DE PEDREIRO | D73: 17691088744 | E73: 45810 | G73: A | H73: PROJETO 743 - FACILITIES MULT CABIUNAS-SINTRAINDISTAL | I73: BARRA DO FURADO | J73: CIVIL
A74: 21403 | B74: CARLOS ANTONIO DOS SANTOS GENEROSO | C74: ARTIFICE | D74: 91724015753 | E74: 45783 | G74: A | H74: PROJETO 741 - FACILITIES MULT CABIUNAS UTE/AE-SINTRAINDISTAL | I74: UTE | J74: CIVIL
A75: 21288 | B75: BRENO ROSA DE OLIVEIRA | C75: MECANICO | D75: 17282607796 | E75: 45779 | F75: 46066 | G75: D | H75: PROJETO 743 - FACILITIES MULT CABIUNAS-SINTRAINDISTAL | I75: CABIUNAS
A76: 21647 | B76: BRENO HENRIQUE DAUMAS PEREIRA | C76: AJUDANTE DE PINTURA | D76: 14724426799 | E76: 45792 | G76: A | H76: PROJETO 743 - FACILITIES MULT CABIUNAS-SINTRAINDISTAL | I76: CABIUNAS | J76: CIVIL
A77: 22061 | B77: BRUNO GOMES DE SOUZA | C77: MECANICO | D77: 17703753769 | E77: 45828 | F77: 45870 | G77: D | H77: PROJETO 743 - FACILITIES MULT CABIUNAS-SINTRAINDISTAL | I77: CABIUNAS
A78: 22024 | B78: GUSTAVO NASCIMENTO DUTRA | C78: AJUDANTE DE PINTURA | D78: 6589409706 | E78: 45826 | G78: A | H78: PROJETO 743 - FACILITIES MULT CABIUNAS-SINTRAINDISTAL | I78: CABIUNAS | J78: CIVIL
A79: 21661 | B79: BRUNO MARTINS ROCHA | C79: AJUDANTE DE CALDEIRARIA | D79: 16697585757 | E79: 45793 | F79: 46129 | G79: D | H79: PROJETO 741 - FACILITIES MULT CABIUNAS UTE/AE-SINTRAINDISTAL
A80: 24020 | B80: JACKSON DOUGLAS MADUREIRA DE PAULA | C80: AJUDANTE DE PINTURA | D80: 13435218746 | E80: 46037 | G80: A | H80: PROJETO 743 - FACILITIES MULT CABIUNAS-SINTRAINDISTAL | I80: CABIUNAS | J80: CIVIL
A81: 21703 | B81: CARLOS AUGUSTO POSES DO NASCIMENTO | C81: ARTIFICE | D81: 4188894733 | E81: 45797 | G81: A | H81: PROJETO 741 - FACILITIES MULT CABIUNAS UTE/AE-SINTRAINDISTAL | I81: UTE | J81: CIVIL
A82: 21786 | B82: SIDNEY BATISTA LANDIM | C82: AJUDANTE DE PINTURA | D82: 8285844510 | E82: 45810 | G82: A | H82: PROJETO 743 - FACILITIES MULT CABIUNAS-SINTRAINDISTAL | I82: CABIUNAS | J82: CIVIL
A83: 20765 | B83: BRUNO VENANCIO LIMA | C83: OPERADOR DE ROCADEIRA | D83: 16783388778 | E83: 45756 | F83: 45940 | G83: D | H83: PROJETO 741 - FACILITIES MULT CABIUNAS UTE/AE-SEEACEC
A84: 21897 | B84: CAIO GABRIEL DA SILVA SANTOS LIMA | C84: AUXILIAR DE JARDINAGEM | D84: 21260225798 | E84: 45818 | F84: 45980 | G84: D | H84: PROJETO 743 - FACILITIES MULT CABIUNAS-SEEACEC | I84: CABIUNAS
A85: 22047 | B85: THIAGO MANHAES GOMES | C85: AJUDANTE DE PINTURA | D85: 12205633740 | E85: 45828 | G85: A | H85: PROJETO 743 - FACILITIES MULT CABIUNAS-SINTRAINDISTAL | I85: BARRA DO FURADO | J85: CIVIL
A86: 21783 | B86: MANOEL CAETANO DAS CANDEIAS | C86: AJUDANTE DE PINTURA INDUSTRIAL | D86: 92360440772 | E86: 45810 | G86: A | H86: PROJETO 743 - FACILITIES MULT CABIUNAS-SINTRAINDISTAL | I86: CABIUNAS | J86: CIVIL
A87: 22353 | B87: CARLOS ALBERTO NUNES BARBOSA | C87: ELETRICISTA | D87: 18950640740 | E87: 45840 | F87: 45853 | G87: D | H87: PROJETO 743 - FACILITIES MULT CABIUNAS-SINTRAINDISTAL | I87: CABIUNAS
A88: 24783 | B88: HIAN DO NASCIMENTO QUEIROZ | C88: AJUDANTE DE REFRIGERACAO | D88: 20314597751 | E88: 46128 | G88: A | H88: PROJETO 743 - FACILITIES MULT CABIUNAS-SINTRAINDISTAL | I88: CABIUNAS | J88: REFRIGERACAO
A89: 21328 | B89: CARLOS FRANCISCO CABRAL BESSA | C89: ARTIFICE | D89: 8205279713 | E89: 45779 | G89: A | H89: PROJETO 741 - FACILITIES MULT CABIUNAS UTE/AE-SINTRAINDISTAL | I89: UTE | J89: CIVIL
A90: 23770 | B90: FERNANDO LOPES DA SILVA | C90: ARTIFICE | D90: 86089379565 | E90: 45964 | G90: A | H90: PROJETO 741 - FACILITIES MULT CABIUNAS UTE/AE-SEEACEC | I90: APOIO | J90: CIVIL
A91: 21392 | B91: ANA CLAUDIA DA SILVA RIBEIRO RODRIGUES | C91: ALMOXARIFE | D91: 17068929770 | E91: 45782 | G91: A | H91: PROJETO 743 - FACILITIES MULT CABIUNAS-SINTRAINDISTAL | I91: CABIUNAS | J91: SUPRIMENTOS
A92: 21265 | B92: FLAVIO RENATO DE SOUZA EVANGELISTA BRANDAO | C92: ARTIFICE | D92: 7733023793 | E92: 45779 | G92: A | H92: PROJETO 741 - FACILITIES MULT CABIUNAS UTE/AE-SINTRAINDISTAL | I92: AE | J92: CIVIL
A93: 21745 | B93: GENILSON SANTANA DA CONCEICAO | C93: ARTIFICE | D93: 1402744722 | E93: 45810 | G93: A | H93: PROJETO 741 - FACILITIES MULT CABIUNAS UTE/AE-SINTRAINDISTAL | I93: UTE | J93: CIVIL
A94: 17935 | B94: KEVEN DIAS MAGALHAES DA CONCEICAO | C94: ALMOXARIFE | D94: 15782595760 | E94: 45401 | G94: A | H94: PROJETO 743 - FACILITIES MULT CABIUNAS-SINTRAINDISTAL | I94: CABIUNAS | J94: ?
A95: 21594 | B95: CARLOS DANIEL FRANCA SANTOS | C95: AUXILIAR DE MANUTENCAO CIVIL | D95: 86515026560 | E95: 45791 | F95: 45932 | G95: D | H95: PROJETO 741 - FACILITIES MULT CABIUNAS UTE/AE-SINTRAINDISTAL
A96: 22618 | B96: CARLOS ALBERTO SERAFIM PEREIRA | C96: ARTIFICE | D96: 1757705732 | E96: 45859 | G96: A | H96: PROJETO 743 - FACILITIES MULT CABIUNAS-SINTRAINDISTAL | I96: BARRA DO FURADO | J96: CIVIL
A97: 21888 | B97: CARLOS EDUARDO GUERREIRO DOS SANTOS ALVES | C97: AUXILIAR DE SERVICOS GERAIS | D97: 13860774700 | E97: 45818 | F97: 45784 | G97: D | H97: PROJETO 741 - FACILITIES MULT CABIUNAS UTE/AE-SEEACEC
A98: 20758 | B98: GILSON CARVALHO DOS SANTOS | C98: ARTIFICE | D98: 92102832791 | E98: 45756 | G98: A | H98: PROJETO 741 - FACILITIES MULT CABIUNAS UTE/AE-SINTRAINDISTAL | I98: AE | J98: CIVIL
A99: 24241 | B99: EDVALDO FERREIRA ADORNO | C99: ARTIFICE | D99: 36694592515 | E99: 46084 | G99: A | H99: PROJETO 743 - FACILITIES MULT CABIUNAS-SINTRAINDISTAL | I99: CABIUNAS | J99: CIVIL
A100: 20778 | B100: ISAIAS DO ROSARIO | C100: ARTIFICE | D100: 5514722511 | E100: 45756 | G100: A | H100: PROJETO 741 - FACILITIES MULT CABIUNAS UTE/AE-SINTRAINDISTAL | I100: AE | J100: CIVIL
...

Sheet FG-ORGANOGRAMA-743
HB21: Gerente Regional
HA22: DIEGO CASTELUBER BASSETTI
HA27: 0.2 | HB27: Gerente de Facilities | IB27: Engenheiro de Segurança | JM27: Gerente Administrativo
HA28: JOSE DANIEL SILVA SANTOS JUNIOR | IA28: RODRIGO RODRIGUES | JL28: EVANDO GERONIMO
EZ29: =SUM(EQ30+EQ32) -> 1 | GF29: =SUM(GD34,FP34,FN30) -> 9 | GT29: =SUM(GK30+GK33+GK35+GK37+GK39+GK41+GK43+GK45+GK47) -> 7.5
EQ30: 0.5 | ER30: Assistente Administrativo | FN30: 0.5 | FO30: Supervisor Administrativo | GK30: 0.5 | GL30: Supervisor de Planejamento
EQ31: GABRIEL SERAFIM DA CRUZ | FN31: MAICON MONTEIRO | GK31: CELIANE RODRIGUES DE SOUZA | IW31: =SUM(IA37+HR41+HR43+IA41+IA43+IA45+IA47+IA49+IJ41+IJ43+IJ45+IA34) -> 6 | JL31: =SUM(JC35) -> 1 | KD31: =SUM(JU35+JU37+JU39) -> 3
EQ32: 0.5 | ER32: Assistente Administrativo | IO32: Tecnico de Enfermagem | JD32: Supervisora Administrativo | JV32: Supervisor Administrativo
EQ33: RAPHAEL DURAO SENOS DE CAMPOS | GK33: 1 | GL33: Planejador | IN33: CLEITON ORILIO LIRA DA SILVA
FP34: =SUM(FG35+FG37+FG39+FG41+FG43+FG45) -> 5 | GD34: =SUM(FU35+FU37+FU39+FU41) -> 3.5 | GK34: CAMILA MAYARA VASCONCELOS XIMENES | IA34: 0.2 | IB34: Supervisora de SMS
EW35: Software | FG35: 1 | FH35: Assistente de Logistica I | FU35: 1 | FV35: Comprador - Normatel | GK35: 1 | GL35: Planejador | IA35: DANIELE LIMA PONTES | JC35: 1 | JD35: Auxiliar Administrativo | JU35: 1 | JV35: Almoxarife
FG36: POLIANE LAPA MARINS | FU36: BEATRIZ CAMPELO FERREIRA | GK36: JEMERSON DO NASCIMENTO BATISTA | JC36: TAILANE | JU36: ANA CLAUDIA DA SILVA RIBEIRO RODRIGUES
FG37: 1 | FH37: Motorista | FU37: 1 | FV37: Comprador - Petrobras | GK37: 1 | GL37: Planejador | IA37: 0.2 | IB37: Tecnico de Segurança II | JU37: 1 | JV37: Auxiliar de Almoxarife II
FG38: GEILSON CUNHA DA SILVA | FU38: DIEGO CHAGAS PIRES | GK38: LEYDIANE DA SILVA BATISTA | IA38: HERALDO JULIO GREGORIO DA SILVA | JI38: RH | JU38: KAUA DE OLIVEIRA MELEGARI DOS SANTOS
FG39: 1 | FH39: Motorista | FU39: 1 | FV39: Comprador - Petrobras | GK39: 1 | GL39: Planejador | JU39: 1 | JV39: Auxiliar de Almoxarife II
FG40: GEOVANES ADELINO DE ANDRADE FILHO | FU40: THAMYRIS BARCELOS BARRETO GONCALVES | GK40: SANDRO OLIVEIRA DA SILVA | HR40: DOCUMENTAÇÃO | IA40: ÁREA / DOCUMENTAÇÃO | IJ40: INSPEÇÃO | JU40: GLEICIANE PESSANHA BARCELOS
FG41: 1 | FH41: Motorista | FU41: 0.5 | FV41: Comprador - Petrobras | GK41: 1 | GL41: Planejador | HR41: 1 | HS41: Auxiliar de SMS | IA41: 1 | IB41: Tecnico de Segurança | IJ41: 0.2 | IK41: Tecnico de Segurança
FG42: RENAN FARIAS DE SOUZA | FU42: CRISTIANO PAIVA | GK42: ISADORA BARCELOS ALMEIDA | HR42: KEROLAYNNE NERES DE SOUZA | IA42: ANA LUIZA NASCIMENTO DA SILVA | IJ42: RAFAELA GAUDENCIO MAXIMO | KA42: Suprimentos
FG43: 0.5 | FH43: Operador de Retroesvacadeira | GK43: 1 | GL43: Assistente Administrativo | HS43: Auxiliar de SMS | IA43: 1 | IB43: Tecnico de Segurança | IJ43: 0.2 | IK43: Tecnico de Segurança
FG44: VAGA | GA44: Compras | GK44: JANKLEY CARVALHO RABELO SILVA | HR44: LUANA BATISTA LACERDA | IA44: WAGNER MACHADO MEDUREIRA | IJ44: SANDRO AUGUSTO SOUZA DO COUTO
FG45: 0.5 | FH45: Motorista Munckeiro | GK45: 1 | GL45: Auxiliar Administrativo | IA45: 1 | IB45: Tecnico de Segurança | IJ45: 0.2 | IK45: Tecnico de Segurança
FG46: UENDER DA SILVA GOMES | GK46: JULIANE GONZAGA DA SILVA | IA46: ALICIA VITORIA TENORIO DA ROCHA | IJ46: MATEUS HIPOLITO CHAGAS RIBEIRO
GL47: Auxiliar Administrativo | IA47: 1 | IB47: Tecnico de Segurança
FM48: Logística | GK48: VAGA | IA48: EM ANDAMENTO
IT50: SMS
GQ51: Planejamento
HA55: 1 | HB55: Preposto
HA56: DAIANA MARQUES
HA58: 1 | HB58: Coordenador de Manutenção
HA59: LETICIA APARECIDA CIRILO PESSANHA
HA63: CABIUNAS
EC70: =SUM(CY71,DJ75,DO81,DT85,DT87,DT89,DT91,DT93,DT95,DT97,DK85,DK87,DK89,DK91,DK93,DA85,DA87,CR85,CR87,CR89,CR91,CR93,CR95,CR97,HW162,CR99,CR101,CI85,CI87,CI89,HW160,CI91,CI93,CI111,CI95,CI97,CR80,CG75,BR80,BW85,BW87,BW89,BW91,BW95,BW97,BW99,BW101,BM85,BM87,BM89,BM91,BM95,BM97,BM99,BM101+DT75) -> 55 | HB70: =SUM(FM71,FI76,FI78,FI80,FR76,FR78,GA76,EZ76,FI84,FI86,FR84,GA84,EZ84,EH91,EH93,EH95,EH97,EQ91,EQ93,EQ95,EQ97,EQ99,EQ101,EZ91,EZ93,EZ95,EZ97,EZ99,EZ101,EZ103,EZ105,EZ107,EZ109,EZ111,EZ113,EZ115,EZ117,EZ119,EZ121,EZ123,EZ125,EZ127,EZ129,EZ131,EZ133,EZ135,EZ137,EZ139,EZ141,EZ143,FI129,FI127,FI125,FI123,FI121,FI119,FI117,FI115,FI113,FI111,FI109,FI107,FI105,FI103,FI101,FI99,FI97,FI95,FI93,FI91,FR91,FR93,FR95,FR97,FR99,FR101,GA99,GA97,GA95,GA93,GA91,GJ91,GJ93,GJ95,GJ97,GJ99,GJ101,GS99,GS97,GS95,GS93,GS91) -> 89.4 | JF70: =SUM(IC71,IC75,IM78,IC82,HN82,IR82,HI85,HS85,IC85,IM85,IW85,IW87,IM87,IC87,HS87,HI87,HI89,HS91,IC89,FR162,FR166,IW91,FR160,IC91,HS93,HI91,HI93,HS95,IC93,IM89,IW93,IW95,IM91,IC95,HS97,HI95,HI97,HS99,IC97,IM93,IW97,IW99,IM95,IC99,HS101,HI99,HI101,HS103,IC101,IM97,IW101,IW103,IW105,IW107,IW109,IW111,IW113,IM107,IM109,IM105,IM103,IM101,FR164,IM99,IC103,IC105,FR168,IC107,IC109,IC111,IC113,IW89,HS115,HR111,HS113,HS111,HS109,HS107,HS105,HI103,HI105,HI107,HI109,HI111,HI113,HI115,HS89) -> 85.2 | KW70: =SUM(JZ71+KJ75+JP75+JK78+JU78+KE78+KO80+KE80,JU80,JK80,JK82,JU82,KE82,KO82,KO84,KO86,KO88,KO90,KO92,KO94,KO96,KO98,KO100,KO102,KO104,KE84,KE86,KE88,KE90,KE92,KE94,KE96,KE98,KE100,KE102,JU84,JU86,JU88,JU90,JU92,JU94,JU96,JU98,JU100,JU102,JK84,JK86,JK88,JK90,JK92,JK94,JK96,JK98,JK100) -> 54
CY71: 1 | CZ71: Engenheiro de Eletrica | FM71: 0.5 | FN71: Engenheira Civil | IC71: 0.2 | ID71: Engenheiro Agronomo | JZ71: 1 | KA71: Supervisor de Limpeza
CY72: DANIEL DOS SANTOS NASCIMENTO | FM72: GABRIELLA RODRIGUES PINTO | IC72: GUSTAVO FABRI BASTOS | JZ72: ELAINE EUGENIO DA SILVA
CG75: 1 | CH75: Supervisor de Eletrica | DJ75: 1 | DK75: Supervisor de Refrigeração | DT75: 1 | DU75: Cadista | EZ75: DRONE | FI75: SUPERVISÃO OPERACIONAL | FR75: SUPERVISÃO ADMINISTRATIVA | GA75: GESTÃO DE OCUPACAO | IC75: 1 | ID75: Supervisor de Áreas Verdes | JP75: 1 | JQ75: Encarregado de Limpeza | KJ75: 1 | KK75: Encarregado de Limpeza
CG76: THIAGO DA SILVA | DJ76: WENDERSON DE SOUZA FURTADO | DT76: KAIO KNUPP | EZ76: 0.2 | FA76: Operador de RPAS | FI76: 1 | FJ76: Supervisor de Manutencao Civil | FR76: 1 | FS76: Supervisor de Manutencao Civil | GA76: 0.2 | GB76: Auxiliar Administrativo | IC76: MAGNO CANDEIAS PEREIRA | JP76: VALDENICE DOS SANTOS LEMOS | KJ76: ELAINE LOPES FREITAS GONZAGA
EZ77: DIEGO WAGNER MARTINS DA SILVA | FI77: LEONARDO NUNES FIRMINO | FR77: ANTONIO CESAR BATISTA DE ALMEIDA | GA77: DANIEL MAIA DA SILVA | IM77: APOIO TECNICO
FI78: 1 | FJ78: Inspetor Predial | FR78: 1 | FS78: Cadista | IM78: 1 | IN78: Tecnico Agronomo | JK78: 1 | JL78: Auxiliar de Serviços Gerais | JU78: 1 | JV78: Auxiliar de Serviços Gerais | KE78: 1 | KF78: Auxiliar de Serviços Gerais | KO78: 1 | KP78: Auxiliar de Serviços Gerais
FI79: WILLIAM COSME MANHAES DILAIS | FR79: ARGOS MATHEUS SOUZA LOPES | IM79: ALEX PIMENTA BENTO | JK79: ADELSON LEITE DA SILVA | JU79: AFRICA DE AZEVEDO NEVES CARINO | KE79: ALEX SANDRO PIZIO DA SILVA | KO79: ANA CELIA DE OLIVEIRA SANTOS
BR80: 1 | BS80: Operador | CR80: 1 | CS80: Encarregado de Elétrica | FI80: 1 | FJ80: Auxiliar de Manutencao Civil | JK80: 1 | JL80: Auxiliar de Serviços Gerais | JU80: 1 | JV80: Auxiliar de Serviços Gerais | KE80: 1 | KF80: Auxiliar de Serviços Gerais | KO80: 1 | KP80: Auxiliar de Serviços Gerais
BR81: ANDRE FARIAS DE MOURA | CR81: DIARLEN CALDEIRA DO ESPIRITO SANTO | DO81: 1 | DP81: Encarregado de Eletromecânica | FI81: DAIANE MARINS DA SILVA | JK81: CLARISIANE SANTANA SOARES | JU81: VAGA | KE81: AURENICE ALVES BATISTA CORREIA | KO81: CINTIA MARTINS SILVA
DO82: CARLOS HENRIQUE ALVES DE OLIVEIRA | HN82: 1 | HO82: Encarregado de Áreas Verdes | IC82: 1 | ID82: Encarregado de Áreas Verdes | IR82: 1 | IS82: Encarregado de Áreas Verdes | JK82: 1 | JL82: Auxiliar de Serviços Gerais | JU82: 1 | JV82: Auxiliar de Serviços Gerais | KE82: 1 | KF82: Auxiliar de Serviços Gerais | KO82: 1 | KP82: Auxiliar de Serviços Gerais
HN83: ELIAS DE OLIVEIRA MACHADO | IC83: FILIPE MACHADO MADUREIRA | IR83: JOHN EMERSON ANDRADE ROSA | JK83: EDIJANE EUGENIO DA SILVA | JU83: CRISTIANE MARQUES DA SILVA | KE83: EDILENE DA SILVA BUENO MADUREIRA | KO83: VAGA
BM84: OPERAÇÃO - EQUIPE A | BW84: OPERAÇÃO - EQUIPE B | CI84: ELETRICA | CR84: ELETRICA | DA84: APOIO TECNICO | DK84: REFRIGERAÇÃO | DT84: ELETROMECÂNICA | EZ84: 0.5 | FA84: Encarregado Civil | FI84: 1 | FJ84: Encarregado Civil | FR84: 1 | FS84: Encarregado Civil | GA84: 1 | GB84: Encarregado Civil | JK84: 1 | JL84: Auxiliar de Serviços Gerais | JU84: 1 | JV84: Auxiliar de Serviços Gerais | KE84: 1 | KF84: Auxiliar de Serviços Gerais | KO84: 1 | KP84: Auxiliar de Serviços Gerais
BM85: 1 | BN85: Operador - 4x4 | BW85: 1 | BX85: Operador - 4x4 | CI85: 1 | CJ85: Eletricista Predial | CR85: 1 | CS85: Eletricista Predial | DA85: 1 | DB85: Técnico de Elétrica | DK85: 1 | DL85: Eletricista Predial | DT85: 1 | DU85: Tecnico de Mecanica | EZ85: BRUNO MANHAES | FI85: GUILHERME ALVES | FR85: LEONARDO DOS SANTOS HENRIQUES | GA85: RODRIGO DE CARVALHO CYPRIANO | HI85: 1 | HJ85: Jardineiro | HS85: 1 | HT85: Jardineiro | IC85: 1 | ID85: Jardineiro | IM85: 1 | IN85: Operador de Rocadeira | IW85: 1 | IX85: Operador de Rocadeira | JK85: ELISANGELA DOS SANTOS SILVA | JU85: EDILAINE DA SILVA SANTOS | KE85: FABIANE ALVES DE OLIVEIRA | KO85: VAGA
BM86: THYAGO GONCALVES FARIAS | BW86: ISMAEL MOCO DA SILVA | CI86: JOCIRLEI AMARO SARAIVA | CR86: RAPHAEL LUIZ PINHEIRO PEREIRA | DA86: PABLO SILVA DE OLIVEIRA | DK86: PAULO VINICIUS RODRIGUES MEIRELES | DT86: MATHEUS BARCELLOS GOMES | FI86: 1 | FJ86: Pedreiro (líder) | HI86: GILSIMAR TELES MALAFAIA | HS86: LUIS CLAUDIO FORTUNATA | IC86: MARCELO MOREIRA | IM86: ALESSANDRO DOS SANTOS | IW86: IAN DA SILVA NEVES | JK86: 1 | JL86: Auxiliar de Serviços Gerais | JU86: 1 | JV86: Auxiliar de Serviços Gerais | KE86: 1 | KF86: Auxiliar de Serviços Gerais | KO86: 1 | KP86: Auxiliar de Serviços Gerais
BM87: 1 | BN87: Eletricista - 4x4 | BW87: 1 | BX87: Eletricista - 4x4 | CI87: 1 | CJ87: Eletricista Predial | CR87: 1 | CS87: Eletricista Predial | DA87: 1 | DB87: Técnico de Elétrica | DK87: 1 | DL87: Mecanico de Refrigeracao | DT87: 1 | DU87: Mecanico | FI87: AMARILDO DA SILVA MOREIRA | HI87: 1 | HJ87: Jardineiro | HS87: 1 | HT87: Jardineiro | IC87: 1 | ID87: Jardineiro | IM87: 1 | IN87: Operador de Rocadeira | IW87: 1 | IX87: Operador de Rocadeira | JK87: FABRICIA LOPES DA SILVA | JU87: EVILIN PERES GRIGORIO MAIA | KE87: GISLAINE SOUZA DA SILVA | KO87: FABIO ROCHA DE AZEVEDO
BM88: RHAY DINIZ BUENO MADUREIRA | BW88: CRISTIANO MOREIRA DE OLIVEIRA | CI88: JOHN KEVIN DE OLIVEIRA QUINTES | CR88: JOAO PEDRO MELLO | DA88: MARCELO OLIVEIRA FALCAO | DK88: NELCI PACHECO | DT88: GILMAR BARCELOS | HI88: CARLOS OTAVIO PINTO ALVES | HS88: LUIZ CARLOS TEIXEIRA DA CRUZ | IC88: MARCIO DO ESPIRITO SANTO | IM88: ALEXANDRE BARDASSON GONCALVES | IW88: JHONATAN ALVES DA SILVA | JK88: 1 | JL88: Auxiliar de Serviços Gerais | JU88: 1 | JV88: Auxiliar de Serviços Gerais | KE88: 1 | KF88: Auxiliar de Serviços Gerais | KO88: 1 | KP88: Auxiliar de Serviços Gerais
BM89: 1 | BN89: Ajudante de Elétrica Predial - 4x4 | BW89: 1 | BX89: Ajudante de Elétrica Predial - 4x4 | CI89: 1 | CJ89: Eletricista Predial | CR89: 1 | CS89: Eletricista Predial | DK89: 1 | DL89: Oficial de Refrigeracao | DT89: 1 | DU89: Mecanico | HI89: 1 | HJ89: Auxiliar de Jardinagem | HS89: 1 | HT89: Jardineiro | IC89: 1 | ID89: Jardineiro | IM89: 1 | IN89: Operador de Rocadeira | IW89: 1 | IX89: Auxiliar de Jardinagem | JK89: GRAZIELE OSORIO DE CASTRO COUTO DE OLIVEIRA | JU89: VAGA | KE89: LUCIANA VICENTE DE SOUZA | KO89: GLEICIANE DOS ANGELOS OLIVEIRA
BM90: JOAO VITOR CORDEIRO LUNA | BW90: VAGA | CI90: JOAO CARLOS DE OLIVEIRA MATHIAS | CR90: PROMOÇÃO INTERNA | DK90: MARLLON SILVA DE OLIVEIRA | DT90: LEONARDO GRAVINA RASMA | EH90: MARCENARIA | EQ90: CARPINTARIA | EZ90: PINTURA | FI90: ALVENARIA | FR90: HIDRÁULICA | GA90: ANDAIMES | GJ90: CALDEIRARIA | GS90: MOVIMENTAÇÃO DE VOLUMES | HI90: ALDAIR JOSE PONCE SOARES | HS90: VAGA | IC90: WILIAN DA SILVA MORAES | IM90: CHEDI WILLIAN DA SILVA PERES | IW90: WAGNER SILVA DE OLIVEIRA | JK90: 1 | JL90: Auxiliar de Serviços Gerais | JU90: 1 | JV90: Auxiliar de Serviços Gerais | KE90: 1 | KF90: Auxiliar de Serviços Gerais | KO90: 1 | KP90: Auxiliar de Serviços Gerais
BM91: 1 | BN91: Oficial de Refrigeracao - 4x4 | BW91: 1 | BX91: Oficial de Refrigeracao - 4x4 | CI91: 1 | CJ91: Ajudante de Elétrica Predial | CR91: 1 | CS91: Eletricista Predial | DK91: 1 | DL91: Oficial de Refrigeracao | DT91: 1 | DU91: Mecanico | EH91: 1 | EI91: Marceneiro | EQ91: 1 | ER91: Carpinteiro | EZ91: 1 | FA91: Pintor (líder) | FI91: 1 | FJ91: Pedreiro (líder) | FR91: 1 | FS91: Bombeiro Hidraulico | GA91: 1 | GB91: Encarregado de Andaime | GJ91: 1 | GK91: Caldeireiro | GS91: 1 | GT91: Estivas | HI91: 1 | HJ91: Auxiliar de Jardinagem | HS91: 1 | HT91: Auxiliar de Jardinagem | IC91: 1 | ID91: Auxiliar de Jardinagem | IM91: 1 | IN91: Operador de Rocadeira | IW91: 1 | IX91: Operador de Rocadeira | JK91: KATLLUEN ANDRE DE SOUZA | JU91: JEFFERSON SANTOS PEREIRA | KE91: MARIA LUCIA DA CONCEICAO SILVA | KO91: JOSIEL DA SILVA MARQUES
BM92: GEORGE ANTONIO DA COSTA DE SOUZA | BW92: VAGA | CI92: VAGA | CR92: PROMOÇÃO INTERNA | DK92: GEORGE ANTONIO DA COSTA DE SOUZA | DT92: WANDERSON MANHAES DILAIS | EH92: GILMAR LEITE AZEVEDO | EQ92: MAICON DE SOUSA CRISTO | EZ92: LEANDRO MARTINS PENA | FI92: ROBERTO CABRAL FEITOSA | FR92: JOSUE TIL | GA92: LUIS VALERIO DOS SANTOS | GJ92: LEONARDO SOARES MARTINS | GS92: BRUNO NASCIMENTO DE ABREU SOUZA | HI92: ANDREWS DUARTE DOS REIS ARRUDA | HS92: FILIPE LEANDRO LEAL | IC92: KAIQUE SOUZA DOS SANTOS | IM92: CLOVIS NEVES CHAVES | IW92: LEONARDO DOS SANTOS GOMES | JK92: 1 | JL92: Auxiliar de Serviços Gerais | JU92: 1 | JV92: Auxiliar de Serviços Gerais | KE92: 1 | KF92: Auxiliar de Serviços Gerais | KO92: 1 | KP92: Auxiliar de Serviços Gerais
CI93: 1 | CJ93: Ajudante de Elétrica Predial | CR93: 1 | CS93: Ajudante de Elétrica Predial | DK93: 1 | DL93: Ajudante de Refrigeração | DT93: 1 | DU93: Ajudante de Mecanica Predial | EH93: 1 | EI93: Marceneiro | EQ93: 1 | ER93: Carpinteiro | EZ93: 1 | FA93: Pintor | FI93: 1 | FJ93: Pedreiro | FR93: 1 | FS93: Bombeiro Hidraulico | GA93: 1 | GB93: Montador de Andaimes | GJ93: 1 | GK93: Caldeireiro | GS93: 1 | GT93: Estivas | HI93: 1 | HJ93: Auxiliar de Jardinagem | HS93: 1 | HT93: Auxiliar de Jardinagem | IC93: 1 | ID93: Auxiliar de Jardinagem | IM93: 1 | IN93: Operador de Rocadeira | IW93: 1 | IX93: Operador de Rocadeira | JK93: MARCIA VERONICA PORTO DOS SANTOS | JU93: LILIANE DA CONCEICAO SILVA | KE93: SIDICLEI PEDRO DIAS | KO93: LUSIMAR DA SILVA NASCIMENTO CASTRO
BM94: OPERAÇÃO - EQUIPE C | BW94: OPERAÇÃO - EQUIPE D | CI94: GABRIEL DE ALMEIDA SOUTO | CR94: VAGA | DK94: HIAN DO NASCIMENTO QUEIROZ | DT94: DANIEL GONCALVES DA SILVA | EH94: JULIO MUNIZ | EQ94: PAULO CEZAR DA SILVA BARBOSA | EZ94: ANDERSON DANIEL ROSA SCHELES | FI94: BARTOLOMEU PORFIRIO ROSA | FR94: SANDRO ALEX DE LIMA RIBEIRO | GA94: JOSE ROBERTO DOS REIS | GJ94: LEONIS DE JESUS MARTINS | GS94: GUILHERME DE SOUZA BATISTA | HI94: BRUNO SILVA PEREIRA MARQUES | HS94: GABRIEL NASCIMENTO DA SILVA | IC94: LUCAS BRAGANCA DE AZEREDO | IM94: DALTON FERREIRA CRUZ | IW94: LUIZ FERNANDO FRANCISCO CORDEIRO | JK94: 1 | JL94: Auxiliar de Serviços Gerais | JU94: 1 | JV94: Auxiliar de Serviços Gerais | KE94: 1 | KF94: Auxiliar de Serviços Gerais | KO94: 1 | KP94: Auxiliar de Serviços Gerais
BM95: 1 | BN95: Operador - 4x4 | BW95: 1 | BX95: Operador - 4x4 | CI95: 1 | CJ95: Ajudante de Elétrica Predial | CR95: 1 | CS95: Ajudante de Elétrica Predial | DT95: 1 | DU95: Ajudante de Mecanica Predial | EH95: 1 | EI95: Ajudante de Marceneiro | EQ95: 1 | ER95: Carpinteiro | EZ95: 1 | FA95: Pintor | FI95: 1 | FJ95: Pedreiro | FR95: 1 | FS95: Artifice | GA95: 1 | GB95: Montador de Andaimes | GJ95: 1 | GK95: Caldeireiro | GS95: 1 | GT95: Estivas | HI95: 1 | HJ95: Auxiliar de Jardinagem | HS95: 1 | HT95: Auxiliar de Jardinagem | IC95: 1 | ID95: Auxiliar de Jardinagem | IM95: 1 | IN95: Operador de Rocadeira | IW95: 1 | IX95: Operador de Rocadeira | JK95: MARILENE NEVES BATISTA DA SILVA | JU95: MARIA ANDREA DE OLIVEIRA MELEGARI FIGUEIRA | KE95: SIMONE COUTINHO | KO95: MARIANA VENTUROTT FERREIRA BARCELOS
BM96: ELCINEI DIAS DOMINGOS | BW96: ZILDEAN BARBOZA ALVES | CI96: LUCAS NASCIMENTO FERREIRA | CR96: VALMIR SILVA VIANA NETO | DT96: JOSUE DA CONCEICAO PESSANHA | EH96: JOSE AIRES DA SILVA | EQ96: WESLLEY ALVES FRAGA | EZ96: CARLOS ANTONIO PORTO ALBINO DA SILVA | FI96: FABIO FERREIRA SANTOS | FR96: JULIO DE JESUS DOS SANTOS | GA96: LUCIANO SANTANA BISPO | GJ96: PAULO ROBERTO FRANCISCO | GS96: IGOR DA SILVA DIAS | HI96: CARLOS EDUARDO DE ANDRADE SOUZA | HS96: GILBERTO BARCELOS | IC96: MAICON PARAHYBA LOPES | IM96: DAVI MADUREIRA | IW96: MAGNO CESAR PEREIRA COSTA | JK96: 1 | JL96: Auxiliar de Serviços Gerais | JU96: 1 | JV96: Auxiliar de Serviços Gerais | KE96: 1 | KF96: Auxiliar de Serviços Gerais | KO96: 1 | KP96: Auxiliar de Serviços Gerais
BM97: 1 | BN97: Eletricista - 4x4 | BW97: 1 | BX97: Eletricista - 4x4 | CI97: 1 | CJ97: Ajudante de Elétrica Predial | CR97: 1 | CS97: Ajudante de Elétrica Predial | DT97: 1 | DU97: Ajudante de Mecanica Predial | EH97: 1 | EI97: Ajudante de Marceneiro | EQ97: 1 | ER97: Ajudante de Carpinteiro | EZ97: 1 | FA97: Pintor | FI97: 1 | FJ97: Pedreiro | FR97: 1 | FS97: Ajudante de Bombeiro Predial | GA97: 1 | GB97: Montador de Andaimes | GJ97: 1 | GK97: Ajudante de Caldeiraria Predial | GS97: 1 | GT97: Estivas | HI97: 1 | HJ97: Auxiliar de Jardinagem | HS97: 1 | HT97: Auxiliar de Jardinagem | IC97: 1 | ID97: Auxiliar de Jardinagem | IM97: 1 | IN97: Operador de Rocadeira | IW97: 1 | IX97: Operador de Rocadeira | JK97: RACHEL AUGUSTA DE AGUIAR ALVES E ALVES | JU97: MATHEUS DE SOUZA PINTO | KE97: SIRLEI CANUTO MORAES | KO97: THIAGO CASSIANO DE CASTRO
BM98: LUCAS SILVA PEREIRA MARQUES | BW98: ALESSANDRO PEREIRA BORGES | CI98: RAFAEL ALVES DA SILVA | CR98: JOAO PEDRO SANTOS CARDIM | DT98: NADILTON SANTOS DE JESUS | EH98: PATRICK MUNIZ ALVARENGA | EQ98: LUIS GUSTAVO SILVA GEMINO | EZ98: CARLOS DANIEL DOS SANTOS RODRIGUES | FI98: FRANCISCO DE ASSIZ ALIPIO DE SOUSA | FR98: FABRICIO JOSE PINTO | GA98: ROGERIO FRANCISCO CARVALHO | GJ98: LUCAS OLIVEIRA DE PAULA | GS98: PAULO HENRIQUE DOS SANTOS SILVA | HI98: CRISTIAN FORTUNATA DA SILVA VIEGAS | HS98: GUARACI BORGES | IC98: MARCIO SANT ANA DOS SANTOS | IM98: DEYVID TRAJANO DE ALVARENGA | IW98: MARLONI DE SOUZA SILVA | JK98: 1 | JL98: Auxiliar de Serviços Gerais | JU98: 1 | JV98: Auxiliar de Serviços Gerais | KE98: 1 | KF98: Auxiliar de Serviços Gerais | KO98: 1 | KP98: Auxiliar de Serviços Gerais - 2x2
BM99: 1 | BN99: Ajudante de Elétrica Predial - 4x4 | BW99: 1 | BX99: Ajudante de Elétrica Predial - 4x4 | CR99: 1 | CS99: Ajudante de Elétrica Predial | EQ99: 1 | ER99: Ajudante de Carpinteiro | EZ99: 1 | FA99: Pintor | FI99: 1 | FJ99: Pedreiro | FR99: 1 | FS99: Ajudante de Bombeiro Predial | GA99: 1 | GB99: Montador de Andaime | GJ99: 1 | GK99: Auxiliar de Manutenção em Caldeiraria | GS99: 1 | GT99: Estivas | HI99: 1 | HJ99: Auxiliar de Jardinagem | HS99: 1 | HT99: Auxiliar de Jardinagem | IC99: 1 | ID99: Auxiliar de Jardinagem | IM99: 1 | IN99: Operador de Rocadeira | IW99: 1 | IX99: Operador de Rocadeira | JK99: ROUSE DE OLIVEIRA SOUZA | JU99: PALOMA DE RESENDE DUARTE BARBOSA | KE99: VIRGINIA SILVA MACHADO BEZERRA | KO99: DARCI TEIXEIRA DOS SANTOS
BM100: VAGA | BW100: VAGA | CR100: MATHEUS FERREIRA CALDEIRA | EQ100: THIAGO ILDEBRANDO FINAMOR | EZ100: FLAVIO JOSE PINTO | FI100: JOSE RENATO GAMA PESSANHA | FR100: LUIZ FELIPE DA SILVA MARTINS | GA100: VAGA | GJ100: LUCAS AZEVEDO DA SILVA | GS100: RUAN DE ANDRADE LEAL ROCHA | HI100: CRISTIANO DA CONCEICAO DE PAULA | HS100: HENRIQUE PINHEIRO DE AGUIAR | IC100: MARCOS PAULO RIBEIRO BENAVENUTO | IM100: DIEGO MARQUES DA SILVA | IW100: MATEUS MACHADO | JK100: 1 | JL100: Auxiliar de Serviços Gerais | JU100: 1 | JV100: Auxiliar de Serviços Gerais | KE100: 1 | KF100: Auxiliar de Serviços Gerais | KO100: 1 | KP100: Auxiliar de Serviços Gerais - 2x2
BM101: 1 | BN101: Oficial de Refrigeracao - 4x4 | BW101: 1 | BX101: Oficial de Refrigeracao - 4x4 | CR101: 1 | CS101: Ajudante de Elétrica Predial | EQ101: 1 | ER101: Auxiliar de Manutencao Civil | EZ101: 1 | FA101: Pintor | FI101: 1 | FJ101: Pedreiro | FR101: 1 | FS101: Ajudante de Bombeiro Predial | GJ101: 1 | GK101: Auxiliar de Manutenção em Caldeiraria | HI101: 1 | HJ101: Auxiliar de Jardinagem | HS101: 1 | HT101: Auxiliar de Jardinagem | IC101: 1 | ID101: Auxiliar de Jardinagem | IM101: 1 | IN101: Operador de Rocadeira | IW101: 1 | IX101: Operador de Rocadeira | JK101: SANDRA REGINA SOUTHER DA SILVA | JU101: PATRICIA DE PAULA SOUZA | KE101: WENDERSON WILLIAMS DOS SANTOS MIRANDA | KO101: EDILENE MARTINS DA SILVA
BM102: DANIEL MARTINS ROCHA | BW102: RODRIGO MAIA LOPES | CR102: WALDIR PEREIRA DE SOUZA | EQ102: VAGA | EZ102: ITHALO MAXWELL PACHECO PEREIRA | FI102: MARCILIANO DA SILVA SANTOS | FR102: VAGA | GJ102: VAGA | HI102: DELEON DOS SANTOS SILVA | HS102: JACKSON INACIO PESSANHA | IC102: MATHEUS BUENO AUGUSTO ALVES | IM102: FABIANO DA SILVA | IW102: NERLON LANNES PEREIRA | JU102: 1 | JV102: Auxiliar de Serviços Gerais | KE102: 1 | KF102: Auxiliar de Serviços Gerais | KO102: 1 | KP102: Auxiliar de Serviços Gerais - 2x2
EZ103: 1 | FA103: Pintor | FI103: 1 | FJ103: Pedreiro | HI103: 1 | HJ103: Auxiliar de Jardinagem | HS103: 1 | HT103: Auxiliar de Jardinagem | IC103: 1 | ID103: Auxiliar de Jardinagem | IM103: 1 | IN103: Operador de Rocadeira | IW103: 1 | IX103: Operador de Rocadeira | JU103: PATRICK ERNANI DE SOUZA PINTO | KE103: ZENILDA MARTINS DOS SANTOS | KO103: FLAVIO RIBEIRO CRESPO
EZ104: JOILSON MARQUES GURGEL DA SILVA | FI104: ANTONIO CORREA PIASSA | HI104: DOUGLAS SILVA DE MOURA | HS104: JOAO VICTOR ARAUJO ALVES | IC104: PAULO AUGUSTO COSTA OLIVEIRA | IM104: FABIO JUNIOR LOPES DA SILVA | IW104: RAFAEL MACHADO | KO104: 1 | KP104: Auxiliar de Serviços Gerais - 2x2
DY105: Elétrica | EZ105: 1 | FA105: Pintor | FI105: 1 | FJ105: Artifice | HI105: 1 | HJ105: Auxiliar de Jardinagem | HS105: 1 | HT105: Auxiliar de Jardinagem | IC105: 1 | ID105: Auxiliar de Jardinagem | IM105: 1 | IN105: Operador de Rocadeira | IW105: 1 | IX105: Operador de Rocadeira | KO105: ANTONIA LUCIETE NUNES CAMELO
EZ106: LEANDRO ALBINO DA SILVA | FI106: EDVALDO FERREIRA ADORNO | HI106: EDUARDO DE SOUZA FERNANDES DINIZ | HS106: JOAO VITOR ALVES FARIA | IC106: PAULO HENRIQUE DE OLIVEIRA SOUZA SILVA | IM106: GERALDO VALDECIR DE OLIVEIRA | IW106: RAFAEL ALVES DA SILVA MACHADO
EZ107: 1 | FA107: Pintor | FI107: 1 | FJ107: Artifice | HI107: 1 | HJ107: Auxiliar de Jardinagem | HS107: 1 | HT107: Auxiliar de Jardinagem | IC107: 1 | ID107: Auxiliar de Jardinagem | IM107: 1 | IN107: Operador de Rocadeira | IW107: 1 | IX107: Operador de Rocadeira
EZ108: PATRICK VICTOR DOS SANTOS RAMOS | FI108: GABRIEL DA SILVA DAUMAS | HI108: EVERT CLEY ANDRADE ROSA | HS108: JOAO VITOR BUENO AUGUSTO ALVES | IC108: VAGA | IM108: GILSON DOS SANTOS | IW108: ROBSON JORGE RIBEIRO ALVES | KT108: Limpeza
EZ109: 1 | FA109: Pintor | FI109: 1 | FJ109: Artifice | HI109: 1 | HJ109: Auxiliar de Jardinagem | HS109: 1 | HT109: Auxiliar de Jardinagem | IC109: 1 | ID109: Auxiliar de Jardinagem | IM109: 1 | IN109: Operador de Rocadeira | IW109: 1 | IX109: Operador de Rocadeira
EZ110: LUIZ CESAR MADUREIRA NEVES | FI110: JORGE ASSIS SILVA NASCIMENTO | HI110: RHUAN VENANCIO LIMA | HS110: KAIO CORREA PACHECO | IC110: THIAGO MOREIRA DE SOUZA | IM110: VAGA | IW110: SAULO AZEVEDO DE MATOS
EZ111: 1 | FA111: Pintor Industrial | FI111: 1 | FJ111: Auxiliar de Manutencao Civil | HI111: 1 | HJ111: Auxiliar de Jardinagem | HS111: 1 | HT111: Auxiliar de Jardinagem | IC111: 1 | ID111: Auxiliar de Jardinagem | IM111: 1 | IN111: Auxiliar de Jardinagem | IW111: 1 | IX111: Operador de Rocadeira
EZ112: ARLINDO DELFINO DA SILVA FILHO | FI112: ATHIRSON NASCIMENTO SILVA | HI112: RIVERTON VICENTE DOS SANTOS | HS112: RYAN DE OLIVEIRA SILVA | IC112: VALCINEI DA SILVA | IM112: VAGA | IW112: VAGA
EZ113: 1 | FA113: Pintor Industrial | FI113: 1 | FJ113: Auxiliar de Manutencao Civil | HI113: 1 | HJ113: Auxiliar de Jardinagem | HS113: 1 | HT113: Auxiliar de Jardinagem | IC113: 1 | ID113: Auxiliar de Jardinagem | IM113: 1 | IN113: Auxiliar de Jardinagem | IW113: 1 | IX113: Operador de Rocadeira
EZ114: CARLOS RENATO GOMES DE SOUZA | FI114: RENAN PEREIRA DE AZEVEDO | HI114: RODRIGO MARTINS DE SOUZA | HS114: VAGA | IC114: VAGA | IM114: VAGA | IW114: HELIO PEREIRA DE MORAIS NETTO
EZ115: 1 | FA115: Pintor Industrial | FI115: 1 | FJ115: Auxiliar de Manutencao Civil | HI115: 1 | HJ115: Auxiliar de Jardinagem | HS115: 1 | HT115: Auxiliar de Jardinagem | IC115: 1 | ID115: Auxiliar de Jardinagem | IM115: 1 | IN115: Auxiliar de Jardinagem | IW115: 1 | IX115: Auxiliar de Jardinagem
EZ116: JAMIL DE ASSUNCAO | FI116: ADRIANO DA SILVA MOREIRA | HI116: VANDERLEY FELICIANO ALVES | HS116: SAYLON BRAGANCA DE OLIVEIRA | IC116: VAGA | IM116: VAGA | IW116: VAGA
EZ117: 1 | FA117: Pintor Industrial | FI117: 1 | FJ117: Auxiliar de Manutencao Civil
EZ118: MANOEL PESSANHA | FI118: DANIEL BUENO MARQUES
EZ119: 1 | FA119: Pintor Industrial | FI119: 1 | FJ119: Auxiliar de Manutencao Civil | JC119: Àreas Verdes
EZ120: MARCELO DOS SANTOS | FI120: EMERSON BRANDAO SILVA
EZ121: 1 | FA121: Ajudante de Pintura | FI121: 1 | FJ121: Auxiliar de Manutencao Civil
EZ122: BRENO HENRIQUE DAUMAS PEREIRA | FI122: JOSE CARLOS SILVA DOS SANTOS
EZ123: 1 | FA123: Ajudante de Pintura | FI123: 1 | FJ123: Auxiliar de Manutencao Civil
EZ124: GUSTAVO NASCIMENTO DUTRA | FI124: LEONARDO DIAS DOS SANTOS MACHADO
EZ125: 1 | FA125: Ajudante de Pintura | FI125: 1 | FJ125: Auxiliar de Manutencao Civil
EZ126: JACKSON DOUGLAS MADUREIRA DE PAULA | FI126: MARCIO CLAUDIO MOTA SILVEIRA
EZ127: 1 | FA127: Ajudante de Pintura | FI127: 1 | FJ127: Auxiliar de Manutencao Civil
EZ128: SIDNEY BATISTA LANDIM | FI128: VAGA
EZ129: 1 | FA129: Ajudante de Pintura Industrial | FI129: 1 | FJ129: Auxiliar de Manutencao Civil
EZ130: MANOEL CAETANO DAS CANDEIAS | FI130: VAGA
EZ131: 1 | FA131: Auxiliar de Manutencao Civil
EZ132: TIAGO PESSANHA DA SILVA
EZ133: 1 | FA133: Auxiliar de Manutencao Civil
EZ134: FABIO JUNIO PESSANHA SILVA
EZ135: 1 | FA135: Auxiliar de Manutencao Civil
EZ136: VAGA
EZ137: 1 | FA137: Auxiliar de Manutencao Civil
EZ138: FILIPE LEITE AZEVEDO
EZ139: 1 | FA139: Auxiliar de Manutencao Civil
EZ140: DANILO RODRIGUES COUTINHO
...

Sheet ORG-RESUMIDO-743
X3: Gerente Regional
W4: DIEGO CASTELUBER BASSETTI
W7: 0.5 | X7: Gerente de Facilites | AX7: Gerente de SMS | BK7: Gerente ADM
W8: JOSE DANIEL SILVA SANTOS JUNIOR | AW8: RODRIGO CESAR RODRIGUES | BJ8: EVANDO GERONIMO
P10: EQUIPE ESTRATÉGICA
P11: GERÊNCIA DE INTEGRAÇÃO | AX11: QUALIDADE, SAÚDE SEGURANÇA E MEIO AMBIENTE | BB11: EQUIPE DE SAUDE | BK11: RH | BO11: ALMOXARIFADO
M15: 0.5 | N15: Assistente Administrativo | W15: ='FG-ORGANOGRAMA-741'!BG13 -> 0.5 | X15: Supervisor Administrativo | AG15: ='FG-ORGANOGRAMA-741'!CD13 -> 1 | AH15: Supervisora de Planejamento
M16: GABRIEL SERAFIM DA CRUZ | W16: MAICON MONTEIRO | AG16: CELIANE RODRIGUES DE SOUZA
P18: SOFTWARE | X18: LOGÍSTICA | AA18: COMPRAS | AJ18: PLANEJAMENTO
AX21: ='FG-ORGANOGRAMA-743'!IW31 -> 6 | BB21: 0 | BK21: ='FG-ORGANOGRAMA-743'!JL31 -> 1 | BO21: ='FG-ORGANOGRAMA-743'!KD31 -> 3
P28: ='FG-ORGANOGRAMA-743'!EZ29 -> 1 | X28: ='FG-ORGANOGRAMA-743'!FP34 -> 5 | AA28: ='FG-ORGANOGRAMA-743'!GD34 -> 3.5 | AJ28: ='FG-ORGANOGRAMA-743'!GT29 -> 7.5
AO33: 1 | AP33: Preposto
AO34: DAIANA MARQUES
AO36: 1 | AP36: Coordenador de Manutenção
AO37: LETICIA APARECIDA CIRILO PESSANHA
T40: Cabiunas | AQ40: Fazenda Severina | BN40: Barra do Furado
H44: 0.5 | I44: Engenheiro Eletricista | R44: 0.5 | S44: Engenheiro Civil | AB44: 0.5 | AC44: Engenheiro Agronomo | BB44: 0.5 | BC44: Engenheiro Eletricista | BL44: 0.5 | BM44: Engenheiro Civil | BV44: 0.5 | BW44: Engenheiro Agronomo
H45: DANIEL DOS SANTOS NASCIMENTO | R45: GABRIELLA RODRIGUES PINTO | AB45: GUSTAVO FABRI BASTOS | BB45: DANIEL DOS SANTOS NASCIMENTO | BL45: GABRIELLA RODRIGUES PINTO | BV45: GUSTAVO FABRI BASTOS
K47: MANUTENÇÃO | U47: CIVIL | AD47: ÁREAS VERDES | AG47: CONS. LIMPEZA | AR47: CONS. LIMPEZA | BE47: MANUTENÇÃO | BO47: CIVIL | BX47: ÁREAS VERDES | CA47: CONS. LIMPEZA
K57: ='FG-ORGANOGRAMA-743'!EC70 -> 55 | U57: ='FG-ORGANOGRAMA-743'!HB70 -> 89.4 | AD57: ='FG-ORGANOGRAMA-743'!JF70 -> 85.2 | AG57: ='FG-ORGANOGRAMA-743'!KW70 -> 54 | AR57: ='FG-ORGANOGRAMA-743'!HJ181 -> 1 | BE57: ='FG-ORGANOGRAMA-743'!IF158 -> 2 | BO57: ='FG-ORGANOGRAMA-743'!HS158 -> 6 | BX57: ='FG-ORGANOGRAMA-743'!GA158 -> 5 | CA57: ='FG-ORGANOGRAMA-743'!GN158 -> 5
AM64: TOTAL | AQ64: =SUM(W3+W7+M15+W15+AG15+P28+X28+AA28+AJ28+AW7+AX21+BB21+BJ7+BK21+BO21+AO33+AO36+H44+R44+AB44+K57+U57+AD57+AG57+AO44+BB44+BE57+BL44+BO57+BV44+BX57+AR57) -> 332.1

Sheet Análises 743 1
A1: NORMATEL • Análises Projeto 743
A2: Cálculos dinâmicos sobre EFETIVO 11.05.2026 - Situações (SIT): A=Ativo, D=Desligado, F=Férias, P=INSS, T=Acidente de Trabalho, M=Serviço Militar
B4: 1. Indicadores do Projeto 743
B5: Total de registros vinculados ao 743 (todas situações) | C5: {=SUMPRODUCT(ISNUMBER(SEARCH("743",'EFETIVO 11.05.2026'!$H$2:$H$712))*(('EFETIVO 11.05.2026'!$G$2:$G$712="A")+('EFETIVO 11.05.2026'!$G$2:$G$712="D")+('EFETIVO 11.05.2026'!$G$2:$G$712="F")+('EFETIVO 11.05.2026'!$G$2:$G$712="P")+('EFETIVO 11.05.2026'!$G$2:$G$712="T")+('EFETIVO 11.05.2026'!$G$2:$G$712="M")))} -> 433
B6: Ativos no 743 | C6: {=SUMPRODUCT(ISNUMBER(SEARCH("743",'EFETIVO 11.05.2026'!$H$2:$H$712))*('EFETIVO 11.05.2026'!$G$2:$G$712="A"))} -> 319
B7: Desligados no 743 | C7: {=SUMPRODUCT(ISNUMBER(SEARCH("743",'EFETIVO 11.05.2026'!$H$2:$H$712))*('EFETIVO 11.05.2026'!$G$2:$G$712="D"))} -> 101
B8: % de turnover (desligados / total) | C8: =IFERROR(C7/C5,0) -> 0.23325635
B9: Afastados no 743 (F+P+T+M) | C9: {=SUMPRODUCT(ISNUMBER(SEARCH("743",'EFETIVO 11.05.2026'!$H$2:$H$712))*(('EFETIVO 11.05.2026'!$G$2:$G$712="F")+('EFETIVO 11.05.2026'!$G$2:$G$712="P")+('EFETIVO 11.05.2026'!$G$2:$G$712="T")+('EFETIVO 11.05.2026'!$G$2:$G$712="M")))} -> 13
B10: Funções distintas (somente ativos) | C10: {=SUMPRODUCT(--(C15:C89>0))} -> 66
B12: 2. Headcount por Função (Ativos / Desligados / Afastados)
B14: Função | C14: Ativos | D14: Desligados | E14: % do total ativos | F14: Afastados
B15: AJUDANTE DE BOMBEIRO PREDIAL | C15: {=SUMPRODUCT(ISNUMBER(SEARCH("743",'EFETIVO 11.05.2026'!$H$2:$H$712))*('EFETIVO 11.05.2026'!$G$2:$G$712="A")*('EFETIVO 11.05.2026'!$C$2:$C$712=B15))} -> 3 | D15: {=SUMPRODUCT(ISNUMBER(SEARCH("743",'EFETIVO 11.05.2026'!$H$2:$H$712))*('EFETIVO 11.05.2026'!$G$2:$G$712="D")*('EFETIVO 11.05.2026'!$C$2:$C$712=B15))} -> 1 | E15: =IFERROR(C15/$C$6,0) -> 0.0094043887 | F15: {=SUMPRODUCT(ISNUMBER(SEARCH("743",'EFETIVO 11.05.2026'!$H$2:$H$712))*(('EFETIVO 11.05.2026'!$G$2:$G$712="F")+('EFETIVO 11.05.2026'!$G$2:$G$712="P")+('EFETIVO 11.05.2026'!$G$2:$G$712="T")+('EFETIVO 11.05.2026'!$G$2:$G$712="M"))*('EFETIVO 11.05.2026'!$C$2:$C$712=$B15))} -> 0
B16: AJUDANTE DE CALDEIRARIA PREDIAL | C16: {=SUMPRODUCT(ISNUMBER(SEARCH("743",'EFETIVO 11.05.2026'!$H$2:$H$712))*('EFETIVO 11.05.2026'!$G$2:$G$712="A")*('EFETIVO 11.05.2026'!$C$2:$C$712=B16))} -> 1 | D16: {=SUMPRODUCT(ISNUMBER(SEARCH("743",'EFETIVO 11.05.2026'!$H$2:$H$712))*('EFETIVO 11.05.2026'!$G$2:$G$712="D")*('EFETIVO 11.05.2026'!$C$2:$C$712=B16))} -> 3 | E16: =IFERROR(C16/$C$6,0) -> 0.0031347962 | F16: {=SUMPRODUCT(ISNUMBER(SEARCH("743",'EFETIVO 11.05.2026'!$H$2:$H$712))*(('EFETIVO 11.05.2026'!$G$2:$G$712="F")+('EFETIVO 11.05.2026'!$G$2:$G$712="P")+('EFETIVO 11.05.2026'!$G$2:$G$712="T")+('EFETIVO 11.05.2026'!$G$2:$G$712="M"))*('EFETIVO 11.05.2026'!$C$2:$C$712=$B16))} -> 0
B17: AJUDANTE DE CARPINTEIRO | C17: {=SUMPRODUCT(ISNUMBER(SEARCH("743",'EFETIVO 11.05.2026'!$H$2:$H$712))*('EFETIVO 11.05.2026'!$G$2:$G$712="A")*('EFETIVO 11.05.2026'!$C$2:$C$712=B17))} -> 2 | D17: {=SUMPRODUCT(ISNUMBER(SEARCH("743",'EFETIVO 11.05.2026'!$H$2:$H$712))*('EFETIVO 11.05.2026'!$G$2:$G$712="D")*('EFETIVO 11.05.2026'!$C$2:$C$712=B17))} -> 1 | E17: =IFERROR(C17/$C$6,0) -> 0.0062695925 | F17: {=SUMPRODUCT(ISNUMBER(SEARCH("743",'EFETIVO 11.05.2026'!$H$2:$H$712))*(('EFETIVO 11.05.2026'!$G$2:$G$712="F")+('EFETIVO 11.05.2026'!$G$2:$G$712="P")+('EFETIVO 11.05.2026'!$G$2:$G$712="T")+('EFETIVO 11.05.2026'!$G$2:$G$712="M"))*('EFETIVO 11.05.2026'!$C$2:$C$712=$B17))} -> 0
B18: AJUDANTE DE ELETRICA PREDIAL | C18: {=SUMPRODUCT(ISNUMBER(SEARCH("743",'EFETIVO 11.05.2026'!$H$2:$H$712))*('EFETIVO 11.05.2026'!$G$2:$G$712="A")*('EFETIVO 11.05.2026'!$C$2:$C$712=B18))} -> 8 | D18: {=SUMPRODUCT(ISNUMBER(SEARCH("743",'EFETIVO 11.05.2026'!$H$2:$H$712))*('EFETIVO 11.05.2026'!$G$2:$G$712="D")*('EFETIVO 11.05.2026'!$C$2:$C$712=B18))} -> 3 | E18: =IFERROR(C18/$C$6,0) -> 0.02507837 | F18: {=SUMPRODUCT(ISNUMBER(SEARCH("743",'EFETIVO 11.05.2026'!$H$2:$H$712))*(('EFETIVO 11.05.2026'!$G$2:$G$712="F")+('EFETIVO 11.05.2026'!$G$2:$G$712="P")+('EFETIVO 11.05.2026'!$G$2:$G$712="T")+('EFETIVO 11.05.2026'!$G$2:$G$712="M"))*('EFETIVO 11.05.2026'!$C$2:$C$712=$B18))} -> 0
B19: AJUDANTE DE ELETROMECANICA PREDIAL | C19: {=SUMPRODUCT(ISNUMBER(SEARCH("743",'EFETIVO 11.05.2026'!$H$2:$H$712))*('EFETIVO 11.05.2026'!$G$2:$G$712="A")*('EFETIVO 11.05.2026'!$C$2:$C$712=B19))} -> 0 | D19: {=SUMPRODUCT(ISNUMBER(SEARCH("743",'EFETIVO 11.05.2026'!$H$2:$H$712))*('EFETIVO 11.05.2026'!$G$2:$G$712="D")*('EFETIVO 11.05.2026'!$C$2:$C$712=B19))} -> 1 | E19: =IFERROR(C19/$C$6,0) -> 0 | F19: {=SUMPRODUCT(ISNUMBER(SEARCH("743",'EFETIVO 11.05.2026'!$H$2:$H$712))*(('EFETIVO 11.05.2026'!$G$2:$G$712="F")+('EFETIVO 11.05.2026'!$G$2:$G$712="P")+('EFETIVO 11.05.2026'!$G$2:$G$712="T")+('EFETIVO 11.05.2026'!$G$2:$G$712="M"))*('EFETIVO 11.05.2026'!$C$2:$C$712=$B19))} -> 0
B20: AJUDANTE DE MANUTENCAO ELETRICA | C20: {=SUMPRODUCT(ISNUMBER(SEARCH("743",'EFETIVO 11.05.2026'!$H$2:$H$712))*('EFETIVO 11.05.2026'!$G$2:$G$712="A")*('EFETIVO 11.05.2026'!$C$2:$C$712=B20))} -> 4 | D20: {=SUMPRODUCT(ISNUMBER(SEARCH("743",'EFETIVO 11.05.2026'!$H$2:$H$712))*('EFETIVO 11.05.2026'!$G$2:$G$712="D")*('EFETIVO 11.05.2026'!$C$2:$C$712=B20))} -> 0 | E20: =IFERROR(C20/$C$6,0) -> 0.012539185 | F20: {=SUMPRODUCT(ISNUMBER(SEARCH("743",'EFETIVO 11.05.2026'!$H$2:$H$712))*(('EFETIVO 11.05.2026'!$G$2:$G$712="F")+('EFETIVO 11.05.2026'!$G$2:$G$712="P")+('EFETIVO 11.05.2026'!$G$2:$G$712="T")+('EFETIVO 11.05.2026'!$G$2:$G$712="M"))*('EFETIVO 11.05.2026'!$C$2:$C$712=$B20))} -> 0
B21: AJUDANTE DE MARCENEIRO | C21: {=SUMPRODUCT(ISNUMBER(SEARCH("743",'EFETIVO 11.05.2026'!$H$2:$H$712))*('EFETIVO 11.05.2026'!$G$2:$G$712="A")*('EFETIVO 11.05.2026'!$C$2:$C$712=B21))} -> 2 | D21: {=SUMPRODUCT(ISNUMBER(SEARCH("743",'EFETIVO 11.05.2026'!$H$2:$H$712))*('EFETIVO 11.05.2026'!$G$2:$G$712="D")*('EFETIVO 11.05.2026'!$C$2:$C$712=B21))} -> 0 | E21: =IFERROR(C21/$C$6,0) -> 0.0062695925 | F21: {=SUMPRODUCT(ISNUMBER(SEARCH("743",'EFETIVO 11.05.2026'!$H$2:$H$712))*(('EFETIVO 11.05.2026'!$G$2:$G$712="F")+('EFETIVO 11.05.2026'!$G$2:$G$712="P")+('EFETIVO 11.05.2026'!$G$2:$G$712="T")+('EFETIVO 11.05.2026'!$G$2:$G$712="M"))*('EFETIVO 11.05.2026'!$C$2:$C$712=$B21))} -> 0
B22: AJUDANTE DE MECANICA PREDIAL | C22: {=SUMPRODUCT(ISNUMBER(SEARCH("743",'EFETIVO 11.05.2026'!$H$2:$H$712))*('EFETIVO 11.05.2026'!$G$2:$G$712="A")*('EFETIVO 11.05.2026'!$C$2:$C$712=B22))} -> 3 | D22: {=SUMPRODUCT(ISNUMBER(SEARCH("743",'EFETIVO 11.05.2026'!$H$2:$H$712))*('EFETIVO 11.05.2026'!$G$2:$G$712="D")*('EFETIVO 11.05.2026'!$C$2:$C$712=B22))} -> 1 | E22: =IFERROR(C22/$C$6,0) -> 0.0094043887 | F22: {=SUMPRODUCT(ISNUMBER(SEARCH("743",'EFETIVO 11.05.2026'!$H$2:$H$712))*(('EFETIVO 11.05.2026'!$G$2:$G$712="F")+('EFETIVO 11.05.2026'!$G$2:$G$712="P")+('EFETIVO 11.05.2026'!$G$2:$G$712="T")+('EFETIVO 11.05.2026'!$G$2:$G$712="M"))*('EFETIVO 11.05.2026'!$C$2:$C$712=$B22))} -> 0
B23: AJUDANTE DE PEDREIRO | C23: {=SUMPRODUCT(ISNUMBER(SEARCH("743",'EFETIVO 11.05.2026'!$H$2:$H$712))*('EFETIVO 11.05.2026'!$G$2:$G$712="A")*('EFETIVO 11.05.2026'!$C$2:$C$712=B23))} -> 8 | D23: {=SUMPRODUCT(ISNUMBER(SEARCH("743",'EFETIVO 11.05.2026'!$H$2:$H$712))*('EFETIVO 11.05.2026'!$G$2:$G$712="D")*('EFETIVO 11.05.2026'!$C$2:$C$712=B23))} -> 2 | E23: =IFERROR(C23/$C$6,0) -> 0.02507837 | F23: {=SUMPRODUCT(ISNUMBER(SEARCH("743",'EFETIVO 11.05.2026'!$H$2:$H$712))*(('EFETIVO 11.05.2026'!$G$2:$G$712="F")+('EFETIVO 11.05.2026'!$G$2:$G$712="P")+('EFETIVO 11.05.2026'!$G$2:$G$712="T")+('EFETIVO 11.05.2026'!$G$2:$G$712="M"))*('EFETIVO 11.05.2026'!$C$2:$C$712=$B23))} -> 2
B24: AJUDANTE DE PINTURA | C24: {=SUMPRODUCT(ISNUMBER(SEARCH("743",'EFETIVO 11.05.2026'!$H$2:$H$712))*('EFETIVO 11.05.2026'!$G$2:$G$712="A")*('EFETIVO 11.05.2026'!$C$2:$C$712=B24))} -> 5 | D24: {=SUMPRODUCT(ISNUMBER(SEARCH("743",'EFETIVO 11.05.2026'!$H$2:$H$712))*('EFETIVO 11.05.2026'!$G$2:$G$712="D")*('EFETIVO 11.05.2026'!$C$2:$C$712=B24))} -> 5 | E24: =IFERROR(C24/$C$6,0) -> 0.015673981 | F24: {=SUMPRODUCT(ISNUMBER(SEARCH("743",'EFETIVO 11.05.2026'!$H$2:$H$712))*(('EFETIVO 11.05.2026'!$G$2:$G$712="F")+('EFETIVO 11.05.2026'!$G$2:$G$712="P")+('EFETIVO 11.05.2026'!$G$2:$G$712="T")+('EFETIVO 11.05.2026'!$G$2:$G$712="M"))*('EFETIVO 11.05.2026'!$C$2:$C$712=$B24))} -> 0
B25: AJUDANTE DE PINTURA INDUSTRIAL | C25: {=SUMPRODUCT(ISNUMBER(SEARCH("743",'EFETIVO 11.05.2026'!$H$2:$H$712))*('EFETIVO 11.05.2026'!$G$2:$G$712="A")*('EFETIVO 11.05.2026'!$C$2:$C$712=B25))} -> 1 | D25: {=SUMPRODUCT(ISNUMBER(SEARCH("743",'EFETIVO 11.05.2026'!$H$2:$H$712))*('EFETIVO 11.05.2026'!$G$2:$G$712="D")*('EFETIVO 11.05.2026'!$C$2:$C$712=B25))} -> 2 | E25: =IFERROR(C25/$C$6,0) -> 0.0031347962 | F25: {=SUMPRODUCT(ISNUMBER(SEARCH("743",'EFETIVO 11.05.2026'!$H$2:$H$712))*(('EFETIVO 11.05.2026'!$G$2:$G$712="F")+('EFETIVO 11.05.2026'!$G$2:$G$712="P")+('EFETIVO 11.05.2026'!$G$2:$G$712="T")+('EFETIVO 11.05.2026'!$G$2:$G$712="M"))*('EFETIVO 11.05.2026'!$C$2:$C$712=$B25))} -> 1
B26: AJUDANTE DE REFRIGERACAO | C26: {=SUMPRODUCT(ISNUMBER(SEARCH("743",'EFETIVO 11.05.2026'!$H$2:$H$712))*('EFETIVO 11.05.2026'!$G$2:$G$712="A")*('EFETIVO 11.05.2026'!$C$2:$C$712=B26))} -> 1 | D26: {=SUMPRODUCT(ISNUMBER(SEARCH("743",'EFETIVO 11.05.2026'!$H$2:$H$712))*('EFETIVO 11.05.2026'!$G$2:$G$712="D")*('EFETIVO 11.05.2026'!$C$2:$C$712=B26))} -> 0 | E26: =IFERROR(C26/$C$6,0) -> 0.0031347962 | F26: {=SUMPRODUCT(ISNUMBER(SEARCH("743",'EFETIVO 11.05.2026'!$H$2:$H$712))*(('EFETIVO 11.05.2026'!$G$2:$G$712="F")+('EFETIVO 11.05.2026'!$G$2:$G$712="P")+('EFETIVO 11.05.2026'!$G$2:$G$712="T")+('EFETIVO 11.05.2026'!$G$2:$G$712="M"))*('EFETIVO 11.05.2026'!$C$2:$C$712=$B26))} -> 0
... B72: OPERADOR DE ROCADEIRA | C72: {=SUMPRODUCT(ISNUMBER(SEARCH("743",'EFETIVO 11.05.2026'!$H$2:$H$712))*('EFETIVO 11.05.2026'!$G$2:$G$712="A")*('EFETIVO 11.05.2026'!$C$2:$C$712=B72))} -> 31 | D72: {=SUMPRODUCT(ISNUMBER(SEARCH("743",'EFETIVO 11.05.2026'!$H$2:$H$712))*('EFETIVO 11.05.2026'!$G$2:$G$712="D")*('EFETIVO 11.05.2026'!$C$2:$C$712=B72))} -> 2 | E72: =IFERROR(C72/$C$6,0) -> 0.097178683 | F72: {=SUMPRODUCT(ISNUMBER(SEARCH("743",'EFETIVO 11.05.2026'!$H$2:$H$712))*(('EFETIVO 11.05.2026'!$G$2:$G$712="F")+('EFETIVO 11.05.2026'!$G$2:$G$712="P")+('EFETIVO 11.05.2026'!$G$2:$G$712="T")+('EFETIVO 11.05.2026'!$G$2:$G$712="M"))*('EFETIVO 11.05.2026'!$C$2:$C$712=$B72))} -> 0
F73: {=SUMPRODUCT(ISNUMBER(SEARCH("743",'EFETIVO 11.05.2026'!$H$2:$H$712))*(('EFETIVO 11.05.2026'!$G$2:$G$712="F")+('EFETIVO 11.05.2026'!$G$2:$G$712="P")+('EFETIVO 11.05.2026'!$G$2:$G$712="T")+('EFETIVO 11.05.2026'!$G$2:$G$712="M"))*('EFETIVO 11.05.2026'!$C$2:$C$712=$B73))} -> 0
B74: PINTOR | C74: {=SUMPRODUCT(ISNUMBER(SEARCH("743",'EFETIVO 11.05.2026'!$H$2:$H$712))*('EFETIVO 11.05.2026'!$G$2:$G$712="A")*('EFETIVO 11.05.2026'!$C$2:$C$712=B74))} -> 9 | D74: {=SUMPRODUCT(ISNUMBER(SEARCH("743",'EFETIVO 11.05.2026'!$H$2:$H$712))*('EFETIVO 11.05.2026'!$G$2:$G$712="D")*('EFETIVO 11.05.2026'!$C$2:$C$712=B74))} -> 1 | F74: {=SUMPRODUCT(ISNUMBER(SEARCH("743",'EFETIVO 11.05.2026'!$H$2:$H$712))*(('EFETIVO 11.05.2026'!$G$2:$G$712="F")+('EFETIVO 11.05.2026'!$G$2:$G$712="P")+('EFETIVO 11.05.2026'!$G$2:$G$712="T")+('EFETIVO 11.05.2026'!$G$2:$G$712="M"))*('EFETIVO 11.05.2026'!$C$2:$C$712=$B74))} -> 0
B75: PINTOR INDUSTRIAL | C75: {=SUMPRODUCT(ISNUMBER(SEARCH("743",'EFETIVO 11.05.2026'!$H$2:$H$712))*('EFETIVO 11.05.2026'!$G$2:$G$712="A")*('EFETIVO 11.05.2026'!$C$2:$C$712=B75))} -> 6 | D75: {=SUMPRODUCT(ISNUMBER(SEARCH("743",'EFETIVO 11.05.2026'!$H$2:$H$712))*('EFETIVO 11.05.2026'!$G$2:$G$712="D")*('EFETIVO 11.05.2026'!$C$2:$C$712=B75))} -> 1 | F75: {=SUMPRODUCT(ISNUMBER(SEARCH("743",'EFETIVO 11.05.2026'!$H$2:$H$712))*(('EFETIVO 11.05.2026'!$G$2:$G$712="F")+('EFETIVO 11.05.2026'!$G$2:$G$712="P")+('EFETIVO 11.05.2026'!$G$2:$G$712="T")+('EFETIVO 11.05.2026'!$G$2:$G$712="M"))*('EFETIVO 11.05.2026'!$C$2:$C$712=$B75))} -> 0
B76: PLANEJADOR
B77: SOLDADOR
B78: SUPERVISOR DE AREAS VERDES | C78: {=SUMPRODUCT(ISNUMBER(SEARCH("743",'EFETIVO 11.05.2026'!$H$2:$H$712))*('EFETIVO 11.05.2026'!$G$2:$G$712="A")*('EFETIVO 11.05.2026'!$C$2:$C$712=B78))} -> 1 | D78: {=SUMPRODUCT(ISNUMBER(SEARCH("743",'EFETIVO 11.05.2026'!$H$2:$H$712))*('EFETIVO 11.05.2026'!$G$2:$G$712="D")*('EFETIVO 11.05.2026'!$C$2:$C$712=B78))} -> 0 | F78: {=SUMPRODUCT(ISNUMBER(SEARCH("743",'EFETIVO 11.05.2026'!$H$2:$H$712))*(('EFETIVO 11.05.2026'!$G$2:$G$712="F")+('EFETIVO 11.05.2026'!$G$2:$G$712="P")+('EFETIVO 11.05.2026'!$G$2:$G$712="T")+('EFETIVO 11.05.2026'!$G$2:$G$712="M"))*('EFETIVO 11.05.2026'!$C$2:$C$712=$B78))} -> 0
B79: SUPERVISOR DE ELETRICA | C79: {=SUMPRODUCT(ISNUMBER(SEARCH("743",'EFETIVO 11.05.2026'!$H$2:$H$712))*('EFETIVO 11.05.2026'!$G$2:$G$712="A")*('EFETIVO 11.05.2026'!$C$2:$C$712=B79))} -> 1 | D79: {=SUMPRODUCT(ISNUMBER(SEARCH("743",'EFETIVO 11.05.2026'!$H$2:$H$712))*('EFETIVO 11.05.2026'!$G$2:$G$712="D")*('EFETIVO 11.05.2026'!$C$2:$C$712=B79))} -> 0 | F79: {=SUMPRODUCT(ISNUMBER(SEARCH("743",'EFETIVO 11.05.2026'!$H$2:$H$712))*(('EFETIVO 11.05.2026'!$G$2:$G$712="F")+('EFETIVO 11.05.2026'!$G$2:$G$712="P")+('EFETIVO 11.05.2026'!$G$2:$G$712="T")+('EFETIVO 11.05.2026'!$G$2:$G$712="M"))*('EFETIVO 11.05.2026'!$C$2:$C$712=$B79))} -> 0
B80: SUPERVISOR DE ELETROMECANICA | C80: {=SUMPRODUCT(ISNUMBER(SEARCH("743",'EFETIVO 11.05.2026'!$H$2:$H$712))*('EFETIVO 11.05.2026'!$G$2:$G$712="A")*('EFETIVO 11.05.2026'!$C$2:$C$712=B80))} -> 0 | D80: {=SUMPRODUCT(ISNUMBER(SEARCH("743",'EFETIVO 11.05.2026'!$H$2:$H$712))*('EFETIVO 11.05.2026'!$G$2:$G$712="D")*('EFETIVO 11.05.2026'!$C$2:$C$712=B80))} -> 1 | F80: {=SUMPRODUCT(ISNUMBER(SEARCH("743",'EFETIVO 11.05.2026'!$H$2:$H$712))*(('EFETIVO 11.05.2026'!$G$2:$G$712="F")+('EFETIVO 11.05.2026'!$G$2:$G$712="P")+('EFETIVO 11.05.2026'!$G$2:$G$712="T")+('EFETIVO 11.05.2026'!$G$2:$G$712="M"))*('EFETIVO 11.05.2026'!$C$2:$C$712=$B80))} -> 0
B81: SUPERVISOR DE LIMPEZA E CONSERVACAO | C81: {=SUMPRODUCT(ISNUMBER(SEARCH("743",'EFETIVO 11.05.2026'!$H$2:$H$712))*('EFETIVO 11.05.2026'!$G$2:$G$712="A")*('EFETIVO 11.05.2026'!$C$2:$C$712=B81))} -> 1 | D81: {=SUMPRODUCT(ISNUMBER(SEARCH("743",'EFETIVO 11.05.2026'!$H$2:$H$712))*('EFETIVO 11.05.2026'!$G$2:$G$712="D")*('EFETIVO 11.05.2026'!$C$2:$C$712=B81))} -> 0 | F81: {=SUMPRODUCT(ISNUMBER(SEARCH("743",'EFETIVO 11.05.2026'!$H$2:$H$712))*(('EFETIVO 11.05.2026'!$G$2:$G$712="F")+('EFETIVO 11.05.2026'!$G$2:$G$712="P")+('EFETIVO 11.05.2026'!$G$2:$G$712="T")+('EFETIVO 11.05.2026'!$G$2:$G$712="M"))*('EFETIVO 11.05.2026'!$C$2:$C$712=$B81))} -> 0
B82: SUPERVISOR DE MANUTENCAO CIVIL | C82: {=SUMPRODUCT(ISNUMBER(SEARCH("743",'EFETIVO 11.05.2026'!$H$2:$H$712))*('EFETIVO 11.05.2026'!$G$2:$G$712="A")*('EFETIVO 11.05.2026'!$C$2:$C$712=B82))} -> 3 | D82: {=SUMPRODUCT(ISNUMBER(SEARCH("743",'EFETIVO 11.05.2026'!$H$2:$H$712))*('EFETIVO 11.05.2026'!$G$2:$G$712="D")*('EFETIVO 11.05.2026'!$C$2:$C$712=B82))} -> 0 | F82: {=SUMPRODUCT(ISNUMBER(SEARCH("743",'EFETIVO 11.05.2026'!$H$2:$H$712))*(('EFETIVO 11.05.2026'!$G$2:$G$712="F")+('EFETIVO 11.05.2026'!$G$2:$G$712="P")+('EFETIVO 11.05.2026'!$G$2:$G$712="T")+('EFETIVO 11.05.2026'!$G$2:$G$712="M"))*('EFETIVO 11.05.2026'!$C$2:$C$712=$B82))} -> 0
B83: SUPERVISOR DE PLANEJAMENTO | C83: {=SUMPRODUCT(ISNUMBER(SEARCH("743",'EFETIVO 11.05.2026'!$H$2:$H$712))*('EFETIVO 11.05.2026'!$G$2:$G$712="A")*('EFETIVO 11.05.2026'!$C$2:$C$712=B83))} -> 1 | D83: {=SUMPRODUCT(ISNUMBER(SEARCH("743",'EFETIVO 11.05.2026'!$H$2:$H$712))*('EFETIVO 11.05.2026'!$G$2:$G$712="D")*('EFETIVO 11.05.2026'!$C$2:$C$712=B83))} -> 0 | F83: {=SUMPRODUCT(ISNUMBER(SEARCH("743",'EFETIVO 11.05.2026'!$H$2:$H$712))*(('EFETIVO 11.05.2026'!$G$2:$G$712="F")+('EFETIVO 11.05.2026'!$G$2:$G$712="P")+('EFETIVO 11.05.2026'!$G$2:$G$712="T")+('EFETIVO 11.05.2026'!$G$2:$G$712="M"))*('EFETIVO 11.05.2026'!$C$2:$C$712=$B83))} -> 0
B84: TECNICO AGRONOMO | C84: {=SUMPRODUCT(ISNUMBER(SEARCH("743",'EFETIVO 11.05.2026'!$H$2:$H$712))*('EFETIVO 11.05.2026'!$G$2:$G$712="A")*('EFETIVO 11.05.2026'!$C$2:$C$712=B84))} -> 1 | D84: {=SUMPRODUCT(ISNUMBER(SEARCH("743",'EFETIVO 11.05.2026'!$H$2:$H$712))*('EFETIVO 11.05.2026'!$G$2:$G$712="D")*('EFETIVO 11.05.2026'!$C$2:$C$712=B84))} -> 0 | F84: {=SUMPRODUCT(ISNUMBER(SEARCH("743",'EFETIVO 11.05.2026'!$H$2:$H$712))*(('EFETIVO 11.05.2026'!$G$2:$G$712="F")+('EFETIVO 11.05.2026'!$G$2:$G$712="P")+('EFETIVO 11.05.2026'!$G$2:$G$712="T")+('EFETIVO 11.05.2026'!$G$2:$G$712="M"))*('EFETIVO 11.05.2026'!$C$2:$C$712=$B84))} -> 0
B85: TECNICO DE ELETRICA | C85: {=SUMPRODUCT(ISNUMBER(SEARCH("743",'EFETIVO 11.05.2026'!$H$2:$H$712))*('EFETIVO 11.05.2026'!$G$2:$G$712="A")*('EFETIVO 11.05.2026'!$C$2:$C$712=B85))} -> 4 | D85: {=SUMPRODUCT(ISNUMBER(SEARCH("743",'EFETIVO 11.05.2026'!$H$2:$H$712))*('EFETIVO 11.05.2026'!$G$2:$G$712="D")*('EFETIVO 11.05.2026'!$C$2:$C$712=B85))} -> 2 | F85: {=SUMPRODUCT(ISNUMBER(SEARCH("743",'EFETIVO 11.05.2026'!$H$2:$H$712))*(('EFETIVO 11.05.2026'!$G$2:$G$712="F")+('EFETIVO 11.05.2026'!$G$2:$G$712="P")+('EFETIVO 11.05.2026'!$G$2:$G$712="T")+('EFETIVO 11.05.2026'!$G$2:$G$712="M"))*('EFETIVO 11.05.2026'!$C$2:$C$712=$B85))} -> 0
B86: TECNICO DE MECANICA | C86: {=SUMPRODUCT(ISNUMBER(SEARCH("743",'EFETIVO 11.05.2026'!$H$2:$H$712))*('EFETIVO 11.05.2026'!$G$2:$G$712="A")*('EFETIVO 11.05.2026'!$C$2:$C$712=B86))} -> 1 | D86: {=SUMPRODUCT(ISNUMBER(SEARCH("743",'EFETIVO 11.05.2026'!$H$2:$H$712))*('EFETIVO 11.05.2026'!$G$2:$G$712="D")*('EFETIVO 11.05.2026'!$C$2:$C$712=B86))} -> 1 | F86: {=SUMPRODUCT(ISNUMBER(SEARCH("743",'EFETIVO 11.05.2026'!$H$2:$H$712))*(('EFETIVO 11.05.2026'!$G$2:$G$712="F")+('EFETIVO 11.05.2026'!$G$2:$G$712="P")+('EFETIVO 11.05.2026'!$G$2:$G$712="T")+('EFETIVO 11.05.2026'!$G$2:$G$712="M"))*('EFETIVO 11.05.2026'!$C$2:$C$712=$B86))} -> 0
B87: TECNICO DE SEGURANCA DO TRABALHO | C87: {=SUMPRODUCT(ISNUMBER(SEARCH("743",'EFETIVO 11.05.2026'!$H$2:$H$712))*('EFETIVO 11.05.2026'!$G$2:$G$712="A")*('EFETIVO 11.05.2026'!$C$2:$C$712=B87))} -> 5 | D87: {=SUMPRODUCT(ISNUMBER(SEARCH("743",'EFETIVO 11.05.2026'!$H$2:$H$712))*('EFETIVO 11.05.2026'!$G$2:$G$712="D")*('EFETIVO 11.05.2026'!$C$2:$C$712=B87))} -> 3 | F87: {=SUMPRODUCT(ISNUMBER(SEARCH("743",'EFETIVO 11.05.2026'!$H$2:$H$712))*(('EFETIVO 11.05.2026'!$G$2:$G$712="F")+('EFETIVO 11.05.2026'!$G$2:$G$712="P")+('EFETIVO 11.05.2026'!$G$2:$G$712="T")+('EFETIVO 11.05.2026'!$G$2:$G$712="M"))*('EFETIVO 11.05.2026'!$C$2:$C$712=$B87))} -> 1
B88: TECNICO DE SEGURANCA DO TRABALHO II
B89: TECNICO EM AUTOMACAO
B90: TOTAL | C90: =C6 -> 319 | D90: =C7 -> 101 | F90: =SUM(F15:F89) -> 12
B91: # | C91: Função | D91: Nome do único ocupante | E91: Base | F91: Admissão
B92: 1 | C92: {=IFERROR(INDEX($B$15:$B$89,SMALL(IF($C$15:$C$89=1,ROW($C$15:$C$89)-ROW($C$15)+1),$B92)),"")} -> AJUDANTE DE CALDEIRARIA PREDIAL | D92: {=IF(C92="","",IFERROR(INDEX('EFETIVO 11.05.2026'!$B$2:$B$712,MATCH(1,(ISNUMBER(SEARCH("743",'EFETIVO 11.05.2026'!$H$2:$H$712)))*('EFETIVO 11.05.2026'!$G$2:$G$712="A")*('EFETIVO 11.05.2026'!$C$2:$C$712=C92),0)),""))} -> LUCAS OLIVEIRA DE PAULA | E92: {=IF(C92="","",IFERROR(INDEX('EFETIVO 11.05.2026'!$I$2:$I$712,MATCH(1,(ISNUMBER(SEARCH("743",'EFETIVO 11.05.2026'!$H$2:$H$712)))*('EFETIVO 11.05.2026'!$G$2:$G$712="A")*('EFETIVO 11.05.2026'!$C$2:$C$712=C92),0)),""))} -> CABIUNAS | F92: {=IF(C92="","",IFERROR(INDEX('EFETIVO 11.05.2026'!$E$2:$E$712,MATCH(1,(ISNUMBER(SEARCH("743",'EFETIVO 11.05.2026'!$H$2:$H$712)))*('EFETIVO 11.05.2026'!$G$2:$G$712="A")*('EFETIVO 11.05.2026'!$C$2:$C$712=C92),0)),""))} -> 45779
B93: 2 | C93: {=IFERROR(INDEX($B$15:$B$89,SMALL(IF($C$15:$C$89=1,ROW($C$15:$C$89)-ROW($C$15)+1),$B93)),"")} -> AJUDANTE DE PINTURA INDUSTRIAL | D93: {=IF(C93="","",IFERROR(INDEX('EFETIVO 11.05.2026'!$B$2:$B$712,MATCH(1,(ISNUMBER(SEARCH("743",'EFETIVO 11.05.2026'!$H$2:$H$712)))*('EFETIVO 11.05.2026'!$G$2:$G$712="A")*('EFETIVO 11.05.2026'!$C$2:$C$712=C93),0)),""))} -> MANOEL CAETANO DAS CANDEIAS | E93: {=IF(C93="","",IFERROR(INDEX('EFETIVO 11.05.2026'!$I$2:$I$712,MATCH(1,(ISNUMBER(SEARCH("743",'EFETIVO 11.05.2026'!$H$2:$H$712)))*('EFETIVO 11.05.2026'!$G$2:$G$712="A")*('EFETIVO 11.05.2026'!$C$2:$C$712=C93),0)),""))} -> CABIUNAS | F93: {=IF(C93="","",IFERROR(INDEX('EFETIVO 11.05.2026'!$E$2:$E$712,MATCH(1,(ISNUMBER(SEARCH("743",'EFETIVO 11.05.2026'!$H$2:$H$712)))*('EFETIVO 11.05.2026'!$G$2:$G$712="A")*('EFETIVO 11.05.2026'!$C$2:$C$712=C93),0)),""))} -> 45810
B94: 3 | C94: {=IFERROR(INDEX($B$15:$B$89,SMALL(IF($C$15:$C$89=1,ROW($C$15:$C$89)-ROW($C$15)+1),$B94)),"")} -> AJUDANTE DE REFRIGERACAO | D94: {=IF(C94="","",IFERROR(INDEX('EFETIVO 11.05.2026'!$B$2:$B$712,MATCH(1,(ISNUMBER(SEARCH("743",'EFETIVO 11.05.2026'!$H$2:$H$712)))*('EFETIVO 11.05.2026'!$G$2:$G$712="A")*('EFETIVO 11.05.2026'!$C$2:$C$712=C94),0)),""))} -> HIAN DO NASCIMENTO QUEIROZ | E94: {=IF(C94="","",IFERROR(INDEX('EFETIVO 11.05.2026'!$I$2:$I$712,MATCH(1,(ISNUMBER(SEARCH("743",'EFETIVO 11.05.2026'!$H$2:$H$712)))*('EFETIVO 11.05.2026'!$G$2:$G$712="A")*('EFETIVO 11.05.2026'!$C$2:$C$712=C94),0)),""))} -> CABIUNAS | F94: {=IF(C94="","",IFERROR(INDEX('EFETIVO 11.05.2026'!$E$2:$E$712,MATCH(1,(ISNUMBER(SEARCH("743",'EFETIVO 11.05.2026'!$H$2:$H$712)))*('EFETIVO 11.05.2026'!$G$2:$G$712="A")*('EFETIVO 11.05.2026'!$C$2:$C$712=C94),0)),""))} -> 46128
B95: 4 | C95: {=IFERROR(INDEX($B$15:$B$89,SMALL(IF($C$15:$C$89=1,ROW($C$15:$C$89)-ROW($C$15)+1),$B95)),"")} -> ASSISTENTE DE LOGISTICA I | D95: {=IF(C95="","",IFERROR(INDEX('EFETIVO 11.05.2026'!$B$2:$B$712,MATCH(1,(ISNUMBER(SEARCH("743",'EFETIVO 11.05.2026'!$H$2:$H$712)))*('EFETIVO 11.05.2026'!$G$2:$G$712="A")*('EFETIVO 11.05.2026'!$C$2:$C$712=C95),0)),""))} -> POLIANE LAPA MARINS | E95: {=IF(C95="","",IFERROR(INDEX('EFETIVO 11.05.2026'!$I$2:$I$712,MATCH(1,(ISNUMBER(SEARCH("743",'EFETIVO 11.05.2026'!$H$2:$H$712)))*('EFETIVO 11.05.2026'!$G$2:$G$712="A")*('EFETIVO 11.05.2026'!$C$2:$C$712=C95),0)),""))} -> CABIUNAS | F95: {=IF(C95="","",IFERROR(INDEX('EFETIVO 11.05.2026'!$E$2:$E$712,MATCH(1,(ISNUMBER(SEARCH("743",'EFETIVO 11.05.2026'!$H$2:$H$712)))*('EFETIVO 11.05.2026'!$G$2:$G$712="A")*('EFETIVO 11.05.2026'!$C$2:$C$712=C95),0)),""))} -> 45358
B96: 5 | C96: {=IFERROR(INDEX($B$15:$B$89,SMALL(IF($C$15:$C$89=1,ROW($C$15:$C$89)-ROW($C$15)+1),$B96)),"")} -> AUXILIAR DE MANUTENCAO EM CALDEIRARIA | D96: {=IF(C96="","",IFERROR(INDEX('EFETIVO 11.05.2026'!$B$2:$B$712,MATCH(1,(ISNUMBER(SEARCH("743",'EFETIVO 11.05.2026'!$H$2:$H$712)))*('EFETIVO 11.05.2026'!$G$2:$G$712="A")*('EFETIVO 11.05.2026'!$C$2:$C$712=C96),0)),""))} -> LUCAS AZEVEDO DA SILVA | E96: {=IF(C96="","",IFERROR(INDEX('EFETIVO 11.05.2026'!$I$2:$I$712,MATCH(1,(ISNUMBER(SEARCH("743",'EFETIVO 11.05.2026'!$H$2:$H$712)))*('EFETIVO 11.05.2026'!$G$2:$G$712="A")*('EFETIVO 11.05.2026'!$C$2:$C$712=C96),0)),""))} -> CABIUNAS | F96: {=IF(C96="","",IFERROR(INDEX('EFETIVO 11.05.2026'!$E$2:$E$712,MATCH(1,(ISNUMBER(SEARCH("743",'EFETIVO 11.05.2026'!$H$2:$H$712)))*('EFETIVO 11.05.2026'!$G$2:$G$712="A")*('EFETIVO 11.05.2026'!$C$2:$C$712=C96),0)),""))} -> 46090
B97: 6 | C97: {=IFERROR(INDEX($B$15:$B$89,SMALL(IF($C$15:$C$89=1,ROW($C$15:$C$89)-ROW($C$15)+1),$B97)),"")} -> COORDENADOR DE MANUTENCAO | D97: {=IF(C97="","",IFERROR(INDEX('EFETIVO 11.05.2026'!$B$2:$B$712,MATCH(1,(ISNUMBER(SEARCH("743",'EFETIVO 11.05.2026'!$H$2:$H$712)))*('EFETIVO 11.05.2026'!$G$2:$G$712="A")*('EFETIVO 11.05.2026'!$C$2:$C$712=C97),0)),""))} -> LETICIA APARECIDA CIRILO PESSANHA | E97: {=IF(C97="","",IFERROR(INDEX('EFETIVO 11.05.2026'!$I$2:$I$712,MATCH(1,(ISNUMBER(SEARCH("743",'EFETIVO 11.05.2026'!$H$2:$H$712)))*('EFETIVO 11.05.2026'!$G$2:$G$712="A")*('EFETIVO 11.05.2026'!$C$2:$C$712=C97),0)),""))} -> CABIUNAS | F97: {=IF(C97="","",IFERROR(INDEX('EFETIVO 11.05.2026'!$E$2:$E$712,MATCH(1,(ISNUMBER(SEARCH("743",'EFETIVO 11.05.2026'!$H$2:$H$712)))*('EFETIVO 11.05.2026'!$G$2:$G$712="A")*('EFETIVO 11.05.2026'!$C$2:$C$712=C97),0)),""))} -> 46084
B98: 7 | C98: {=IFERROR(INDEX($B$15:$B$89,SMALL(IF($C$15:$C$89=1,ROW($C$15:$C$89)-ROW($C$15)+1),$B98)),"")} -> ELETRICISTA | D98: {=IF(C98="","",IFERROR(INDEX('EFETIVO 11.05.2026'!$B$2:$B$712,MATCH(1,(ISNUMBER(SEARCH("743",'EFETIVO 11.05.2026'!$H$2:$H$712)))*('EFETIVO 11.05.2026'!$G$2:$G$712="A")*('EFETIVO 11.05.2026'!$C$2:$C$712=C98),0)),""))} -> CRISTIANO MOREIRA DE OLIVEIRA | E98: {=IF(C98="","",IFERROR(INDEX('EFETIVO 11.05.2026'!$I$2:$I$712,MATCH(1,(ISNUMBER(SEARCH("743",'EFETIVO 11.05.2026'!$H$2:$H$712)))*('EFETIVO 11.05.2026'!$G$2:$G$712="A")*('EFETIVO 11.05.2026'!$C$2:$C$712=C98),0)),""))} -> CABIUNAS | F98: {=IF(C98="","",IFERROR(INDEX('EFETIVO 11.05.2026'!$E$2:$E$712,MATCH(1,(ISNUMBER(SEARCH("743",'EFETIVO 11.05.2026'!$H$2:$H$712)))*('EFETIVO 11.05.2026'!$G$2:$G$712="A")*('EFETIVO 11.05.2026'!$C$2:$C$712=C98),0)),""))} -> 45890
B99: 8 | C99: {=IFERROR(INDEX($B$15:$B$89,SMALL(IF($C$15:$C$89=1,ROW($C$15:$C$89)-ROW($C$15)+1),$B99)),"")} -> ENCARREGADO DE ANDAIME | D99: {=IF(C99="","",IFERROR(INDEX('EFETIVO 11.05.2026'!$B$2:$B$712,MATCH(1,(ISNUMBER(SEARCH("743",'EFETIVO 11.05.2026'!$H$2:$H$712)))*('EFETIVO 11.05.2026'!$G$2:$G$712="A")*('EFETIVO 11.05.2026'!$C$2:$C$712=C99),0)),""))} -> LUIS VALERIO DOS SANTOS | E99: {=IF(C99="","",IFERROR(INDEX('EFETIVO 11.05.2026'!$I$2:$I$712,MATCH(1,(ISNUMBER(SEARCH("743",'EFETIVO 11.05.2026'!$H$2:$H$712)))*('EFETIVO 11.05.2026'!$G$2:$G$712="A")*('EFETIVO 11.05.2026'!$C$2:$C$712=C99),0)),""))} -> CABIUNAS | F99: {=IF(C99="","",IFERROR(INDEX('EFETIVO 11.05.2026'!$E$2:$E$712,MATCH(1,(ISNUMBER(SEARCH("743",'EFETIVO 11.05.2026'!$H$2:$H$712)))*('EFETIVO 11.05.2026'!$G$2:$G$712="A")*('EFETIVO 11.05.2026'!$C$2:$C$712=C99),0)),""))} -> 45840
B100: 9 | C100: {=IFERROR(INDEX($B$15:$B$89,SMALL(IF($C$15:$C$89=1,ROW($C$15:$C$89)-ROW($C$15)+1),$B100)),"")} -> ENCARREGADO DE CONSERVACAO E LIMPEZA | D100: {=IF(C100="","",IFERROR(INDEX('EFETIVO 11.05.2026'!$B$2:$B$712,MATCH(1,(ISNUMBER(SEARCH("743",'EFETIVO 11.05.2026'!$H$2:$H$712)))*('EFETIVO 11.05.2026'!$G$2:$G$712="A")*('EFETIVO 11.05.2026'!$C$2:$C$712=C100),0)),""))} -> VALDENICE DOS SANTOS LEMOS | E100: {=IF(C100="","",IFERROR(INDEX('EFETIVO 11.05.2026'!$I$2:$I$712,MATCH(1,(ISNUMBER(SEARCH("743",'EFETIVO 11.05.2026'!$H$2:$H$712)))*('EFETIVO 11.05.2026'!$G$2:$G$712="A")*('EFETIVO 11.05.2026'!$C$2:$C$712=C100),0)),""))} -> CABIUNAS | F100: {=IF(C100="","",IFERROR(INDEX('EFETIVO 11.05.2026'!$E$2:$E$712,MATCH(1,(ISNUMBER(SEARCH("743",'EFETIVO 11.05.2026'!$H$2:$H$712)))*('EFETIVO 11.05.2026'!$G$2:$G$712="A")*('EFETIVO 11.05.2026'!$C$2:$C$712=C100),0)),""))} -> 45763
B101: 10 | C101: {=IFERROR(INDEX($B$15:$B$89,SMALL(IF($C$15:$C$89=1,ROW($C$15:$C$89)-ROW($C$15)+1),$B101)),"")} -> ENCARREGADO DE ELETRICA | D101: {=IF(C101="","",IFERROR(INDEX('EFETIVO 11.05.2026'!$B$2:$B$712,MATCH(1,(ISNUMBER(SEARCH("743",'EFETIVO 11.05.2026'!$H$2:$H$712)))*('EFETIVO 11.05.2026'!$G$2:$G$712="A")*('EFETIVO 11.05.2026'!$C$2:$C$712=C101),0)),""))} -> DIARLEN CALDEIRA DO ESPIRITO SANTO | E101: {=IF(C101="","",IFERROR(INDEX('EFETIVO 11.05.2026'!$I$2:$I$712,MATCH(1,(ISNUMBER(SEARCH("743",'EFETIVO 11.05.2026'!$H$2:$H$712)))*('EFETIVO 11.05.2026'!$G$2:$G$712="A")*('EFETIVO 11.05.2026'!$C$2:$C$712=C101),0)),""))} -> CABIUNAS | F101: {=IF(C101="","",IFERROR(INDEX('EFETIVO 11.05.2026'!$E$2:$E$712,MATCH(1,(ISNUMBER(SEARCH("743",'EFETIVO 11.05.2026'!$H$2:$H$712)))*('EFETIVO 11.05.2026'!$G$2:$G$712="A")*('EFETIVO 11.05.2026'!$C$2:$C$712=C101),0)),""))} -> 45779
B102: 11 | C102: {=IFERROR(INDEX($B$15:$B$89,SMALL(IF($C$15:$C$89=1,ROW($C$15:$C$89)-ROW($C$15)+1),$B102)),"")} -> ENCARREGADO DE ELETROMECANICA | D102: {=IF(C102="","",IFERROR(INDEX('EFETIVO 11.05.2026'!$B$2:$B$712,MATCH(1,(ISNUMBER(SEARCH("743",'EFETIVO 11.05.2026'!$H$2:$H$712)))*('EFETIVO 11.05.2026'!$G$2:$G$712="A")*('EFETIVO 11.05.2026'!$C$2:$C$712=C102),0)),""))} -> CARLOS HENRIQUE ALVES DE OLIVEIRA | E102: {=IF(C102="","",IFERROR(INDEX('EFETIVO 11.05.2026'!$I$2:$I$712,MATCH(1,(ISNUMBER(SEARCH("743",'EFETIVO 11.05.2026'!$H$2:$H$712)))*('EFETIVO 11.05.2026'!$G$2:$G$712="A")*('EFETIVO 11.05.2026'!$C$2:$C$712=C102),0)),""))} -> CABIUNAS | F102: {=IF(C102="","",IFERROR(INDEX('EFETIVO 11.05.2026'!$E$2:$E$712,MATCH(1,(ISNUMBER(SEARCH("743",'EFETIVO 11.05.2026'!$H$2:$H$712)))*('EFETIVO 11.05.2026'!$G$2:$G$712="A")*('EFETIVO 11.05.2026'!$C$2:$C$712=C102),0)),""))} -> 45772
B103: 12 | C103: {=IFERROR(INDEX($B$15:$B$89,SMALL(IF($C$15:$C$89=1,ROW($C$15:$C$89)-ROW($C$15)+1),$B103)),"")} -> ENGENHEIRO CIVIL | D103: {=IF(C103="","",IFERROR(INDEX('EFETIVO 11.05.2026'!$B$2:$B$712,MATCH(1,(ISNUMBER(SEARCH("743",'EFETIVO 11.05.2026'!$H$2:$H$712)))*('EFETIVO 11.05.2026'!$G$2:$G$712="A")*('EFETIVO 11.05.2026'!$C$2:$C$712=C103),0)),""))} -> GABRIELLA RODRIGUES PINTO | E103: {=IF(C103="","",IFERROR(INDEX('EFETIVO 11.05.2026'!$I$2:$I$712,MATCH(1,(ISNUMBER(SEARCH("743",'EFETIVO 11.05.2026'!$H$2:$H$712)))*('EFETIVO 11.05.2026'!$G$2:$G$712="A")*('EFETIVO 11.05.2026'!$C$2:$C$712=C103),0)),""))} -> CABIUNAS | F103: {=IF(C103="","",IFERROR(INDEX('EFETIVO 11.05.2026'!$E$2:$E$712,MATCH(1,(ISNUMBER(SEARCH("743",'EFETIVO 11.05.2026'!$H$2:$H$712)))*('EFETIVO 11.05.2026'!$G$2:$G$712="A")*('EFETIVO 11.05.2026'!$C$2:$C$712=C103),0)),""))} -> 45749
... B111: 20 | C111: {=IFERROR(INDEX($B$15:$B$89,SMALL(IF($C$15:$C$89=1,ROW($C$15:$C$89)-ROW($C$15)+1),$B111)),"")} -> OPERADOR DE RETRO ESCAVADEIRA | D111: {=IF(C111="","",IFERROR(INDEX('EFETIVO 11.05.2026'!$B$2:$B$712,MATCH(1,(ISNUMBER(SEARCH("743",'EFETIVO 11.05.2026'!$H$2:$H$712)))*('EFETIVO 11.05.2026'!$G$2:$G$712="A")*('EFETIVO 11.05.2026'!$C$2:$C$712=C111),0)),""))} -> LEOMAR GOMES DA SILVA | E111: {=IF(C111="","",IFERROR(INDEX('EFETIVO 11.05.2026'!$I$2:$I$712,MATCH(1,(ISNUMBER(SEARCH("743",'EFETIVO 11.05.2026'!$H$2:$H$712)))*('EFETIVO 11.05.2026'!$G$2:$G$712="A")*('EFETIVO 11.05.2026'!$C$2:$C$712=C111),0)),""))} -> CABIUNAS | F111: {=IF(C111="","",IFERROR(INDEX('EFETIVO 11.05.2026'!$E$2:$E$712,MATCH(1,(ISNUMBER(SEARCH("743",'EFETIVO 11.05.2026'!$H$2:$H$712)))*('EFETIVO 11.05.2026'!$G$2:$G$712="A")*('EFETIVO 11.05.2026'!$C$2:$C$712=C111),0)),""))} -> 45772
B114: 5. Movimentação Histórica - Admissões e Desligamentos por Ano
B115: Base: coluna ADMISSÃO conta entradas; coluna DEMISSÃO conta saídas. Filtro: PROJETO contém 743.
B117: Ano | C117: Admissões | D117: Desligamentos | E117: Saldo líquido
B118: 2024 | C118: {=SUMPRODUCT(ISNUMBER(SEARCH("743",'EFETIVO 11.05.2026'!$H$2:$H$712))*(YEAR('EFETIVO 11.05.2026'!$E$2:$E$712)=2024))} -> 5 | D118: {=SUMPRODUCT(ISNUMBER(SEARCH("743",'EFETIVO 11.05.2026'!$H$2:$H$712))*(IFERROR(YEAR('EFETIVO 11.05.2026'!$F$2:$F$712),0)=2024))} -> 0 | E118: =C118-D118 -> 5
B119: 2025 | C119: {=SUMPRODUCT(ISNUMBER(SEARCH("743",'EFETIVO 11.05.2026'!$H$2:$H$712))*(YEAR('EFETIVO 11.05.2026'!$E$2:$E$712)=2025))} -> 380 | D119: {=SUMPRODUCT(ISNUMBER(SEARCH("743",'EFETIVO 11.05.2026'!$H$2:$H$712))*(IFERROR(YEAR('EFETIVO 11.05.2026'!$F$2:$F$712),0)=2025))} -> 66 | E119: =C119-D119 -> 314
B120: 2026 | C120: {=SUMPRODUCT(ISNUMBER(SEARCH("743",'EFETIVO 11.05.2026'!$H$2:$H$712))*(YEAR('EFETIVO 11.05.2026'!$E$2:$E$712)=2026))} -> 46 | D120: {=SUMPRODUCT(ISNUMBER(SEARCH("743",'EFETIVO 11.05.2026'!$H$2:$H$712))*(IFERROR(YEAR('EFETIVO 11.05.2026'!$F$2:$F$712),0)=2026))} -> 35 | E120: =C120-D120 -> 11
B121: TOTAL | C121: =SUM(C118:C120) -> 431 | D121: =SUM(D118:D120) -> 101 | E121: =C121-D121 -> 330

Sheet Análises 743
A1: NORMATEL • Análises Projeto 743
A2: Cálculos dinâmicos sobre EFETIVO 11.05.2026 - Situações (SIT): A=Ativo, D=Desligado, F=Férias, P=INSS, T=Acidente de Trabalho, M=Serviço Militar
B4: 1. Indicadores do Projeto 743
B5: Total de registros vinculados ao 743 (todas situações) | C5: {=SUMPRODUCT(ISNUMBER(SEARCH("743",'EFETIVO 11.05.2026'!$H$2:$H$712))*(('EFETIVO 11.05.2026'!$G$2:$G$712="A")+('EFETIVO 11.05.2026'!$G$2:$G$712="D")+('EFETIVO 11.05.2026'!$G$2:$G$712="F")+('EFETIVO 11.05.2026'!$G$2:$G$712="P")+('EFETIVO 11.05.2026'!$G$2:$G$712="T")+('EFETIVO 11.05.2026'!$G$2:$G$712="M")))} -> 433
B6: Ativos no 743 | C6: {=SUMPRODUCT(ISNUMBER(SEARCH("743",'EFETIVO 11.05.2026'!$H$2:$H$712))*('EFETIVO 11.05.2026'!$G$2:$G$712="A"))} -> 319
B7: Desligados no 743 | C7: {=SUMPRODUCT(ISNUMBER(SEARCH("743",'EFETIVO 11.05.2026'!$H$2:$H$712))*('EFETIVO 11.05.2026'!$G$2:$G$712="D"))} -> 101
B8: % de turnover (desligados / total) | C8: =IFERROR(C7/C5,0) -> 0.23325635
B9: Afastados no 743 (F+P+T+M) | C9: {=SUMPRODUCT(ISNUMBER(SEARCH("743",'EFETIVO 11.05.2026'!$H$2:$H$712))*(('EFETIVO 11.05.2026'!$G$2:$G$712="F")+('EFETIVO 11.05.2026'!$G$2:$G$712="P")+('EFETIVO 11.05.2026'!$G$2:$G$712="T")+('EFETIVO 11.05.2026'!$G$2:$G$712="M")))} -> 13
B10: Funções distintas (somente ativos) | C10: {=SUMPRODUCT(--(C15:C88>0))} -> 69
B12: 2. Colaboradores por Função (Ativos / Desligados / Afastados)
B14: Função | C14: Ativos | D14: Desligados | E14: % do total ativos | F14: Afastados
B15: AJUDANTE DE BOMBEIRO PREDIAL | C15: {=SUMPRODUCT(ISNUMBER(SEARCH("743",'EFETIVO 11.05.2026'!$H$2:$H$712))*('EFETIVO 11.05.2026'!$G$2:$G$712="A")*('EFETIVO 11.05.2026'!$C$2:$C$712=B15))} -> 3 | D15: {=SUMPRODUCT(ISNUMBER(SEARCH("743",'EFETIVO 11.05.2026'!$H$2:$H$712))*('EFETIVO 11.05.2026'!$G$2:$G$712="D")*('EFETIVO 11.05.2026'!$C$2:$C$712=B15))} -> 1 | E15: =IFERROR(C15/$C$6,0) -> 0.0094043887 | F15: {=SUMPRODUCT(ISNUMBER(SEARCH("743",'EFETIVO 11.05.2026'!$H$2:$H$712))*(('EFETIVO 11.05.2026'!$G$2:$G$712="F")+('EFETIVO 11.05.2026'!$G$2:$G$712="P")+('EFETIVO 11.05.2026'!$G$2:$G$712="T")+('EFETIVO 11.05.2026'!$G$2:$G$712="M"))*('EFETIVO 11.05.2026'!$C$2:$C$712=$B15))} -> 0
B16: AJUDANTE DE CALDEIRARIA PREDIAL | C16: {=SUMPRODUCT(ISNUMBER(SEARCH("743",'EFETIVO 11.05.2026'!$H$2:$H$712))*('EFETIVO 11.05.2026'!$G$2:$G$712="A")*('EFETIVO 11.05.2026'!$C$2:$C$712=B16))} -> 1 | D16: {=SUMPRODUCT(ISNUMBER(SEARCH("743",'EFETIVO 11.05.2026'!$H$2:$H$712))*('EFETIVO 11.05.2026'!$G$2:$G$712="D")*('EFETIVO 11.05.2026'!$C$2:$C$712=B16))} -> 3 | E16: =IFERROR(C16/$C$6,0) -> 0.0031347962 | F16: {=SUMPRODUCT(ISNUMBER(SEARCH("743",'EFETIVO 11.05.2026'!$H$2:$H$712))*(('EFETIVO 11.05.2026'!$G$2:$G$712="F")+('EFETIVO 11.05.2026'!$G$2:$G$712="P")+('EFETIVO 11.05.2026'!$G$2:$G$712="T")+('EFETIVO 11.05.2026'!$G$2:$G$712="M"))*('EFETIVO 11.05.2026'!$C$2:$C$712=$B16))} -> 0
B17: AJUDANTE DE CARPINTEIRO | C17: {=SUMPRODUCT(ISNUMBER(SEARCH("743",'EFETIVO 11.05.2026'!$H$2:$H$712))*('EFETIVO 11.05.2026'!$G$2:$G$712="A")*('EFETIVO 11.05.2026'!$C$2:$C$712=B17))} -> 2 | D17: {=SUMPRODUCT(ISNUMBER(SEARCH("743",'EFETIVO 11.05.2026'!$H$2:$H$712))*('EFETIVO 11.05.2026'!$G$2:$G$712="D")*('EFETIVO 11.05.2026'!$C$2:$C$712=B17))} -> 1 | E17: =IFERROR(C17/$C$6,0) -> 0.0062695925 | F17: {=SUMPRODUCT(ISNUMBER(SEARCH("743",'EFETIVO 11.05.2026'!$H$2:$H$712))*(('EFETIVO 11.05.2026'!$G$2:$G$712="F")+('EFETIVO 11.05.2026'!$G$2:$G$712="P")+('EFETIVO 11.05.2026'!$G$2:$G$712="T")+('EFETIVO 11.05.2026'!$G$2:$G$712="M"))*('EFETIVO 11.05.2026'!$C$2:$C$712=$B17))} -> 0
B18: AJUDANTE DE ELETRICA PREDIAL | C18: {=SUMPRODUCT(ISNUMBER(SEARCH("743",'EFETIVO 11.05.2026'!$H$2:$H$712))*('EFETIVO 11.05.2026'!$G$2:$G$712="A")*('EFETIVO 11.05.2026'!$C$2:$C$712=B18))} -> 8 | D18: {=SUMPRODUCT(ISNUMBER(SEARCH("743",'EFETIVO 11.05.2026'!$H$2:$H$712))*('EFETIVO 11.05.2026'!$G$2:$G$712="D")*('EFETIVO 11.05.2026'!$C$2:$C$712=B18))} -> 3 | E18: =IFERROR(C18/$C$6,0) -> 0.02507837 | F18: {=SUMPRODUCT(ISNUMBER(SEARCH("743",'EFETIVO 11.05.2026'!$H$2:$H$712))*(('EFETIVO 11.05.2026'!$G$2:$G$712="F")+('EFETIVO 11.05.2026'!$G$2:$G$712="P")+('EFETIVO 11.05.2026'!$G$2:$G$712="T")+('EFETIVO 11.05.2026'!$G$2:$G$712="M"))*('EFETIVO 11.05.2026'!$C$2:$C$712=$B18))} -> 0
B19: AJUDANTE DE ELETROMECANICA PREDIAL | C19: {=SUMPRODUCT(ISNUMBER(SEARCH("743",'EFETIVO 11.05.2026'!$H$2:$H$712))*('EFETIVO 11.05.2026'!$G$2:$G$712="A")*('EFETIVO 11.05.2026'!$C$2:$C$712=B19))} -> 0 | D19: {=SUMPRODUCT(ISNUMBER(SEARCH("743",'EFETIVO 11.05.2026'!$H$2:$H$712))*('EFETIVO 11.05.2026'!$G$2:$G$712="D")*('EFETIVO 11.05.2026'!$C$2:$C$712=B19))} -> 1 | E19: =IFERROR(C19/$C$6,0) -> 0 | F19: {=SUMPRODUCT(ISNUMBER(SEARCH("743",'EFETIVO 11.05.2026'!$H$2:$H$712))*(('EFETIVO 11.05.2026'!$G$2:$G$712="F")+('EFETIVO 11.05.2026'!$G$2:$G$712="P")+('EFETIVO 11.05.2026'!$G$2:$G$712="T")+('EFETIVO 11.05.2026'!$G$2:$G$712="M"))*('EFETIVO 11.05.2026'!$C$2:$C$712=$B19))} -> 0
B20: AJUDANTE DE MANUTENCAO ELETRICA | C20: {=SUMPRODUCT(ISNUMBER(SEARCH("743",'EFETIVO 11.05.2026'!$H$2:$H$712))*('EFETIVO 11.05.2026'!$G$2:$G$712="A")*('EFETIVO 11.05.2026'!$C$2:$C$712=B20))} -> 4 | D20: {=SUMPRODUCT(ISNUMBER(SEARCH("743",'EFETIVO 11.05.2026'!$H$2:$H$712))*('EFETIVO 11.05.2026'!$G$2:$G$712="D")*('EFETIVO 11.05.2026'!$C$2:$C$712=B20))} -> 0 | E20: =IFERROR(C20/$C$6,0) -> 0.012539185 | F20: {=SUMPRODUCT(ISNUMBER(SEARCH("743",'EFETIVO 11.05.2026'!$H$2:$H$712))*(('EFETIVO 11.05.2026'!$G$2:$G$712="F")+('EFETIVO 11.05.2026'!$G$2:$G$712="P")+('EFETIVO 11.05.2026'!$G$2:$G$712="T")+('EFETIVO 11.05.2026'!$G$2:$G$712="M"))*('EFETIVO 11.05.2026'!$C$2:$C$712=$B20))} -> 0
B21: AJUDANTE DE MARCENEIRO | C21: {=SUMPRODUCT(ISNUMBER(SEARCH("743",'EFETIVO 11.05.2026'!$H$2:$H$712))*('EFETIVO 11.05.2026'!$G$2:$G$712="A")*('EFETIVO 11.05.2026'!$C$2:$C$712=B21))} -> 2 | D21: {=SUMPRODUCT(ISNUMBER(SEARCH("743",'EFETIVO 11.05.2026'!$H$2:$H$712))*('EFETIVO 11.05.2026'!$G$2:$G$712="D")*('EFETIVO 11.05.2026'!$C$2:$C$712=B21))} -> 0 | E21: =IFERROR(C21/$C$6,0) -> 0.0062695925 | F21: {=SUMPRODUCT(ISNUMBER(SEARCH("743",'EFETIVO 11.05.2026'!$H$2:$H$712))*(('EFETIVO 11.05.2026'!$G$2:$G$712="F")+('EFETIVO 11.05.2026'!$G$2:$G$712="P")+('EFETIVO 11.05.2026'!$G$2:$G$712="T")+('EFETIVO 11.05.2026'!$G$2:$G$712="M"))*('EFETIVO 11.05.2026'!$C$2:$C$712=$B21))} -> 0
B22: AJUDANTE DE MECANICA PREDIAL | C22: {=SUMPRODUCT(ISNUMBER(SEARCH("743",'EFETIVO 11.05.2026'!$H$2:$H$712))*('EFETIVO 11.05.2026'!$G$2:$G$712="A")*('EFETIVO 11.05.2026'!$C$2:$C$712=B22))} -> 3 | D22: {=SUMPRODUCT(ISNUMBER(SEARCH("743",'EFETIVO 11.05.2026'!$H$2:$H$712))*('EFETIVO 11.05.2026'!$G$2:$G$712="D")*('EFETIVO 11.05.2026'!$C$2:$C$712=B22))} -> 1 | E22: =IFERROR(C22/$C$6,0) -> 0.0094043887 | F22: {=SUMPRODUCT(ISNUMBER(SEARCH("743",'EFETIVO 11.05.2026'!$H$2:$H$712))*(('EFETIVO 11.05.2026'!$G$2:$G$712="F")+('EFETIVO 11.05.2026'!$G$2:$G$712="P")+('EFETIVO 11.05.2026'!$G$2:$G$712="T")+('EFETIVO 11.05.2026'!$G$2:$G$712="M"))*('EFETIVO 11.05.2026'!$C$2:$C$712=$B22))} -> 0
B23: AJUDANTE DE PEDREIRO | C23: {=SUMPRODUCT(ISNUMBER(SEARCH("743",'EFETIVO 11.05.2026'!$H$2:$H$712))*('EFETIVO 11.05.2026'!$G$2:$G$712="A")*('EFETIVO 11.05.2026'!$C$2:$C$712=B23))} -> 8 | D23: {=SUMPRODUCT(ISNUMBER(SEARCH("743",'EFETIVO 11.05.2026'!$H$2:$H$712))*('EFETIVO 11.05.2026'!$G$2:$G$712="D")*('EFETIVO 11.05.2026'!$C$2:$C$712=B23))} -> 2 | E23: =IFERROR(C23/$C$6,0) -> 0.02507837 | F23: {=SUMPRODUCT(ISNUMBER(SEARCH("743",'EFETIVO 11.05.2026'!$H$2:$H$712))*(('EFETIVO 11.05.2026'!$G$2:$G$712="F")+('EFETIVO 11.05.2026'!$G$2:$G$712="P")+('EFETIVO 11.05.2026'!$G$2:$G$712="T")+('EFETIVO 11.05.2026'!$G$2:$G$712="M"))*('EFETIVO 11.05.2026'!$C$2:$C$712=$B23))} -> 2
B24: AJUDANTE DE PINTURA | C24: {=SUMPRODUCT(ISNUMBER(SEARCH("743",'EFETIVO 11.05.2026'!$H$2:$H$712))*('EFETIVO 11.05.2026'!$G$2:$G$712="A")*('EFETIVO 11.05.2026'!$C$2:$C$712=B24))} -> 5 | D24: {=SUMPRODUCT(ISNUMBER(SEARCH("743",'EFETIVO 11.05.2026'!$H$2:$H$712))*('EFETIVO 11.05.2026'!$G$2:$G$712="D")*('EFETIVO 11.05.2026'!$C$2:$C$712=B24))} -> 5 | E24: =IFERROR(C24/$C$6,0) -> 0.015673981 | F24: {=SUMPRODUCT(ISNUMBER(SEARCH("743",'EFETIVO 11.05.2026'!$H$2:$H$712))*(('EFETIVO 11.05.2026'!$G$2:$G$712="F")+('EFETIVO 11.05.2026'!$G$2:$G$712="P")+('EFETIVO 11.05.2026'!$G$2:$G$712="T")+('EFETIVO 11.05.2026'!$G$2:$G$712="M"))*('EFETIVO 11.05.2026'!$C$2:$C$712=$B24))} -> 0
B25: AJUDANTE DE PINTURA INDUSTRIAL | C25: {=SUMPRODUCT(ISNUMBER(SEARCH("743",'EFETIVO 11.05.2026'!$H$2:$H$712))*('EFETIVO 11.05.2026'!$G$2:$G$712="A")*('EFETIVO 11.05.2026'!$C$2:$C$712=B25))} -> 1 | D25: {=SUMPRODUCT(ISNUMBER(SEARCH("743",'EFETIVO 11.05.2026'!$H$2:$H$712))*('EFETIVO 11.05.2026'!$G$2:$G$712="D")*('EFETIVO 11.05.2026'!$C$2:$C$712=B25))} -> 2 | E25: =IFERROR(C25/$C$6,0) -> 0.0031347962 | F25: {=SUMPRODUCT(ISNUMBER(SEARCH("743",'EFETIVO 11.05.2026'!$H$2:$H$712))*(('EFETIVO 11.05.2026'!$G$2:$G$712="F")+('EFETIVO 11.05.2026'!$G$2:$G$712="P")+('EFETIVO 11.05.2026'!$G$2:$G$712="T")+('EFETIVO 11.05.2026'!$G$2:$G$712="M"))*('EFETIVO 11.05.2026'!$C$2:$C$712=$B25))} -> 1
B26: AJUDANTE DE REFRIGERACAO | C26: {=SUMPRODUCT(ISNUMBER(SEARCH("743",'EFETIVO 11.05.2026'!$H$2:$H$712))*('EFETIVO 11.05.2026'!$G$2:$G$712="A")*('EFETIVO 11.05.2026'!$C$2:$C$712=B26))} -> 1 | D26: {=SUMPRODUCT(ISNUMBER(SEARCH("743",'EFETIVO 11.05.2026'!$H$2:$H$712))*('EFETIVO 11.05.2026'!$G$2:$G$712="D")*('EFETIVO 11.05.2026'!$C$2:$C$712=B26))} -> 0 | E26: =IFERROR(C26/$C$6,0) -> 0.0031347962 | F26: {=SUMPRODUCT(ISNUMBER(SEARCH("743",'EFETIVO 11.05.2026'!$H$2:$H$712))*(('EFETIVO 11.05.2026'!$G$2:$G$712="F")+('EFETIVO 11.05.2026'!$G$2:$G$712="P")+('EFETIVO 11.05.2026'!$G$2:$G$712="T")+('EFETIVO 11.05.2026'!$G$2:$G$712="M"))*('EFETIVO 11.05.2026'!$C$2:$C$712=$B26))} -> 0
... B88: TECNICO EM AUTOMACAO | C88: {=SUMPRODUCT(ISNUMBER(SEARCH("743",'EFETIVO 11.05.2026'!$H$2:$H$712))*('EFETIVO 11.05.2026'!$G$2:$G$712="A")*('EFETIVO 11.05.2026'!$C$2:$C$712=B88))} -> 1 | D88: {=SUMPRODUCT(ISNUMBER(SEARCH("743",'EFETIVO 11.05.2026'!$H$2:$H$712))*('EFETIVO 11.05.2026'!$G$2:$G$712="D")*('EFETIVO 11.05.2026'!$C$2:$C$712=B88))} -> 0 | E88: =IFERROR(C88/$C$6,0) -> 0.0031347962 | F88: {=SUMPRODUCT(ISNUMBER(SEARCH("743",'EFETIVO 11.05.2026'!$H$2:$H$712))*(('EFETIVO 11.05.2026'!$G$2:$G$712="F")+('EFETIVO 11.05.2026'!$G$2:$G$712="P")+('EFETIVO 11.05.2026'!$G$2:$G$712="T")+('EFETIVO 11.05.2026'!$G$2:$G$712="M"))*('EFETIVO 11.05.2026'!$C$2:$C$712=$B88))} -> 0
B89: TOTAL | C89: =C6 -> 319 | D89: =C7 -> 101 | E89: =IFERROR(C89/$C$6,0) -> 1 | F89: =SUM(F15:F88) -> 12
B90: 3. Colaboradores por Carteira
B91: Carteira | C91: Ativos | D91: Desligados | E91: Afastados | F91: % total
B92: CIVIL | C92: {=SUMPRODUCT(ISNUMBER(SEARCH("743",'EFETIVO 11.05.2026'!H$2:H$1919))*('EFETIVO 11.05.2026'!G$2:G$1919="A")*('EFETIVO 11.05.2026'!J$2:J$1919=B92))} -> 91 | D92: {=SUMPRODUCT(ISNUMBER(SEARCH("743",'EFETIVO 11.05.2026'!H$2:H$1919))*('EFETIVO 11.05.2026'!G$2:G$1919="D")*('EFETIVO 11.05.2026'!J$2:J$1919=B92))} -> 0 | E92: {=SUMPRODUCT(ISNUMBER(SEARCH("743",'EFETIVO 11.05.2026'!H$2:H$1919))*((('EFETIVO 11.05.2026'!G$2:G$1919="F")+('EFETIVO 11.05.2026'!G$2:G$1919="P")+('EFETIVO 11.05.2026'!G$2:G$1919="T")+('EFETIVO 11.05.2026'!G$2:G$1919="M"))>0)*('EFETIVO 11.05.2026'!J$2:J$1919=B92))} -> 0 | F92: =IFERROR(C92/$C$6,0) -> 0.28526646
B93: AREAS VERDES | C93: {=SUMPRODUCT(ISNUMBER(SEARCH("743",'EFETIVO 11.05.2026'!H$2:H$1919))*('EFETIVO 11.05.2026'!G$2:G$1919="A")*('EFETIVO 11.05.2026'!J$2:J$1919=B93))} -> 81 | D93: {=SUMPRODUCT(ISNUMBER(SEARCH("743",'EFETIVO 11.05.2026'!H$2:H$1919))*('EFETIVO 11.05.2026'!G$2:G$1919="D")*('EFETIVO 11.05.2026'!J$2:J$1919=B93))} -> 0 | E93: {=SUMPRODUCT(ISNUMBER(SEARCH("743",'EFETIVO 11.05.2026'!H$2:H$1919))*((('EFETIVO 11.05.2026'!G$2:G$1919="F")+('EFETIVO 11.05.2026'!G$2:G$1919="P")+('EFETIVO 11.05.2026'!G$2:G$1919="T")+('EFETIVO 11.05.2026'!G$2:G$1919="M"))>0)*('EFETIVO 11.05.2026'!J$2:J$1919=B93))} -> 1 | F93: =IFERROR(C93/$C$6,0) -> 0.2539185
B94: CONSERVACAO E LIMPEZA | C94: {=SUMPRODUCT(ISNUMBER(SEARCH("743",'EFETIVO 11.05.2026'!H$2:H$1919))*('EFETIVO 11.05.2026'!G$2:G$1919="A")*('EFETIVO 11.05.2026'!J$2:J$1919=B94))} -> 55 | D94: {=SUMPRODUCT(ISNUMBER(SEARCH("743",'EFETIVO 11.05.2026'!H$2:H$1919))*('EFETIVO 11.05.2026'!G$2:G$1919="D")*('EFETIVO 11.05.2026'!J$2:J$1919=B94))} -> 0 | E94: {=SUMPRODUCT(ISNUMBER(SEARCH("743",'EFETIVO 11.05.2026'!H$2:H$1919))*((('EFETIVO 11.05.2026'!G$2:G$1919="F")+('EFETIVO 11.05.2026'!G$2:G$1919="P")+('EFETIVO 11.05.2026'!G$2:G$1919="T")+('EFETIVO 11.05.2026'!G$2:G$1919="M"))>0)*('EFETIVO 11.05.2026'!J$2:J$1919=B94))} -> 0 | F94: =IFERROR(C94/$C$6,0) -> 0.17241379
B95: ELETRICA | C95: {=SUMPRODUCT(ISNUMBER(SEARCH("743",'EFETIVO 11.05.2026'!H$2:H$1919))*('EFETIVO 11.05.2026'!G$2:G$1919="A")*('EFETIVO 11.05.2026'!J$2:J$1919=B95))} -> 18 | D95: {=SUMPRODUCT(ISNUMBER(SEARCH("743",'EFETIVO 11.05.2026'!H$2:H$1919))*('EFETIVO 11.05.2026'!G$2:G$1919="D")*('EFETIVO 11.05.2026'!J$2:J$1919=B95))} -> 0 | E95: {=SUMPRODUCT(ISNUMBER(SEARCH("743",'EFETIVO 11.05.2026'!H$2:H$1919))*((('EFETIVO 11.05.2026'!G$2:G$1919="F")+('EFETIVO 11.05.2026'!G$2:G$1919="P")+('EFETIVO 11.05.2026'!G$2:G$1919="T")+('EFETIVO 11.05.2026'!G$2:G$1919="M"))>0)*('EFETIVO 11.05.2026'!J$2:J$1919=B95))} -> 0 | F95: =IFERROR(C95/$C$6,0) -> 0.056426332
B96: OPERACAO | C96: {=SUMPRODUCT(ISNUMBER(SEARCH("743",'EFETIVO 11.05.2026'!H$2:H$1919))*('EFETIVO 11.05.2026'!G$2:G$1919="A")*('EFETIVO 11.05.2026'!J$2:J$1919=B96))} -> 11 | D96: {=SUMPRODUCT(ISNUMBER(SEARCH("743",'EFETIVO 11.05.2026'!H$2:H$1919))*('EFETIVO 11.05.2026'!G$2:G$1919="D")*('EFETIVO 11.05.2026'!J$2:J$1919=B96))} -> 0 | E96: {=SUMPRODUCT(ISNUMBER(SEARCH("743",'EFETIVO 11.05.2026'!H$2:H$1919))*((('EFETIVO 11.05.2026'!G$2:G$1919="F")+('EFETIVO 11.05.2026'!G$2:G$1919="P")+('EFETIVO 11.05.2026'!G$2:G$1919="T")+('EFETIVO 11.05.2026'!G$2:G$1919="M"))>0)*('EFETIVO 11.05.2026'!J$2:J$1919=B96))} -> 0 | F96: =IFERROR(C96/$C$6,0) -> 0.034482759
B97: SMS | C97: {=SUMPRODUCT(ISNUMBER(SEARCH("743",'EFETIVO 11.05.2026'!H$2:H$1919))*('EFETIVO 11.05.2026'!G$2:G$1919="A")*('EFETIVO 11.05.2026'!J$2:J$1919=B97))} -> 9 | D97: {=SUMPRODUCT(ISNUMBER(SEARCH("743",'EFETIVO 11.05.2026'!H$2:H$1919))*('EFETIVO 11.05.2026'!G$2:G$1919="D")*('EFETIVO 11.05.2026'!J$2:J$1919=B97))} -> 0 | E97: {=SUMPRODUCT(ISNUMBER(SEARCH("743",'EFETIVO 11.05.2026'!H$2:H$1919))*((('EFETIVO 11.05.2026'!G$2:G$1919="F")+('EFETIVO 11.05.2026'!G$2:G$1919="P")+('EFETIVO 11.05.2026'!G$2:G$1919="T")+('EFETIVO 11.05.2026'!G$2:G$1919="M"))>0)*('EFETIVO 11.05.2026'!J$2:J$1919=B97))} -> 1 | F97: =IFERROR(C97/$C$6,0) -> 0.028213166
B98: REFRIGERACAO | C98: {=SUMPRODUCT(ISNUMBER(SEARCH("743",'EFETIVO 11.05.2026'!H$2:H$1919))*('EFETIVO 11.05.2026'!G$2:G$1919="A")*('EFETIVO 11.05.2026'!J$2:J$1919=B98))} -> 7 | D98: {=SUMPRODUCT(ISNUMBER(SEARCH("743",'EFETIVO 11.05.2026'!H$2:H$1919))*('EFETIVO 11.05.2026'!G$2:G$1919="D")*('EFETIVO 11.05.2026'!J$2:J$1919=B98))} -> 0 | E98: {=SUMPRODUCT(ISNUMBER(SEARCH("743",'EFETIVO 11.05.2026'!H$2:H$1919))*((('EFETIVO 11.05.2026'!G$2:G$1919="F")+('EFETIVO 11.05.2026'!G$2:G$1919="P")+('EFETIVO 11.05.2026'!G$2:G$1919="T")+('EFETIVO 11.05.2026'!G$2:G$1919="M"))>0)*('EFETIVO 11.05.2026'!J$2:J$1919=B98))} -> 1 | F98: =IFERROR(C98/$C$6,0) -> 0.021943574
B99: PLANEJAMENTO | C99: {=SUMPRODUCT(ISNUMBER(SEARCH("743",'EFETIVO 11.05.2026'!H$2:H$1919))*('EFETIVO 11.05.2026'!G$2:G$1919="A")*('EFETIVO 11.05.2026'!J$2:J$1919=B99))} -> 9 | D99: {=SUMPRODUCT(ISNUMBER(SEARCH("743",'EFETIVO 11.05.2026'!H$2:H$1919))*('EFETIVO 11.05.2026'!G$2:G$1919="D")*('EFETIVO 11.05.2026'!J$2:J$1919=B99))} -> 0 | E99: {=SUMPRODUCT(ISNUMBER(SEARCH("743",'EFETIVO 11.05.2026'!H$2:H$1919))*((('EFETIVO 11.05.2026'!G$2:G$1919="F")+('EFETIVO 11.05.2026'!G$2:G$1919="P")+('EFETIVO 11.05.2026'!G$2:G$1919="T")+('EFETIVO 11.05.2026'!G$2:G$1919="M"))>0)*('EFETIVO 11.05.2026'!J$2:J$1919=B99))} -> 0 | F99: =IFERROR(C99/$C$6,0) -> 0.028213166
B100: LOGISTICA | C100: {=SUMPRODUCT(ISNUMBER(SEARCH("743",'EFETIVO 11.05.2026'!H$2:H$1919))*('EFETIVO 11.05.2026'!G$2:G$1919="A")*('EFETIVO 11.05.2026'!J$2:J$1919=B100))} -> 7 | D100: {=SUMPRODUCT(ISNUMBER(SEARCH("743",'EFETIVO 11.05.2026'!H$2:H$1919))*('EFETIVO 11.05.2026'!G$2:G$1919="D")*('EFETIVO 11.05.2026'!J$2:J$1919=B100))} -> 0 | E100: {=SUMPRODUCT(ISNUMBER(SEARCH("743",'EFETIVO 11.05.2026'!H$2:H$1919))*((('EFETIVO 11.05.2026'!G$2:G$1919="F")+('EFETIVO 11.05.2026'!G$2:G$1919="P")+('EFETIVO 11.05.2026'!G$2:G$1919="T")+('EFETIVO 11.05.2026'!G$2:G$1919="M"))>0)*('EFETIVO 11.05.2026'!J$2:J$1919=B100))} -> 0 | F100: =IFERROR(C100/$C$6,0) -> 0.021943574
B101: ELETROMECANICA | C101: {=SUMPRODUCT(ISNUMBER(SEARCH("743",'EFETIVO 11.05.2026'!H$2:H$1919))*('EFETIVO 11.05.2026'!G$2:G$1919="A")*('EFETIVO 11.05.2026'!J$2:J$1919=B101))} -> 7 | D101: {=SUMPRODUCT(ISNUMBER(SEARCH("743",'EFETIVO 11.05.2026'!H$2:H$1919))*('EFETIVO 11.05.2026'!G$2:G$1919="D")*('EFETIVO 11.05.2026'!J$2:J$1919=B101))} -> 0 | E101: {=SUMPRODUCT(ISNUMBER(SEARCH("743",'EFETIVO 11.05.2026'!H$2:H$1919))*((('EFETIVO 11.05.2026'!G$2:G$1919="F")+('EFETIVO 11.05.2026'!G$2:G$1919="P")+('EFETIVO 11.05.2026'!G$2:G$1919="T")+('EFETIVO 11.05.2026'!G$2:G$1919="M"))>0)*('EFETIVO 11.05.2026'!J$2:J$1919=B101))} -> 0 | F101: =IFERROR(C101/$C$6,0) -> 0.021943574
B102: COMPRAS | C102: {=SUMPRODUCT(ISNUMBER(SEARCH("743",'EFETIVO 11.05.2026'!H$2:H$1919))*('EFETIVO 11.05.2026'!G$2:G$1919="A")*('EFETIVO 11.05.2026'!J$2:J$1919=B102))} -> 5 | D102: {=SUMPRODUCT(ISNUMBER(SEARCH("743",'EFETIVO 11.05.2026'!H$2:H$1919))*('EFETIVO 11.05.2026'!G$2:G$1919="D")*('EFETIVO 11.05.2026'!J$2:J$1919=B102))} -> 0 | E102: {=SUMPRODUCT(ISNUMBER(SEARCH("743",'EFETIVO 11.05.2026'!H$2:H$1919))*((('EFETIVO 11.05.2026'!G$2:G$1919="F")+('EFETIVO 11.05.2026'!G$2:G$1919="P")+('EFETIVO 11.05.2026'!G$2:G$1919="T")+('EFETIVO 11.05.2026'!G$2:G$1919="M"))>0)*('EFETIVO 11.05.2026'!J$2:J$1919=B102))} -> 1 | F102: =IFERROR(C102/$C$6,0) -> 0.015673981
B103: SUPRIMENTOS | C103: {=SUMPRODUCT(ISNUMBER(SEARCH("743",'EFETIVO 11.05.2026'!H$2:H$1919))*('EFETIVO 11.05.2026'!G$2:G$1919="A")*('EFETIVO 11.05.2026'!J$2:J$1919=B103))} -> 3 | D103: {=SUMPRODUCT(ISNUMBER(SEARCH("743",'EFETIVO 11.05.2026'!H$2:H$1919))*('EFETIVO 11.05.2026'!G$2:G$1919="D")*('EFETIVO 11.05.2026'!J$2:J$1919=B103))} -> 0 | E103: {=SUMPRODUCT(ISNUMBER(SEARCH("743",'EFETIVO 11.05.2026'!H$2:H$1919))*((('EFETIVO 11.05.2026'!G$2:G$1919="F")+('EFETIVO 11.05.2026'!G$2:G$1919="P")+('EFETIVO 11.05.2026'!G$2:G$1919="T")+('EFETIVO 11.05.2026'!G$2:G$1919="M"))>0)*('EFETIVO 11.05.2026'!J$2:J$1919=B103))} -> 0 | F103: =IFERROR(C103/$C$6,0) -> 0.0094043887
... B109: ? | C109: {=SUMPRODUCT(ISNUMBER(SEARCH("743",'EFETIVO 11.05.2026'!H$2:H$1919))*('EFETIVO 11.05.2026'!G$2:G$1919="A")*('EFETIVO 11.05.2026'!J$2:J$1919=B109))} -> 9 | D109: {=SUMPRODUCT(ISNUMBER(SEARCH("743",'EFETIVO 11.05.2026'!H$2:H$1919))*('EFETIVO 11.05.2026'!G$2:G$1919="D")*('EFETIVO 11.05.2026'!J$2:J$1919=B109))} -> 0 | E109: {=SUMPRODUCT(ISNUMBER(SEARCH("743",'EFETIVO 11.05.2026'!H$2:H$1919))*((('EFETIVO 11.05.2026'!G$2:G$1919="F")+('EFETIVO 11.05.2026'!G$2:G$1919="P")+('EFETIVO 11.05.2026'!G$2:G$1919="T")+('EFETIVO 11.05.2026'!G$2:G$1919="M"))>0)*('EFETIVO 11.05.2026'!J$2:J$1919=B109))} -> 0 | F109: =IFERROR(C109/$C$6,0) -> 0.028213166
B110: TOTAL | C110: =SUM(C92:C109) -> 319 | D110: =SUM(D92:D109) -> 0 | E110: =SUM(E92:E109) -> 4 | F110: =SUM(F92:F109) -> 1
B113: 3.1 Carteira × Base (Ativos)
B114: Carteira | C114: CABIUNAS | D114: BARRA DO FURADO | E114: FAZENDA SEVERINA | F114: Total
B115: CIVIL | C115: {=SUMPRODUCT(ISNUMBER(SEARCH("743",'EFETIVO 11.05.2026'!H$2:H$1919))*('EFETIVO 11.05.2026'!G$2:G$1919="A")*('EFETIVO 11.05.2026'!J$2:J$1919=B115)*('EFETIVO 11.05.2026'!I$2:I$1919="CABIUNAS"))} -> 86 | D115: {=SUMPRODUCT(ISNUMBER(SEARCH("743",'EFETIVO 11.05.2026'!H$2:H$1919))*('EFETIVO 11.05.2026'!G$2:G$1919="A")*('EFETIVO 11.05.2026'!J$2:J$1919=B115)*('EFETIVO 11.05.2026'!I$2:I$1919="BARRA DO FURADO"))} -> 5 | E115: {=SUMPRODUCT(ISNUMBER(SEARCH("743",'EFETIVO 11.05.2026'!H$2:H$1919))*('EFETIVO 11.05.2026'!G$2:G$1919="A")*('EFETIVO 11.05.2026'!J$2:J$1919=B115)*('EFETIVO 11.05.2026'!I$2:I$1919="FAZENDA SEVERINA"))} -> 0 | F115: =SUM(C115:E115) -> 91
B116: AREAS VERDES | C116: {=SUMPRODUCT(ISNUMBER(SEARCH("743",'EFETIVO 11.05.2026'!H$2:H$1919))*('EFETIVO 11.05.2026'!G$2:G$1919="A")*('EFETIVO 11.05.2026'!J$2:J$1919=B116)*('EFETIVO 11.05.2026'!I$2:I$1919="CABIUNAS"))} -> 77 | D116: {=SUMPRODUCT(ISNUMBER(SEARCH("743",'EFETIVO 11.05.2026'!H$2:H$1919))*('EFETIVO 11.05.2026'!G$2:G$1919="A")*('EFETIVO 11.05.2026'!J$2:J$1919=B116)*('EFETIVO 11.05.2026'!I$2:I$1919="BARRA DO FURADO"))} -> 4 | E116: {=SUMPRODUCT(ISNUMBER(SEARCH("743",'EFETIVO 11.05.2026'!H$2:H$1919))*('EFETIVO 11.05.2026'!G$2:G$1919="A")*('EFETIVO 11.05.2026'!J$2:J$1919=B116)*('EFETIVO 11.05.2026'!I$2:I$1919="FAZENDA SEVERINA"))} -> 0 | F116: =SUM(C116:E116) -> 81
B117: CONSERVACAO E LIMPEZA | C117: {=SUMPRODUCT(ISNUMBER(SEARCH("743",'EFETIVO 11.05.2026'!H$2:H$1919))*('EFETIVO 11.05.2026'!G$2:G$1919="A")*('EFETIVO 11.05.2026'!J$2:J$1919=B117)*('EFETIVO 11.05.2026'!I$2:I$1919="CABIUNAS"))} -> 50 | D117: {=SUMPRODUCT(ISNUMBER(SEARCH("743",'EFETIVO 11.05.2026'!H$2:H$1919))*('EFETIVO 11.05.2026'!G$2:G$1919="A")*('EFETIVO 11.05.2026'!J$2:J$1919=B117)*('EFETIVO 11.05.2026'!I$2:I$1919="BARRA DO FURADO"))} -> 4 | E117: {=SUMPRODUCT(ISNUMBER(SEARCH("743",'EFETIVO 11.05.2026'!H$2:H$1919))*('EFETIVO 11.05.2026'!G$2:G$1919="A")*('EFETIVO 11.05.2026'!J$2:J$1919=B117)*('EFETIVO 11.05.2026'!I$2:I$1919="FAZENDA SEVERINA"))} -> 1 | F117: =SUM(C117:E117) -> 55
B118: ELETRICA | C118: {=SUMPRODUCT(ISNUMBER(SEARCH("743",'EFETIVO 11.05.2026'!H$2:H$1919))*('EFETIVO 11.05.2026'!G$2:G$1919="A")*('EFETIVO 11.05.2026'!J$2:J$1919=B118)*('EFETIVO 11.05.2026'!I$2:I$1919="CABIUNAS"))} -> 16 | D118: {=SUMPRODUCT(ISNUMBER(SEARCH("743",'EFETIVO 11.05.2026'!H$2:H$1919))*('EFETIVO 11.05.2026'!G$2:G$1919="A")*('EFETIVO 11.05.2026'!J$2:J$1919=B118)*('EFETIVO 11.05.2026'!I$2:I$1919="BARRA DO FURADO"))} -> 2 | E118: {=SUMPRODUCT(ISNUMBER(SEARCH("743",'EFETIVO 11.05.2026'!H$2:H$1919))*('EFETIVO 11.05.2026'!G$2:G$1919="A")*('EFETIVO 11.05.2026'!J$2:J$1919=B118)*('EFETIVO 11.05.2026'!I$2:I$1919="FAZENDA SEVERINA"))} -> 0 | F118: =SUM(C118:E118) -> 18
B119: OPERACAO | C119: {=SUMPRODUCT(ISNUMBER(SEARCH("743",'EFETIVO 11.05.2026'!H$2:H$1919))*('EFETIVO 11.05.2026'!G$2:G$1919="A")*('EFETIVO 11.05.2026'!J$2:J$1919=B119)*('EFETIVO 11.05.2026'!I$2:I$1919="CABIUNAS"))} -> 11 | D119: {=SUMPRODUCT(ISNUMBER(SEARCH("743",'EFETIVO 11.05.2026'!H$2:H$1919))*('EFETIVO 11.05.2026'!G$2:G$1919="A")*('EFETIVO 11.05.2026'!J$2:J$1919=B119)*('EFETIVO 11.05.2026'!I$2:I$1919="BARRA DO FURADO"))} -> 0 | E119: {=SUMPRODUCT(ISNUMBER(SEARCH("743",'EFETIVO 11.05.2026'!H$2:H$1919))*('EFETIVO 11.05.2026'!G$2:G$1919="A")*('EFETIVO 11.05.2026'!J$2:J$1919=B119)*('EFETIVO 11.05.2026'!I$2:I$1919="FAZENDA SEVERINA"))} -> 0 | F119: =SUM(C119:E119) -> 11
B120: SMS | C120: {=SUMPRODUCT(ISNUMBER(SEARCH("743",'EFETIVO 11.05.2026'!H$2:H$1919))*('EFETIVO 11.05.2026'!G$2:G$1919="A")*('EFETIVO 11.05.2026'!J$2:J$1919=B120)*('EFETIVO 11.05.2026'!I$2:I$1919="CABIUNAS"))} -> 9 | D120: {=SUMPRODUCT(ISNUMBER(SEARCH("743",'EFETIVO 11.05.2026'!H$2:H$1919))*('EFETIVO 11.05.2026'!G$2:G$1919="A")*('EFETIVO 11.05.2026'!J$2:J$1919=B120)*('EFETIVO 11.05.2026'!I$2:I$1919="BARRA DO FURADO"))} -> 0 | E120: {=SUMPRODUCT(ISNUMBER(SEARCH("743",'EFETIVO 11.05.2026'!H$2:H$1919))*('EFETIVO 11.05.2026'!G$2:G$1919="A")*('EFETIVO 11.05.2026'!J$2:J$1919=B120)*('EFETIVO 11.05.2026'!I$2:I$1919="FAZENDA SEVERINA"))} -> 0 | F120: =SUM(C120:E120) -> 9
B121: REFRIGERACAO | C121: {=SUMPRODUCT(ISNUMBER(SEARCH("743",'EFETIVO 11.05.2026'!H$2:H$1919))*('EFETIVO 11.05.2026'!G$2:G$1919="A")*('EFETIVO 11.05.2026'!J$2:J$1919=B121)*('EFETIVO 11.05.2026'!I$2:I$1919="CABIUNAS"))} -> 7 | D121: {=SUMPRODUCT(ISNUMBER(SEARCH("743",'EFETIVO 11.05.2026'!H$2:H$1919))*('EFETIVO 11.05.2026'!G$2:G$1919="A")*('EFETIVO 11.05.2026'!J$2:J$1919=B121)*('EFETIVO 11.05.2026'!I$2:I$1919="BARRA DO FURADO"))} -> 0 | E121: {=SUMPRODUCT(ISNUMBER(SEARCH("743",'EFETIVO 11.05.2026'!H$2:H$1919))*('EFETIVO 11.05.2026'!G$2:G$1919="A")*('EFETIVO 11.05.2026'!J$2:J$1919=B121)*('EFETIVO 11.05.2026'!I$2:I$1919="FAZENDA SEVERINA"))} -> 0 | F121: =SUM(C121:E121) -> 7
B122: PLANEJAMENTO | C122: {=SUMPRODUCT(ISNUMBER(SEARCH("743",'EFETIVO 11.05.2026'!H$2:H$1919))*('EFETIVO 11.05.2026'!G$2:G$1919="A")*('EFETIVO 11.05.2026'!J$2:J$1919=B122)*('EFETIVO 11.05.2026'!I$2:I$1919="CABIUNAS"))} -> 9 | D122: {=SUMPRODUCT(ISNUMBER(SEARCH("743",'EFETIVO 11.05.2026'!H$2:H$1919))*('EFETIVO 11.05.2026'!G$2:G$1919="A")*('EFETIVO 11.05.2026'!J$2:J$1919=B122)*('EFETIVO 11.05.2026'!I$2:I$1919="BARRA DO FURADO"))} -> 0 | E122: {=SUMPRODUCT(ISNUMBER(SEARCH("743",'EFETIVO 11.05.2026'!H$2:H$1919))*('EFETIVO 11.05.2026'!G$2:G$1919="A")*('EFETIVO 11.05.2026'!J$2:J$1919=B122)*('EFETIVO 11.05.2026'!I$2:I$1919="FAZENDA SEVERINA"))} -> 0 | F122: =SUM(C122:E122) -> 9
B123: LOGISTICA | C123: {=SUMPRODUCT(ISNUMBER(SEARCH("743",'EFETIVO 11.05.2026'!H$2:H$1919))*('EFETIVO 11.05.2026'!G$2:G$1919="A")*('EFETIVO 11.05.2026'!J$2:J$1919=B123)*('EFETIVO 11.05.2026'!I$2:I$1919="CABIUNAS"))} -> 7 | D123: {=SUMPRODUCT(ISNUMBER(SEARCH("743",'EFETIVO 11.05.2026'!H$2:H$1919))*('EFETIVO 11.05.2026'!G$2:G$1919="A")*('EFETIVO 11.05.2026'!J$2:J$1919=B123)*('EFETIVO 11.05.2026'!I$2:I$1919="BARRA DO FURADO"))} -> 0 | E123: {=SUMPRODUCT(ISNUMBER(SEARCH("743",'EFETIVO 11.05.2026'!H$2:H$1919))*('EFETIVO 11.05.2026'!G$2:G$1919="A")*('EFETIVO 11.05.2026'!J$2:J$1919=B123)*('EFETIVO 11.05.2026'!I$2:I$1919="FAZENDA SEVERINA"))} -> 0 | F123: =SUM(C123:E123) -> 7
B124: ELETROMECANICA | C124: {=SUMPRODUCT(ISNUMBER(SEARCH("743",'EFETIVO 11.05.2026'!H$2:H$1919))*('EFETIVO 11.05.2026'!G$2:G$1919="A")*('EFETIVO 11.05.2026'!J$2:J$1919=B124)*('EFETIVO 11.05.2026'!I$2:I$1919="CABIUNAS"))} -> 7 | D124: {=SUMPRODUCT(ISNUMBER(SEARCH("743",'EFETIVO 11.05.2026'!H$2:H$1919))*('EFETIVO 11.05.2026'!G$2:G$1919="A")*('EFETIVO 11.05.2026'!J$2:J$1919=B124)*('EFETIVO 11.05.2026'!I$2:I$1919="BARRA DO FURADO"))} -> 0 | E124: {=SUMPRODUCT(ISNUMBER(SEARCH("743",'EFETIVO 11.05.2026'!H$2:H$1919))*('EFETIVO 11.05.2026'!G$2:G$1919="A")*('EFETIVO 11.05.2026'!J$2:J$1919=B124)*('EFETIVO 11.05.2026'!I$2:I$1919="FAZENDA SEVERINA"))} -> 0 | F124: =SUM(C124:E124) -> 7
B125: COMPRAS | C125: {=SUMPRODUCT(ISNUMBER(SEARCH("743",'EFETIVO 11.05.2026'!H$2:H$1919))*('EFETIVO 11.05.2026'!G$2:G$1919="A")*('EFETIVO 11.05.2026'!J$2:J$1919=B125)*('EFETIVO 11.05.2026'!I$2:I$1919="CABIUNAS"))} -> 5 | D125: {=SUMPRODUCT(ISNUMBER(SEARCH("743",'EFETIVO 11.05.2026'!H$2:H$1919))*('EFETIVO 11.05.2026'!G$2:G$1919="A")*('EFETIVO 11.05.2026'!J$2:J$1919=B125)*('EFETIVO 11.05.2026'!I$2:I$1919="BARRA DO FURADO"))} -> 0 | E125: {=SUMPRODUCT(ISNUMBER(SEARCH("743",'EFETIVO 11.05.2026'!H$2:H$1919))*('EFETIVO 11.05.2026'!G$2:G$1919="A")*('EFETIVO 11.05.2026'!J$2:J$1919=B125)*('EFETIVO 11.05.2026'!I$2:I$1919="FAZENDA SEVERINA"))} -> 0 | F125: =SUM(C125:E125) -> 5
B126: SUPRIMENTOS | C126: {=SUMPRODUCT(ISNUMBER(SEARCH("743",'EFETIVO 11.05.2026'!H$2:H$1919))*('EFETIVO 11.05.2026'!G$2:G$1919="A")*('EFETIVO 11.05.2026'!J$2:J$1919=B126)*('EFETIVO 11.05.2026'!I$2:I$1919="CABIUNAS"))} -> 3 | D126: {=SUMPRODUCT(ISNUMBER(SEARCH("743",'EFETIVO 11.05.2026'!H$2:H$1919))*('EFETIVO 11.05.2026'!G$2:G$1919="A")*('EFETIVO 11.05.2026'!J$2:J$1919=B126)*('EFETIVO 11.05.2026'!I$2:I$1919="BARRA DO FURADO"))} -> 0 | E126: {=SUMPRODUCT(ISNUMBER(SEARCH("743",'EFETIVO 11.05.2026'!H$2:H$1919))*('EFETIVO 11.05.2026'!G$2:G$1919="A")*('EFETIVO 11.05.2026'!J$2:J$1919=B126)*('EFETIVO 11.05.2026'!I$2:I$1919="FAZENDA SEVERINA"))} -> 0 | F126: =SUM(C126:E126) -> 3
... B132: ? | C132: {=SUMPRODUCT(ISNUMBER(SEARCH("743",'EFETIVO 11.05.2026'!H$2:H$1919))*('EFETIVO 11.05.2026'!G$2:G$1919="A")*('EFETIVO 11.05.2026'!J$2:J$1919=B132)*('EFETIVO 11.05.2026'!I$2:I$1919="CABIUNAS"))} -> 9 | D132: {=SUMPRODUCT(ISNUMBER(SEARCH("743",'EFETIVO 11.05.2026'!H$2:H$1919))*('EFETIVO 11.05.2026'!G$2:G$1919="A")*('EFETIVO 11.05.2026'!J$2:J$1919=B132)*('EFETIVO 11.05.2026'!I$2:I$1919="BARRA DO FURADO"))} -> 0 | E132: {=SUMPRODUCT(ISNUMBER(SEARCH("743",'EFETIVO 11.05.2026'!H$2:H$1919))*('EFETIVO 11.05.2026'!G$2:G$1919="A")*('EFETIVO 11.05.2026'!J$2:J$1919=B132)*('EFETIVO 11.05.2026'!I$2:I$1919="FAZENDA SEVERINA"))} -> 0 | F132: =SUM(C132:E132) -> 9
B133: TOTAL | C133: =SUM(C115:C132) -> 303 | D133: =SUM(D115:D132) -> 15 | E133: =SUM(E115:E132) -> 1 | F133: =SUM(F115:F132) -> 319

Sheet Análises 736
A1: NORMATEL • Análises Projeto 736
A2: Cálculos dinâmicos sobre EFETIVO 11.05.2026 — Situações (SIT): A=Ativo, D=Desligado, F=Férias, P=INSS, T=Acidente de Trabalho, M=Serviço Militar
B4: 1. Indicadores do Projeto 736
B5: Total de registros (Ativos + Desligados + Afastados) | C5: {=SUMPRODUCT(ISNUMBER(SEARCH("736",'EFETIVO 11.05.2026'!$H$2:$H$1919))*(('EFETIVO 11.05.2026'!$G$2:$G$1919="A")+('EFETIVO 11.05.2026'!$G$2:$G$1919="D")+('EFETIVO 11.05.2026'!$G$2:$G$1919="F")+('EFETIVO 11.05.2026'!$G$2:$G$1919="P")+('EFETIVO 11.05.2026'!$G$2:$G$1919="T")+('EFETIVO 11.05.2026'!$G$2:$G$1919="M")))} -> 614
B6: Ativos (A) | C6: {=SUMPRODUCT(ISNUMBER(SEARCH("736",'EFETIVO 11.05.2026'!$H$2:$H$1919))*('EFETIVO 11.05.2026'!$G$2:$G$1919="A"))} -> 399
B7: Desligados (D) | C7: {=SUMPRODUCT(ISNUMBER(SEARCH("736",'EFETIVO 11.05.2026'!$H$2:$H$1919))*('EFETIVO 11.05.2026'!$G$2:$G$1919="D"))} -> 180
B8: % Turnover (D / Total) | C8: =IFERROR(C7/C5,0) -> 0.29315961
B9: Afastados (F + P + T + M) | C9: {=SUMPRODUCT(ISNUMBER(SEARCH("736",'EFETIVO 11.05.2026'!$H$2:$H$1919))*(('EFETIVO 11.05.2026'!$G$2:$G$1919="F")+('EFETIVO 11.05.2026'!$G$2:$G$1919="P")+('EFETIVO 11.05.2026'!$G$2:$G$1919="T")+('EFETIVO 11.05.2026'!$G$2:$G$1919="M")))} -> 35
B10: Funções distintas com presença | C10: {=SUMPRODUCT(--(C15:C107>0))} -> 88
B12: 2. Headcount por Função (Ativos / Desligados / Afastados)
B14: Função | C14: Ativos | D14: Desligados | E14: % do total ativos | F14: Afastados
B15: AJUDANTE | C15: {=SUMPRODUCT(ISNUMBER(SEARCH("736",'EFETIVO 11.05.2026'!$H$2:$H$1919))*('EFETIVO 11.05.2026'!$G$2:$G$1919="A")*('EFETIVO 11.05.2026'!$C$2:$C$1919=B15))} -> 25 | D15: {=SUMPRODUCT(ISNUMBER(SEARCH("736",'EFETIVO 11.05.2026'!$H$2:$H$1919))*('EFETIVO 11.05.2026'!$G$2:$G$1919="D")*('EFETIVO 11.05.2026'!$C$2:$C$1919=B15))} -> 8 | E15: =IFERROR(C15/$C$6,0) -> 0.062656642 | F15: {=SUMPRODUCT(ISNUMBER(SEARCH("736",'EFETIVO 11.05.2026'!$H$2:$H$1919))*(('EFETIVO 11.05.2026'!$G$2:$G$1919="F")+('EFETIVO 11.05.2026'!$G$2:$G$1919="P")+('EFETIVO 11.05.2026'!$G$2:$G$1919="T")+('EFETIVO 11.05.2026'!$G$2:$G$1919="M"))*('EFETIVO 11.05.2026'!$C$2:$C$1919=B15))} -> 1
B16: ALMOXARIFE | C16: {=SUMPRODUCT(ISNUMBER(SEARCH("736",'EFETIVO 11.05.2026'!$H$2:$H$1919))*('EFETIVO 11.05.2026'!$G$2:$G$1919="A")*('EFETIVO 11.05.2026'!$C$2:$C$1919=B16))} -> 5 | D16: {=SUMPRODUCT(ISNUMBER(SEARCH("736",'EFETIVO 11.05.2026'!$H$2:$H$1919))*('EFETIVO 11.05.2026'!$G$2:$G$1919="D")*('EFETIVO 11.05.2026'!$C$2:$C$1919=B16))} -> 4 | E16: =IFERROR(C16/$C$6,0) -> 0.012531328 | F16: {=SUMPRODUCT(ISNUMBER(SEARCH("736",'EFETIVO 11.05.2026'!$H$2:$H$1919))*(('EFETIVO 11.05.2026'!$G$2:$G$1919="F")+('EFETIVO 11.05.2026'!$G$2:$G$1919="P")+('EFETIVO 11.05.2026'!$G$2:$G$1919="T")+('EFETIVO 11.05.2026'!$G$2:$G$1919="M"))*('EFETIVO 11.05.2026'!$C$2:$C$1919=B16))} -> 0
B17: ANALISTA DE SUPRIMENTOS I | C17: {=SUMPRODUCT(ISNUMBER(SEARCH("736",'EFETIVO 11.05.2026'!$H$2:$H$1919))*('EFETIVO 11.05.2026'!$G$2:$G$1919="A")*('EFETIVO 11.05.2026'!$C$2:$C$1919=B17))} -> 1 | D17: {=SUMPRODUCT(ISNUMBER(SEARCH("736",'EFETIVO 11.05.2026'!$H$2:$H$1919))*('EFETIVO 11.05.2026'!$G$2:$G$1919="D")*('EFETIVO 11.05.2026'!$C$2:$C$1919=B17))} -> 0 | E17: =IFERROR(C17/$C$6,0) -> 0.0025062657 | F17: {=SUMPRODUCT(ISNUMBER(SEARCH("736",'EFETIVO 11.05.2026'!$H$2:$H$1919))*(('EFETIVO 11.05.2026'!$G$2:$G$1919="F")+('EFETIVO 11.05.2026'!$G$2:$G$1919="P")+('EFETIVO 11.05.2026'!$G$2:$G$1919="T")+('EFETIVO 11.05.2026'!$G$2:$G$1919="M"))*('EFETIVO 11.05.2026'!$C$2:$C$1919=B17))} -> 0
B18: ARTIFICE | C18: {=SUMPRODUCT(ISNUMBER(SEARCH("736",'EFETIVO 11.05.2026'!$H$2:$H$1919))*('EFETIVO 11.05.2026'!$G$2:$G$1919="A")*('EFETIVO 11.05.2026'!$C$2:$C$1919=B18))} -> 18 | D18: {=SUMPRODUCT(ISNUMBER(SEARCH("736",'EFETIVO 11.05.2026'!$H$2:$H$1919))*('EFETIVO 11.05.2026'!$G$2:$G$1919="D")*('EFETIVO 11.05.2026'!$C$2:$C$1919=B18))} -> 10 | E18: =IFERROR(C18/$C$6,0) -> 0.045112782 | F18: {=SUMPRODUCT(ISNUMBER(SEARCH("736",'EFETIVO 11.05.2026'!$H$2:$H$1919))*(('EFETIVO 11.05.2026'!$G$2:$G$1919="F")+('EFETIVO 11.05.2026'!$G$2:$G$1919="P")+('EFETIVO 11.05.2026'!$G$2:$G$1919="T")+('EFETIVO 11.05.2026'!$G$2:$G$1919="M"))*('EFETIVO 11.05.2026'!$C$2:$C$1919=B18))} -> 0
B19: ASSISTENTE ADMINISTRATIVO | C19: {=SUMPRODUCT(ISNUMBER(SEARCH("736",'EFETIVO 11.05.2026'!$H$2:$H$1919))*('EFETIVO 11.05.2026'!$G$2:$G$1919="A")*('EFETIVO 11.05.2026'!$C$2:$C$1919=B19))} -> 11 | D19: {=SUMPRODUCT(ISNUMBER(SEARCH("736",'EFETIVO 11.05.2026'!$H$2:$H$1919))*('EFETIVO 11.05.2026'!$G$2:$G$1919="D")*('EFETIVO 11.05.2026'!$C$2:$C$1919=B19))} -> 3 | E19: =IFERROR(C19/$C$6,0) -> 0.027568922 | F19: {=SUMPRODUCT(ISNUMBER(SEARCH("736",'EFETIVO 11.05.2026'!$H$2:$H$1919))*(('EFETIVO 11.05.2026'!$G$2:$G$1919="F")+('EFETIVO 11.05.2026'!$G$2:$G$1919="P")+('EFETIVO 11.05.2026'!$G$2:$G$1919="T")+('EFETIVO 11.05.2026'!$G$2:$G$1919="M"))*('EFETIVO 11.05.2026'!$C$2:$C$1919=B19))} -> 0
B20: AUXILIAR ADMINISTRATIVO | C20: {=SUMPRODUCT(ISNUMBER(SEARCH("736",'EFETIVO 11.05.2026'!$H$2:$H$1919))*('EFETIVO 11.05.2026'!$G$2:$G$1919="A")*('EFETIVO 11.05.2026'!$C$2:$C$1919=B20))} -> 1 | D20: {=SUMPRODUCT(ISNUMBER(SEARCH("736",'EFETIVO 11.05.2026'!$H$2:$H$1919))*('EFETIVO 11.05.2026'!$G$2:$G$1919="D")*('EFETIVO 11.05.2026'!$C$2:$C$1919=B20))} -> 2 | E20: =IFERROR(C20/$C$6,0) -> 0.0025062657 | F20: {=SUMPRODUCT(ISNUMBER(SEARCH("736",'EFETIVO 11.05.2026'!$H$2:$H$1919))*(('EFETIVO 11.05.2026'!$G$2:$G$1919="F")+('EFETIVO 11.05.2026'!$G$2:$G$1919="P")+('EFETIVO 11.05.2026'!$G$2:$G$1919="T")+('EFETIVO 11.05.2026'!$G$2:$G$1919="M"))*('EFETIVO 11.05.2026'!$C$2:$C$1919=B20))} -> 0
B21: AUXILIAR DE ALMOXARIFE | C21: {=SUMPRODUCT(ISNUMBER(SEARCH("736",'EFETIVO 11.05.2026'!$H$2:$H$1919))*('EFETIVO 11.05.2026'!$G$2:$G$1919="A")*('EFETIVO 11.05.2026'!$C$2:$C$1919=B21))} -> 1 | D21: {=SUMPRODUCT(ISNUMBER(SEARCH("736",'EFETIVO 11.05.2026'!$H$2:$H$1919))*('EFETIVO 11.05.2026'!$G$2:$G$1919="D")*('EFETIVO 11.05.2026'!$C$2:$C$1919=B21))} -> 1 | E21: =IFERROR(C21/$C$6,0) -> 0.0025062657 | F21: {=SUMPRODUCT(ISNUMBER(SEARCH("736",'EFETIVO 11.05.2026'!$H$2:$H$1919))*(('EFETIVO 11.05.2026'!$G$2:$G$1919="F")+('EFETIVO 11.05.2026'!$G$2:$G$1919="P")+('EFETIVO 11.05.2026'!$G$2:$G$1919="T")+('EFETIVO 11.05.2026'!$G$2:$G$1919="M"))*('EFETIVO 11.05.2026'!$C$2:$C$1919=B21))} -> 0
B22: AUXILIAR DE JARDINAGEM | C22: {=SUMPRODUCT(ISNUMBER(SEARCH("736",'EFETIVO 11.05.2026'!$H$2:$H$1919))*('EFETIVO 11.05.2026'!$G$2:$G$1919="A")*('EFETIVO 11.05.2026'!$C$2:$C$1919=B22))} -> 9 | D22: {=SUMPRODUCT(ISNUMBER(SEARCH("736",'EFETIVO 11.05.2026'!$H$2:$H$1919))*('EFETIVO 11.05.2026'!$G$2:$G$1919="D")*('EFETIVO 11.05.2026'!$C$2:$C$1919=B22))} -> 4 | E22: =IFERROR(C22/$C$6,0) -> 0.022556391 | F22: {=SUMPRODUCT(ISNUMBER(SEARCH("736",'EFETIVO 11.05.2026'!$H$2:$H$1919))*(('EFETIVO 11.05.2026'!$G$2:$G$1919="F")+('EFETIVO 11.05.2026'!$G$2:$G$1919="P")+('EFETIVO 11.05.2026'!$G$2:$G$1919="T")+('EFETIVO 11.05.2026'!$G$2:$G$1919="M"))*('EFETIVO 11.05.2026'!$C$2:$C$1919=B22))} -> 1
B23: AUXILIAR DE MANUTENCAO | C23: {=SUMPRODUCT(ISNUMBER(SEARCH("736",'EFETIVO 11.05.2026'!$H$2:$H$1919))*('EFETIVO 11.05.2026'!$G$2:$G$1919="A")*('EFETIVO 11.05.2026'!$C$2:$C$1919=B23))} -> 30 | D23: {=SUMPRODUCT(ISNUMBER(SEARCH("736",'EFETIVO 11.05.2026'!$H$2:$H$1919))*('EFETIVO 11.05.2026'!$G$2:$G$1919="D")*('EFETIVO 11.05.2026'!$C$2:$C$1919=B23))} -> 14 | E23: =IFERROR(C23/$C$6,0) -> 0.07518797 | F23: {=SUMPRODUCT(ISNUMBER(SEARCH("736",'EFETIVO 11.05.2026'!$H$2:$H$1919))*(('EFETIVO 11.05.2026'!$G$2:$G$1919="F")+('EFETIVO 11.05.2026'!$G$2:$G$1919="P")+('EFETIVO 11.05.2026'!$G$2:$G$1919="T")+('EFETIVO 11.05.2026'!$G$2:$G$1919="M"))*('EFETIVO 11.05.2026'!$C$2:$C$1919=B23))} -> 1
B24: AUXILIAR DE PINTURA | C24: {=SUMPRODUCT(ISNUMBER(SEARCH("736",'EFETIVO 11.05.2026'!$H$2:$H$1919))*('EFETIVO 11.05.2026'!$G$2:$G$1919="A")*('EFETIVO 11.05.2026'!$C$2:$C$1919=B24))} -> 4 | D24: {=SUMPRODUCT(ISNUMBER(SEARCH("736",'EFETIVO 11.05.2026'!$H$2:$H$1919))*('EFETIVO 11.05.2026'!$G$2:$G$1919="D")*('EFETIVO 11.05.2026'!$C$2:$C$1919=B24))} -> 1 | E24: =IFERROR(C24/$C$6,0) -> 0.010025063 | F24: {=SUMPRODUCT(ISNUMBER(SEARCH("736",'EFETIVO 11.05.2026'!$H$2:$H$1919))*(('EFETIVO 11.05.2026'!$G$2:$G$1919="F")+('EFETIVO 11.05.2026'!$G$2:$G$1919="P")+('EFETIVO 11.05.2026'!$G$2:$G$1919="T")+('EFETIVO 11.05.2026'!$G$2:$G$1919="M"))*('EFETIVO 11.05.2026'!$C$2:$C$1919=B24))} -> 0
